Workbook

Sheet Sheet5
A3: Row Labels | B3: Count of discounted_price | C3: Count of actual_price
A4: Car&Motorbike | B4: 1 | C4: 1
A5: Computers&Accessories | B5: 453 | C5: 453
A6: Electronics | B6: 526 | C6: 526
A7: Health&PersonalCare | B7: 1 | C7: 1
A8: Home&Kitchen | B8: 448 | C8: 448
A9: HomeImprovement | B9: 2 | C9: 2
A10: MusicalInstruments | B10: 2 | C10: 2
A11: OfficeProducts | B11: 31 | C11: 31
A12: Toys&Games | B12: 1 | C12: 1
A13: (blank)
A14: Grand Total | B14: 1465 | C14: 1465

Sheet Sheet1
A1: product_id | B1: product_id | C1: product_name | D1: category | E1: discounted_price | F1: actual_price | G1: discount_percentage | H1: rating | I1: rating_count | J1: about_product | K1: user_id | L1: user_name | M1: user_count | N1: review_id | O1: review_title | P1: review_content | Q1: img_link | R1: product_link
A2: =LEFT(B2,LEN(B2)-1) -> B07JW9H4J | B2: B07JW9H4J1 | C2: =CONCATENATE(Sheet2!B2,Sheet2!C2) -> WayonaNylon | D2: Computers&Accessories | E2: $399 | F2: $1,099 | G2: 0.64 | H2: 4.2 | I2: 24269 | J2: High Compatibility : Compatible With iPhone 12, 11, X/XsMax/Xr ,iPhone 8/8 Plus,iPhone 7/7 Plus,iPhone 6s/6s Plus,iPhone 6/6 Plus,iPhone 5/5s/5c/se,iPad Pro,iPad Air 1/2,iPad mini 1/2/3,iPod nano7,iPod touch and more apple devices.|Fast Charge&Data Sync : It can charge and sync simultaneously at a rapid speed, Compatible with any charging adaptor, multi-port charging station or power bank.|Durability : Durable nylon braided design with premium aluminum housing and toughened nylon fiber wound tightly around the cord lending it superior durability and adding a bit to its flexibility.|High Security Level : It is designed to fully protect your device from damaging excessive current.Copper core thick+Multilayer shielding, Anti-interference, Protective circuit equipment.|WARRANTY: 12 months warranty and friendly customer services, ensures the long-time enjoyment of your purchase. If you meet any question or problem, please don't hesitate to contact us. | K2: AG3D6O4STAQKAY2UVGEUV46KN35Q,AHMY5CWJMMK5BJRBBSNLYT3ONILA,AHCTC6ULH4XB6YHDY6PCH2R772LQ,AGYHHIERNXKA6P5T7CZLXKVPT7IQ,AG4OGOFWXJZTQ2HKYIOCOY3KXF2Q,AENGU523SXMOS7JPDTW52PNNVWGQ,AEQJHCVTNINBS4FKTBGQRQTGTE5Q,AFC3FFC5PKFF5PMA52S3VCHOZ5FQ | L2: =CONCATENATE(Sheet4!B2,Sheet4!C2) -> ManavAdarsh gupta | M2: =COUNTA(Sheet4!B2:K2) -> 8 | N2: R3HXWT0LRP0NMF,R2AJM3LFTLZHFO,R6AQJGUP6P86,R1KD19VHEDV0OR,R3C02RMYQMK6FC,R39GQRVBUZBWGY,R2K9EDOE15QIRJ,R3OI7YT648TL8I | O2: Satisfied,Charging is really fast,Value for money,Product review,Good quality,Good product,Good Product,As of now seems good | P2: Looks durable Charging is fine tooNo complains,Charging is really fast, good product.,Till now satisfied with the quality.,This is a good product . The charging speed is slower than the original iPhone cable,Good quality, would recommend,https://m.media-amazon.com/images/W/WEBP_402378-T1/images/I/81---F1ZgHL._SY88.jpg,Product had worked well till date and was having no issue.Cable is also sturdy enough...Have asked for replacement and company is doing the same...,Value for money | Q2: https://m.media-amazon.com/images/W/WEBP_402378-T1/images/I/51UsScvHQNL._SX300_SY300_QL70_FMwebp_.jpg | R2: https://www.amazon.in/Wayona-Braided-WN3LG1-Syncing-Charging/dp/B07JW9H4J1/ref=sr_1_1?qid=1672909124&s=electronics&sr=1-1
A3: =LEFT(B3,LEN(B3)-1) -> B098NS6PV | B3: B098NS6PVG | C3: =CONCATENATE(Sheet2!B3,Sheet2!C3) -> AmbraneUnbreakable | D3: Computers&Accessories | E3: $199 | F3: $349 | G3: 0.43 | H3: 4 | I3: 43994 | J3: Compatible with all Type C enabled devices, be it an android smartphone (Mi, Samsung, Oppo, Vivo, Realme, OnePlus, etc), tablet, laptop (Macbook, Chromebook, etc)|Supports Quick Charging (2.0/3.0)|Unbreakable â€“ Made of special braided outer with rugged interior bindings, it is ultra-durable cable that wonâ€™t be affected by daily rough usage|Ideal Length â€“ It has ideal length of 1.5 meters which is neither too short like your typical 1meter cable or too long like a 2meters cable|Supports maximum 3A fast charging and 480 Mbps data transfer speed|6 months manufacturer warranty from the date of purchase | K3: AECPFYFQVRUWC3KGNLJIOREFP5LQ,AGYYVPDD7YG7FYNBXNGXZJT525AQ,AHONIZU3ICIEHQIGQ6R2VFRSBXOQ,AFPHD2CRPDZMWMBL7WXRSVYWS5JA,AEZ346GX3HJ4O4XNRPHCNHXQURMQ,AEPSWFPNECKO34PUC7I56ITGXR6Q,AHWVEHR5DYLVFTO2KF3IZATFQSWQ,AH4QT33M55677I7ISQOAKEQWACYQ | L3: =CONCATENATE(Sheet4!B3,Sheet4!C3) -> ArdKnNirbhay kumar | M3: =COUNTA(Sheet4!B3:K3) -> 8 | N3: RGIQEG07R9HS2,R1SMWZQ86XIN8U,R2J3Y1WL29GWDE,RYGGS0M09S3KY,R17KQRUTAN5DKS,R3AAQGS6HP2QUK,R1HDNOG6TO2CCA,R3PHKXYA5AFEOU | O3: A Good Braided Cable for Your Type C Device,Good quality product from ambrane,Super cable,As,Good quality,Good product,its good,Good quality for the price but one issue with my unit | P3: I ordered this cable to connect my phone to Android Auto of car. The cable is really strong and the connection ports are really well made. I already has a Micro USB cable from Ambrane and it's still in good shape. I connected my phone to the car using the cable and it got connected well and no issues. I also connected it to the charging port and yes it has Fast Charging support.,It quality is good at this price and the main thing is that i didn't ever thought that this cable will be so long it's good one and charging power is too good and also supports fast charging,Value for money, with extra lengthðŸ‘,Good, working fine,Product quality is good,Good,very good,Bought for my daughter's old phone.Brand new cable it was not charging, I already repacked and requested for replacement.I checked again, and there was some green colour paste/fungus inside the micro USB connector. I cleaned with an alcoholic and starts working again.Checked the ampere of charging speed got around 1400ma-1500ma - not bad, came with braided 1.5m long cable, pretty impressive for the price.Can't blame the manufacturer.But quality issues by the distributor, they might have stored in very humid place. | Q3: https://m.media-amazon.com/images/W/WEBP_402378-T2/images/I/31zOsqQOAOL._SY445_SX342_QL70_FMwebp_.jpg | R3: https://www.amazon.in/Ambrane-Unbreakable-Charging-Braided-Cable/dp/B098NS6PVG/ref=sr_1_2?qid=1672909124&s=electronics&sr=1-2
A4: =LEFT(B4,LEN(B4)-1) -> B096MSW6C | B4: B096MSW6CT | C4: =CONCATENATE(Sheet2!B4,Sheet2!C4) -> SounceFast | D4: Computers&Accessories | E4: $199 | F4: $1,899 | G4: 0.9 | H4: 3.9 | I4: 7928 | J4: ã€ Fast Charger& Data Syncã€‘-With built-in safety proctections and four-core copper wires promote maximum signal quality and strength and enhance charging & data transfer speed with up to 480 mb/s transferring speed.|ã€ Compatibilityã€‘-Compatible with iPhone 13, 12,11, X, 8, 7, 6, 5, iPad Air, Pro, Mini & iOS devices.|ã€ Sturdy & Durableã€‘-The jacket and enforced connector made of TPE and premium copper, are resistant to repeatedly bending and coiling.|ã€ Ultra High Qualityã€‘: According to the experimental results, the fishbone design can accept at least 20,000 bending and insertion tests for extra protection and durability. Upgraded 3D aluminum connector and exclusive laser welding technology, which to ensure the metal part won't break and also have a tighter connection which fits well even with a protective case on and will never loose connection.|ã€ Good After Sales Serviceã€‘-Our friendly and reliable customer service will respond to you within 24 hours ! you can purchase with confidence,and every sale includes a 365-day worry-free Service to prove the importance we set on quality. | K4: AGU3BBQ2V2DDAMOAKGFAWDDQ6QHA,AESFLDV2PT363T2AQLWQOWZ4N3OA,AHTPQRIMGUD4BYR5YIHBH3CCGEFQ,AEUVWXYP5LT7PZLLZENEO2NODPBQ,AHC7MPW55DOO6WNCOQVA2VHOD26A,AFDI6FRPFBTNBG7BAEB7JDJSMKDQ,AFQKCEEEKXCOHTDG4WUN3XPPHJQQ,AHKUUFNMBZIDLSSPA4FEHIO2EC7Q | L4: =CONCATENATE(Sheet4!B4,Sheet4!C4) -> KunalHimanshu | M4: =COUNTA(Sheet4!B4:K4) -> 8 | N4: R3J3EQQ9TZI5ZJ,R3E7WBGK7ID0KV,RWU79XKQ6I1QF,R25X4TBMPY91LX,R27OK7G99VK0TR,R207CYDCHJJTCJ,R3PCU8XMU173BT,R1IMONDOWRNU5V | O4: Good speed for earlier versions,Good Product,Working good,Good for the price,Good,Worth for money,Working nice,it's a really nice product | P4: Not quite durable and sturdy,https://m.media-amazon.com/images/W/WEBP_402378-T1/images/I/71rIggrbUCL._SY88.jpg,Working good,https://m.media-amazon.com/images/W/WEBP_402378-T1/images/I/61bKp9YO6wL._SY88.jpg,Product,Very nice product,Working well,It's a really nice product | Q4: https://m.media-amazon.com/images/W/WEBP_402378-T1/images/I/31IvNJZnmdL._SY445_SX342_QL70_FMwebp_.jpg | R4: https://www.amazon.in/Sounce-iPhone-Charging-Compatible-Devices/dp/B096MSW6CT/ref=sr_1_3?qid=1672909124&s=electronics&sr=1-3
A5: =LEFT(B5,LEN(B5)-1) -> B08HDJ86N | B5: B08HDJ86NZ | C5: =CONCATENATE(Sheet2!B5,Sheet2!C5) -> boAtDeuce | D5: Computers&Accessories | E5: $329 | F5: $699 | G5: 0.53 | H5: 4.2 | I5: 94363 | J5: The boAt Deuce USB 300 2 in 1 cable is compatible with smartphones, tablets, PC peripherals, Bluetooth speakers, power banks and all other devices with Type-C as well as Micro USB port|It ensures 3A fast charging and data transmissions with rapid sync at 480 mbps|The premium Nylon braided skin makes it sturdy and invincible against external damage|Its Aluminium alloy shell housing makes it last longer with 10000+ Bends Lifespan with extended frame protection for strain relief|The resilient and flexible design offers a tangle free experience seamlessly|Deuce USB 300 cable offers a perfect 1.5 meters in length for smooth & hassle-free user experience|2 years warranty from the date of purchase | K5: AEWAZDZZJLQUYVOVGBEUKSLXHQ5A,AG5HTSFRRE6NL3M5SGCUQBP7YSCA,AH725ST5NW2Y4JZPKUNTIJCUK2BA,AHV3TXIFCJPMS4D5JATCEUR266MQ,AGWIGDEMFIIUAOXYY2QATNBSUGHA,AFSTSLQUV4EVEXWKBOLEFHL2H5YQ,AGAKDNBHY2FKX7I4ACRGILU7QL7A,AFNWJUWJRHCC6HN52KMG5AKZY37Q | L5: =CONCATENATE(Sheet4!B5,Sheet4!C5) -> Omkar dhaleJD | M5: =COUNTA(Sheet4!B5:K5) -> 8 | N5: R3EEUZKKK9J36I,R3HJVYCLYOY554,REDECAZ7AMPQC,R1CLH2ULIVG5U3,R2DMKIBGFKBD6R,RC89B5IAJUTR5,R3B3DDON5FH8DS,R13WAEJDI5RS36 | O5: Good product,Good one,Nice,Really nice product,Very first time change,Good,Fine product but could be better,Very nice it's charging like jet | P5: Good product,long wire,Charges good,Nice,I bought this cable for Rs.339 worthy product for this price, i tested it in various charger adapters 33w and 18w it supports fast charging as well.,Good,Ok,I had got this at good price on sale on Amazon and product is useful with warranty but for warranty you need to go very far not practical for such a cost and mine micro to type c connector stopped working after few days only.,I like this product | Q5: https://m.media-amazon.com/images/I/41V5FtEWPkL._SX300_SY300_QL70_FMwebp_.jpg | R5: https://www.amazon.in/Deuce-300-Resistant-Tangle-Free-Transmission/dp/B08HDJ86NZ/ref=sr_1_4?qid=1672909124&s=electronics&sr=1-4
A6: =LEFT(B6,LEN(B6)-1) -> B08CF3B7N | B6: B08CF3B7N1 | C6: =CONCATENATE(Sheet2!B6,Sheet2!C6) -> PortronicsKonnect | D6: Computers&Accessories | E6: $154 | F6: $399 | G6: 0.61 | H6: 4.2 | I6: 16905 | J6: [CHARGE & SYNC FUNCTION]- This cable comes with charging & Data sync function|[HIGH QUALITY MATERIAL]- TPE + Nylon Material to make sure that the life of the cable is enhanced significantly|[LONG CORD]- The Cable is extra thick 1.2 meter long, optimized for an easy use for your comfort at home or office|[MORE DURABLE]-This cable is unique interms of design and multi-use and is positioned to provide the best comfort and performance while using|[UNIVERSAL COMPATIBILITY]- Compatible with all devices like iPhone XS, X, XR, 8, 7, 6S, 6, 5S, iPad Pro, iPad mini and iPad Air | K6: AE3Q6KSUK5P75D5HFYHCRAOLODSA,AFUGIFH5ZAFXRDSZHM4QB2KPKFUQ,AFK4NJOLFSJGWLOJIUIAROJF6YVA,AFUOTYRFUXVPEBGIXVZZ7DR3CZUA,AFDLRSXKDZ6U3U3KD46SQLFGZQRA,AH5VLM66SIK7J3IRG4NY7XVOQ55A,AE3MQNNHHLUHXURL5S7IAR7JTGNQ,AFSEOFZY67MYC7UAJU264Z5NFTLA | L6: =CONCATENATE(Sheet4!B6,Sheet4!C6) -> rahuls6099Swasat Borah | M6: =COUNTA(Sheet4!B6:K6) -> 8 | N6: R1BP4L2HH9TFUP,R16PVJEXKV6QZS,R2UPDB81N66T4P,R3KK4GT934ST3I,RCFHMWUSBIJO,RDO7DACXMAJ84,R3A6MEZL3LY66Z,R1ESIEKPGAYA29 | O6: As good as original,Decent,Good one for secondary use,Best quality,GOOD,Amazing product at a mind blowing price!,Nice Quality,Good product | P6: Bought this instead of original apple, does the work for 150rs, not as fast as apple charger but its a good option if you want cheap and good product, bought it for iPad pro 10.5 and it's working flawlessly, build quality is ok, its not like i am gonna hang my clothes on it and i want a very strong cable, even a braided cable stop working after a year, i have used both Anker and Apple store strong braided cable they all stop working after a year so please don't buy high end cables just for that instead choose a this one and even if it's stops working withing a year you only loose 150rs compares to 2000rs.UPDATE------------------------------------pin has stopped charging from one side, now i have to slip the pin to charge from other side, but i will update and let know for how long does it work,,Itâ€™s good. Not sure about durability as the pin area feels a bit fragile,Does not support apple carplaySo was little disappointed about thatOther than that cable is made up of very good quality,Best to buy,100% NOT FATHFUL,Writing this review post 10 months and 3 orders of the same product.Honestly Portronics Konnect L lightning cable works like magic with the original Apple charging brick.Seeing the price of the cable I initially hesitated buying as it was as low as â‚¹99/- with the offers and so I wasnâ€™t sure if it would work well with my iPhone 12 or whether it would impact my iPhoneâ€™s battery health because all the other lightning cable brands were costing over â‚¹350/- like Wayona, Amazon Basics, etc.Earlier I was using Wayona Brand lightning cable with eventually frayed and stopped working.Charging Speed:Charges my iPhone fast enough almost similar compared to the original cable level when used with 12W Original Apple power adapter.Quality and Durability:Great quality braided cable and doesnâ€™t tangle easily and can withstand day-to-day usage.L-Shaped pin:This is very innovative by Portronics and it makes sure the cable doesnâ€™t get damaged even if used while charging.CarPlay and Data Sync:Works smoothly with CarPlay and syncs data effortlessly.PS: I have used this cable only with the Original Apple Charging Brick and extremely satisfied with its performance.,Better than I expect the product I like that Quality and I plan to buy same type cable come with usb C to Lighting cable for emergency purpose that much I love this cable. Buy for this cable only emergency uses only since Good one,Good product and value for money | Q6: https://m.media-amazon.com/images/W/WEBP_402378-T2/images/I/31VzNhhqifL._SX300_SY300_QL70_FMwebp_.jpg | R6: https://www.amazon.in/Portronics-Konnect-POR-1080-Charging-Function/dp/B08CF3B7N1/ref=sr_1_5?qid=1672909124&s=electronics&sr=1-5
A7: =LEFT(B7,LEN(B7)-1) -> B08Y1TFSP | B7: B08Y1TFSP6 | C7: =CONCATENATE(Sheet2!B7,Sheet2!C7) -> pTronSolero | D7: Computers&Accessories | E7: $149 | F7: $1,000 | G7: 0.85 | H7: 3.9 | I7: 24871 | J7: Fast Charging & Data Sync: Solero TB301 Type-C cable supports fast charge up to 5V/3A for devices and data syncing speed up to 480Mbps.|Universal Compatibility: This USB charging cable connects USB Type-C devices with standard USB devices like laptops, hard drives, power banks, wall and car chargers, etc..Connector One: Reversible Type C|Connector Two: USB A Type|Rough & Tough Type-C Cable: Charging cable with a double-braided exterior, premium aramid fiber core and metal plugs. It has passed 10,000 bending tests and can easily withstand daily use.|Extended Length: 1.5-meter long c-type cable uses nylon material to protect the wire and avoid knots.|Perfect Fit Connectors: pTron Soler USB-C has passed the 5KG load test, swing test, 5000+ times connect & disconnect to ensure that there are no loose connections. | K7: AEQ2YMXSZWEOHK2EHTNLOS56YTZQ,AGRVINWECNY7323CWFXZYYIZOFTQ,AHBAT6VLOXWGYDL57KHCNCLPXAKA,AF7NDY2H6JVYTSQOZP76GCATQ34Q,AFV7ZA733ZLME4KNLZPMPCBUNPPA,AHFAAPSY2MJ5HYOU2VQDJ7AQY4NQ,AH2WGV2PEBUTICRPBEEVKF24G5LA,AEP4MK3EKOBDKTGPJTRN5RBDIODA | L7: =CONCATENATE(Sheet4!B7,Sheet4!C7) -> JayeshRajesh k. | M7: =COUNTA(Sheet4!B7:K7) -> 9 | N7: R7S8ANNSDPR40,R3CLZFLHVJU26P,RFF7U7MPQFUGR,R1MV1NKC23DWPI,R11D3U0V2XKDKF,R18MP1KLUE18PC,RWGJNVEH5ZQME,R1XN72FU6Q37IH | O7: It's pretty good,Average quality,very good and useful usb cable,Good USB cable. My experience was very good it is long lasting,Good,Nice product and useful,-,Sturdy but does not support 33w charging | P7: It's a good product.,Like,Very good item strong and useful USB cableValue for moneyThanks to amazon and producer,https://m.media-amazon.com/images/I/51112ZRE-1L._SY88.jpg,Good,Nice product and useful product,-,Sturdy but does not support 33w charging | Q7: https://m.media-amazon.com/images/I/31wOPjcSxlL._SX300_SY300_QL70_FMwebp_.jpg | R7: https://www.amazon.in/Solero-TB301-Charging-480Mbps-1-5-Meter/dp/B08Y1TFSP6/ref=sr_1_6?qid=1672909124&s=electronics&sr=1-6
A8: =LEFT(B8,LEN(B8)-1) -> B08WRWPM2 | B8: B08WRWPM22 | C8: =CONCATENATE(Sheet2!B8,Sheet2!C8) -> boAtMicro | D8: Computers&Accessories | E8: $176.63 | F8: $499 | G8: 0.65 | H8: 4.1 | I8: 15188 | J8: It Ensures High Speed Transmission And Charging By Offering 3A Fast Charging And Data Transmissions With Rapid Sync At 480 Mbps|The Braided Skin Makes It Durable And Invincible Against External Damage So You Can Have An Absolute Hassle-Free & Tangle Free Experience|Its Durable Pvc Housing And The Flexible Design Makes It Last 6 Times Longer Than Other Cables|Usb Cable Offers A Perfect 1.5 Meters In Length For Smooth & Hassle-Free User Experience For Superior Charging & Data Transfer Tasks|The Compact And Smooth Aluminium Connector Fits Most Cases Seamlessly And Resists Corrosion For Signal Purity|Micro Usb 55 Cable Offers Universal Compatibility As It Is Compatible With Most Android Smartphones, Tablets, Pc Peripherals, Bluetooth Speakers, Power Banks, Game Consoles & All Micro-Usb Enabled Devices|2 years warranty from the date of purchase | K8: AG7C6DAADCTRQJG2BRS3RIKDT52Q,AFU7BOMPVJ7Q3TTA4G67RASTGYIQ,AER5ZGIXXVYG3AWZTRZT7M2BYCEA,AHE76XQSOLGOP5ZEKTIW6KUPDWBQ,AGXTMB2XHZBEWZ2UIX7ODZ4XTU6Q,AHNM2XVU745EDPNGUOAG74PTSNRA,AH5RWQ4S72IVLZD6O75OPCFIVDXQ,AG322TYKVPLPBDXE7ABEUK5QTALQ | L8: =CONCATENATE(Sheet4!B8,Sheet4!C8) -> Vivek kumarAmazon Customer | M8: =COUNTA(Sheet4!B8:K8) -> 8 | N8: R8E73K2KWJRDS,RSD0JTIIWQQL8,R64CRSTE9SLW1,R2FRTNIIUFJE1F,RWGNX3W7UOJ7W,R32TYHHODHTF5D,RQL9ZMQUTY7P2,R280XJ5VZUBOXV | O8: Long durable.,good,Does not charge Lenovo m8 tab,Best charging cable,good,Boat,Product was good,1.5 m à¤•à¤¾ à¤•à¥‡à¤¬à¤² à¤®à¥‡à¤°à¥‡ à¤²à¤¿à¤ à¤¬à¤¹à¥à¤¤ à¤¹à¥€ à¤²à¤¾à¤­à¤¦à¤¾à¤¯à¤• à¤¹à¥ˆ à¥¤ | P8: Build quality is good and it is comes with 2 year warranty.,Good Product,Bought it for charging my mobile & tab but it doesn't work for Lenovo m8 tab,Guys this cable is is best compare of everyone over heat protection, quickly charging, but chance to shock circuit,good,Nice,Good quality,1.5à¤à¤® à¤•à¤¾ à¤¡à¤¾à¤Ÿà¤¾ à¤•à¥‡à¤¬à¤² à¤®à¥‡à¤°à¥‡ à¤²à¤¿à¤ à¤¬à¤¹à¥à¤¤ à¤¹à¥€ à¤²à¤¾à¤­à¤¦à¤¾à¤¯à¤• à¤¹à¥ˆ à¥¤ à¤®à¥ˆà¤‚ à¤‡à¤¸ à¤•à¥‡à¤¬à¤² à¤•à¥‹ à¤²à¤¾à¤‡à¤¨ à¤®à¥‡à¤‚ à¤šà¤¾à¤°à¥à¤œ à¤•à¤°à¤¤à¥‡ à¤¸à¤®à¤¯ à¤«à¥‹à¤¨ à¤¬à¤¹à¥à¤¤ à¤†à¤°à¤¾à¤® à¤¸à¥‡ à¤‰à¤ªà¤¯à¥‹à¤— à¤•à¤° à¤ªà¤¾ à¤°à¤¹à¤¾ à¤¹à¥ à¥¤ à¤†à¤ª à¤‡à¤¸ à¤•à¥‡à¤¬à¤² à¤¸à¥‡ 15watt à¤•à¤¾ à¤šà¤¾à¤°à¥à¤œà¤° à¤‰à¤¸à¥‡ à¤•à¤° à¤¸à¤•à¤¤à¥‡ à¤¹à¥ˆ (à¤‡à¤¸à¤¸à¥‡ à¤œà¤¡à¤¼à¤¾ à¤¨à¤¹à¥€) à¥¤ à¤²à¥‹à¤•à¤² à¤¬à¤¾à¤œà¤¾à¤° à¤®à¥‡à¤‚ à¤‡à¤¸à¤•à¤¾ à¤¦à¤¾à¤® 150 à¤¹à¥ˆ , à¤…à¤®à¥‡à¤œà¤¨ à¤ªà¥‡ à¤¯à¥‡ à¤•à¥‡à¤¬à¤² à¤®à¥à¤à¥‡ 67 à¤®à¥‡à¤‚ à¤®à¤¿à¤²à¤¾ à¥¤ à¤—à¤°à¥à¤µ à¤¸à¥‡ à¤•à¤¹à¥‹ à¤¹à¤® à¤¹à¤¿à¤‚à¤¦à¥‚ à¤¹à¥ˆ , à¤œà¤¯ à¤¹à¤¿à¤‚à¤¦ à¤œà¤¯ à¤­à¤¾à¤°à¤¤ , | Q8: https://m.media-amazon.com/images/W/WEBP_402378-T2/images/I/41jlwEZpa5L._SX300_SY300_QL70_FMwebp_.jpg | R8: https://www.amazon.in/boAt-Micro-USB-Tangle-Free-Transmission/dp/B08WRWPM22/ref=sr_1_8?qid=1672909124&s=electronics&sr=1-8
A9: =LEFT(B9,LEN(B9)-1) -> B08DDRGWT | B9: B08DDRGWTJ | C9: =CONCATENATE(Sheet2!B9,Sheet2!C9) -> MIUsb | D9: Computers&Accessories | E9: $229 | F9: $299 | G9: 0.23 | H9: 4.3 | I9: 30411 | J9: 1m long Type-C USB Cable|Sturdy and Durable. With USB cable you can transfer data with speeds of upto 480 Mbps|Upto 3A output|6months warranty|Sturdy and Durable. With USB cable you can transfer data with speeds of upto 480 Mbps|6months warranty|Up To 3A Output | K9: AHW6E5LQ2BDYOIVLAJGDH45J5V5Q,AF74RSGCHPZITVFSZN76K6GKPICA,AHDD7ZNB47QA2JLYU53HD4ML3VNQ,AHV3ELGDSOWBYUQLXSPDCSHBQRHQ,AEJU4L3ZM2GTILSJZZSNSF6VUOIA,AFVD66VQMSHPDT3A6HBBBGKRXBZA,AELKHQXVSSG6NHXLFJLLNEFRQQUQ,AGYSMAC6V6RFJJOHG2FIRPOZ6CSQ | L9: =CONCATENATE(Sheet4!B9,Sheet4!C9) -> Pavan A HJayesh bagad | M9: =COUNTA(Sheet4!B9:K9) -> 8 | N9: R2X090D1YHACKR,R32ZCIH9AFNJ60,R3N57EVVG0EHAF,R3QWLE8JHROKC1,R2VTSDOOUTSQ5X,R3E6FZ75Q074KH,R1SYBQLTPFCW20,RYQT96J8HPIXE | O9: Worth for money - suitable for Android auto,Good Product,Length,Nice,Original,Very good quay Cable support fast charging.,Original MI cable for charging upto 33 watt,I am veri happy with this product as it provide turbo charging. | P9: Worth for money - suitable for Android auto... my purpose served in car....got it for Rs.150,Everything is Okay. But packaging is not good feeling like seller gave is used cable.,Good product,Good product but cost is more.,Original cable,I bought this cable at 129. Using this cable for Android auto in my car. Perfectly works without any glitch.,Original MI cable. Will charge upto 33 watts. Got it for Rs 150. I have 67 watt charger and I want a cable for my car so I went for it. I checked the performance with battery charging app. The charging speed is exactly half of my 67 watt original cable. Go for it.,It provided me turbo charging. I recommend for all Redmi note 10s mobile phones. As it provide turbo charging. I am veri happy with this product. | Q9: https://m.media-amazon.com/images/I/31XO-wfGGGL._SX300_SY300_QL70_FMwebp_.jpg | R9: https://www.amazon.in/MI-MTCY001IN-USB-Type-C-Cable/dp/B08DDRGWTJ/ref=sr_1_9?qid=1672909124&s=electronics&sr=1-9
A10: =LEFT(B10,LEN(B10)-1) -> B008IFXQF | B10: B008IFXQFU | C10: =CONCATENATE(Sheet2!B10,Sheet2!C10) -> TP-LinkUSB | D10: Computers&Accessories | E10: $499 | F10: $999 | G10: 0.5 | H10: 4.2 | I10: 1,79,691 | J10: USB WiFi Adapter â€”â€” Speedy wireless transmission at up to 150Mbps ideal for video streaming or internet calls|Mini Design â€”â€” Sleek miniature design so small that once plugged in, can be left in a Laptopâ€™s USB port|Advanced Security â€”â€” Supports 64/128 WEP, WPA, PA2/WPA-PSK/WPA2-PSK(TKIP/AES)|Compatibility â€”â€” Windows 11/10/8.1/8/7/XP, Mac OS 10.15 and earlier, Linux|Easy Setup â€”â€” Connect in no time with easy setup utility in 14 languages|In an unlikely case of product quality related issue, we may ask you to reach out to brandâ€™s customer service support and seek resolution. We will require brand proof of issue to process replacement request | K10: AGV3IEFANZCKECFGUM42MRH5FNOA,AEBO7NWCNXKT4AESAN443HQH35FQ,AE7GD3VRRYQEAHDR7FXJIR23INYA,AHPAW24BI5X2GCX5M2LHI72VSJJQ,AE2VXY4CFO36MDSIMPG43XHNF4GA,AHHQEKUNVETALN7DTRHUQ2WAWEKQ,AFMIFTNTUD5PIHGONWOTRMMZ5EBA,AHOJBIZVVIIFJKRREY4B6ESVA4KA | L10: =CONCATENATE(Sheet4!B10,Sheet4!C10) -> Azhar JuManAnirudh Sood | M10: =COUNTA(Sheet4!B10:K10) -> 8 | N10: R1LW6NWSVTVZ2H,R3VR5WFKUS15C5,R2F6GC79OYWUKQ,R3QZ19MECGWG9A,R2MPU42MYK7GPO,R33DVXFB4VYPZZ,R1SQ7OGFR4JRUR,R1S5F9QI0M1VBZ | O10: Works on linux for me. Get the model with antenna.,Does what it say but other brands available at lesser price,Easy Handle,Great product,Perfect working,Speed is perfect,Great Design, Build, Connectivity Range, Packaging and other features but no linux support since v2,Very good | P10: I use this to connect an old PC to internet. I tried lubuntu 20 and ubuntu 22, it worked out of the box in both, didn't have to do any setup. There's an extender cable so you can place this in a comfortable place. Get the model with antenna because otherwise you'll have range problems if you're not directly in line of sight from your wifi router.,The wifi dongle is a simple plug & play device, will start catching available networks right after you plug it into your USB port, no additional installations/ softwares requires. Signal strength is good.... just wonder what would be different in other adapters of lesser known brands which are available at a much more competitive pricing, hence a star less.,Pros:*Easy to use & Portable*Can be connected to Mobile Hotspot and used in PC( Budget Friendly)*Less installation process*No heating issues & Good Coverage*Best alternative for USB Tethering (phone's battery may get damaged for long term run with Tethering)Cons:*Internet connection speed varies at times, also depends on your modem or cellular connection*Issues occur while installing via CD, which is available along with the product( Installation driver can be downloaded from TP-Link site)*Needed to reconnect the adapter every time system is turned ON*Will not work if your software has some issues, so encountered any just update your system(worked for me)*Support Center is worse, calls are unattended most of the times or just visit nearby storeConclusion:Brought this @499/-Ideal for users who don't need very high speed internet usage,a good alternative for USB Tethering and are on Budge(1080p Youtube videos can be easily played with this without any interruptions),wifi connectivity is a great good result for me. however, some jitter problems did exist.,This is perfect device to connect wifi. Go for it.,This wifi adopter is good working,(Pictures attached)Size/Design: â˜… â˜… â˜… â˜… â˜…Build Quality: â˜… â˜… â˜… â˜… â˜…Packaging: â˜… â˜… â˜… â˜… â˜…Software: â˜… â˜… â˜… â˜…Speed: â˜… â˜… â˜… â˜… â˜…Connectivity: â˜… â˜… â˜… â˜… â˜…Experience: â˜… â˜… â˜… â˜… â˜…Warranty: â˜… â˜… â˜… â˜… â˜…Size and Design:The best part about this is that it is very compact in size and very sober and elegant in design. This is a big plus as it is easy plug in and use, add to it the good sober design.Build Quality:The build quality is undoubtedly superb. Just no qualms about that, at all. When held, it doesnt give off that cheap and flimsy product-like feeling. It is good sturdy with its build quality.Packaging:This part is also a big plus as the item was well cushioned and packaged with all the necessary items that ensured that no damage could have been caused to the product during transportation. This ensures that I as a customer have received something not damaged internally already.Software:This is actually good but not great part with the product.The good part is that a CD has been provided with it along with a manual.The not great part is that NO LINUX SUPPORT has been given from Version 2 onwards. This is bad, really.Speed:It easily supports net speeds upto 300 Mbps. Practically speaking, I have tested it at my home and it easily supports net speed of over 100-150 Mbps without a sigh.On testing I found that it did connect to 5GHz network, without any issue.Connectivity:Please mark its not feet its metres. Multiply metres x 3 to get the distance in feet.It easily connects to my laptop or phone from 7 metres across one room. So thats 21 feet. I mean even our old bluetooth used to connect to about 15 ft.So 20-25 feet is not at all an issue with this. This is the big plus I found with the product.Experience:From this point of view, so far except the linux non-compatibility issue, I found no other flaws with this product.So overall its a great product.Warranty:Its 3 years so I am assured that atleast for 3 years I am tension-free and not just 1 year, contrary to most electronic items today that only provide 1 year warranty with their items.,Best adapter I have bought ever. Works nicely seemless connectivity | Q10: https://m.media-amazon.com/images/W/WEBP_402378-T2/images/I/31e6ElWRymL._SX300_SY300_QL70_FMwebp_.jpg | R10: https://www.amazon.in/TP-Link-TL-WN725N-150Mbps-Wireless-Adapter/dp/B008IFXQFU/ref=sr_1_10?qid=1672909124&s=electronics&sr=1-10
A11: =LEFT(B11,LEN(B11)-1) -> B082LZGK3 | B11: B082LZGK39 | C11: =CONCATENATE(Sheet2!B11,Sheet2!C11) -> AmbraneUnbreakable | D11: Computers&Accessories | E11: $199 | F11: $299 | G11: 0.33 | H11: 4 | I11: 43994 | J11: Universal Compatibility â€“ It is compatible with all Micro USB enabled devices, be it an android smartphone, tablet, PC peripheral or any other micro USB compatible device|Unbreakable â€“ Made of special braided outer with rugged interior bindings, it is ultra-durable cable that wonâ€™t be affected by daily rough usage|Ideal Length â€“ It has ideal length of 1.5 meters which is neither too short like your typical 1meter cable or too long like a 2meters cable|Supports maximum 3A fast charging and 480 Mbps data transfer speed|6 Months manufacturer warranty from the date of purchase. | K11: AECPFYFQVRUWC3KGNLJIOREFP5LQ,AGYYVPDD7YG7FYNBXNGXZJT525AQ,AHONIZU3ICIEHQIGQ6R2VFRSBXOQ,AFPHD2CRPDZMWMBL7WXRSVYWS5JA,AEZ346GX3HJ4O4XNRPHCNHXQURMQ,AEPSWFPNECKO34PUC7I56ITGXR6Q,AHWVEHR5DYLVFTO2KF3IZATFQSWQ,AH4QT33M55677I7ISQOAKEQWACYQ | L11: =CONCATENATE(Sheet4!B11,Sheet4!C11) -> ArdKnNirbhay kumar | M11: =COUNTA(Sheet4!B11:K11) -> 8 | N11: RGIQEG07R9HS2,R1SMWZQ86XIN8U,R2J3Y1WL29GWDE,RYGGS0M09S3KY,R17KQRUTAN5DKS,R3AAQGS6HP2QUK,R1HDNOG6TO2CCA,R3PHKXYA5AFEOU | O11: A Good Braided Cable for Your Type C Device,Good quality product from ambrane,Super cable,As,Good quality,Good product,its good,Good quality for the price but one issue with my unit | P11: I ordered this cable to connect my phone to Android Auto of car. The cable is really strong and the connection ports are really well made. I already has a Micro USB cable from Ambrane and it's still in good shape. I connected my phone to the car using the cable and it got connected well and no issues. I also connected it to the charging port and yes it has Fast Charging support.,It quality is good at this price and the main thing is that i didn't ever thought that this cable will be so long it's good one and charging power is too good and also supports fast charging,Value for money, with extra lengthðŸ‘,Good, working fine,Product quality is good,Good,very good,Bought for my daughter's old phone.Brand new cable it was not charging, I already repacked and requested for replacement.I checked again, and there was some green colour paste/fungus inside the micro USB connector. I cleaned with an alcoholic and starts working again.Checked the ampere of charging speed got around 1400ma-1500ma - not bad, came with braided 1.5m long cable, pretty impressive for the price.Can't blame the manufacturer.But quality issues by the distributor, they might have stored in very humid place. | Q11: https://m.media-amazon.com/images/W/WEBP_402378-T2/images/I/31kj3q4SepL._SY445_SX342_QL70_FMwebp_.jpg | R11: https://www.amazon.in/Ambrane-Unbreakable-Charging-Braided-Android/dp/B082LZGK39/ref=sr_1_11?qid=1672909124&s=electronics&sr=1-11
A12: =LEFT(B12,LEN(B12)-1) -> B08CF3D7Q | B12: B08CF3D7QR | C12: =CONCATENATE(Sheet2!B12,Sheet2!C12) -> PortronicsKonnect | D12: Computers&Accessories | E12: $154 | F12: $339 | G12: 0.55 | H12: 4.3 | I12: 13391 | J12: [CHARGE & SYNC FUNCTION]- This cable comes with charging & Data sync function for smartphones|[HIGH QUALITY MATERIAL]- TPE + Nylon Material to make sure that the life of the cable is enhanced significantly|[LONG CORD]- The Cable is extra thick 1.2 meter long, optimized for an easy use for your comfort at home or office|[MORE DURABLE]-This cable is unique interms of design and multi-use and is positioned to provide the best comfort and performance while using | K12: AGYLPKPZHVYKKZHOTHCTYVEDAJ4A,AGTTU64JMX722LYCN3SOWLFPKPAQ,AFWD4ZTM7473CDWARHCDQKK73MTA,AEXCQM3FDLX3YL3UJWWUIAIUJT4A,AHUKYUWRUVRTB3IQGISXWTSPAWLQ,AFWW4UEXAJH7EAB5LTMKMSGLUN2Q,AFM5JL37WY7G6MLQUI4WAXUJME7Q,AFECO24WYFOU2KL7C3DMHTEHRU7Q | L12: =CONCATENATE(Sheet4!B12,Sheet4!C12) -> TanyaAnu | M12: =COUNTA(Sheet4!B12:K12) -> 8 | N12: R11MQS7WD9C3I0,R2AKH69XQY8BY4,R8GBOLYUN5UP6,R1AYVO4R25KJTA,R1HT6XM787V7FV,R339XJL1GMKHA3,R175VFSB2A32HG,R35T9LXYBSP09G | O12: Good for fast charge but not for data transfer,Good cable compares to local the brand.,good but doesnt last,Good product,Good Product,Good and worth it,very good material quality charging speed is 15 watt,Not a fast charger | P12: The cable is efficient in fast charging but in quick data transfer. Overall fine.,I like the usb c L shape. Nylon Shielded core wire it improves the life of the cable.,i think i buy these every 6 months or so. fast charging stops working after a while. probbly something to do with the cable design. the cable gets twisted over time and I suspect that breaks the high capacity wires inside. but i keep buying it because there arent too many options in an L shaped design,Good and durable product. Sometime the charges doesn't work on few adapters. there might be few cut off or something but works fine on apple adapter, Car charger, USB,The product is really good at affordable price.,Good and fast charging, and value for money,à®ªà¯Šà®°à¯à®³à¯ à®‰à®Ÿà¯ˆà®¯ à®•à®Ÿà®¿à®©à®¤à¯à®¤à®©à¯à®®à¯ˆà®¯à®¿à®©à¯ à®¨à®©à¯à®±à®¾à®• à®‰à®³à¯à®³à®¤à¯ à®šà®¾à®°à¯à®œà¯ à®à®±à¯à®®à¯ à®µà¯‡à®•à®®à¯ 15wat,Not a fast charger. Very slow charging with 65w. L-shape pin is very useful. | Q12: https://m.media-amazon.com/images/I/31dJ+lXJq3L._SY300_SX300_.jpg | R12: https://www.amazon.in/Portronics-POR-1081-Charging-1-2Meter-Function/dp/B08CF3D7QR/ref=sr_1_12?qid=1672909124&s=electronics&sr=1-12
A13: =LEFT(B13,LEN(B13)-1) -> B0789LZTC | B13: B0789LZTCJ | C13: =CONCATENATE(Sheet2!B13,Sheet2!C13) -> boAtRugged | D13: Computers&Accessories | E13: $299 | F13: $799 | G13: 0.63 | H13: 4.2 | I13: 94363 | J13: The boAt rugged cable features our special toughest polyethylene braided jacket and this unique jacket provides greater protection than anything else you have seen in its class. Round Cable|Extra tough polyethylene terephthalate cable skin ensures 10000 plus bend lifespan, stress and stretch resistance|The boAt rugged Micro USB cable is compatible with most android smartphones, windows phone, tablets, PC peripherals and other micro USB compatible devices|2.4A rapid charge, fast data transmission and rapid speed to sync your device at the speed up to 480mbps|boAt rugged micro USB cable offers a perfect 1.5 meters in length, optimized for an easy use for your comfort at home or office|2 years warranty from the date of purchase | K13: AEWAZDZZJLQUYVOVGBEUKSLXHQ5A,AG5HTSFRRE6NL3M5SGCUQBP7YSCA,AH725ST5NW2Y4JZPKUNTIJCUK2BA,AHV3TXIFCJPMS4D5JATCEUR266MQ,AGWIGDEMFIIUAOXYY2QATNBSUGHA,AFSTSLQUV4EVEXWKBOLEFHL2H5YQ,AGAKDNBHY2FKX7I4ACRGILU7QL7A,AFNWJUWJRHCC6HN52KMG5AKZY37Q | L13: =CONCATENATE(Sheet4!B13,Sheet4!C13) -> Omkar dhaleJD | M13: =COUNTA(Sheet4!B13:K13) -> 8 | N13: R3EEUZKKK9J36I,R3HJVYCLYOY554,REDECAZ7AMPQC,R1CLH2ULIVG5U3,R2DMKIBGFKBD6R,RC89B5IAJUTR5,R3B3DDON5FH8DS,R13WAEJDI5RS36 | O13: Good product,Good one,Nice,Really nice product,Very first time change,Good,Fine product but could be better,Very nice it's charging like jet | P13: Good product,long wire,Charges good,Nice,I bought this cable for Rs.339 worthy product for this price, i tested it in various charger adapters 33w and 18w it supports fast charging as well.,Good,Ok,I had got this at good price on sale on Amazon and product is useful with warranty but for warranty you need to go very far not practical for such a cost and mine micro to type c connector stopped working after few days only.,I like this product | Q13: https://m.media-amazon.com/images/I/41SDfuK7L2L._SX300_SY300_QL70_FMwebp_.jpg | R13: https://www.amazon.in/Rugged-Extra-Tough-Unbreakable-Braided/dp/B0789LZTCJ/ref=sr_1_13?qid=1672909124&s=electronics&sr=1-13
A14: =LEFT(B14,LEN(B14)-1) -> B07KSMBL2 | B14: B07KSMBL2H | C14: =CONCATENATE(Sheet2!B14,Sheet2!C14) -> AmazonBasicsFlexible | D14: Electronics | E14: $219 | F14: $700 | G14: 0.69 | H14: 4.4 | I14: 4,26,973 | J14: Flexible, lightweight HDMI cable for connecting media devices to playback display such as HDTVs, projectors, and more|Compatible with Blu-Ray players, computers, Apple TV, Roku, cable, PS4, Xbox One, and other HDMI-compatible devices|Solid copper conductors and full metal jacket shielding for durability and high-performance connectivity|Supports Ethernet, 3D, 4K video and Audio Return Channel (ARC) and meets the latest HDMI standards|Supports bandwidth up to 18Gbps and is backwards compatible with earlier versions|Includes a 3 foot cable | K14: AEYJ5I6JZZPOJB6MGWRQOHRQLPSQ,AFY5TVFOMVHGBPBTIJODYDQRZM5Q,AE3O6366WGEQAANKJ76QETTUQQTQ,AEQIJCPWSBCDKUO5VROXXHWX3PPA,AGVIAQK2HQ47P7UVXHW2NBAEU7YQ,AE3D5CJ2GDUP5SQ3AAYMVAGDTX7A,AH77IQRYD54XCRMCO7XEAIAYCLPA,AEA2HQHMFG3ZGJFOLLJQ65WKIZUQ | L14: =CONCATENATE(Sheet4!B14,Sheet4!C14) -> Rishav GossainShashank Mallamraju | M14: =COUNTA(Sheet4!B14:K14) -> 8 | N14: R1FKOKZ3HHKJBZ,R2WNMZI1EXTA0H,RCA1M3W4RIXUR,R3BKCLL6D7ZLIX,REVSR0ILY3547,R15W5KMQB95IV5,R10PB68FRUHT5V,R3TLCE9JSBU3UP | O14: It's quite good and value for money,Works well,Hdmi cable,Value for money,All good,Gets the job done,Delivery was good,This one was my need to purchase | P14: I am using it for 14 days now. The experience is pretty good as of now. Picture quality is also not bad. Don't expect something out of the world at this price point. But you can go for it if you have a tight budget.,Initial impressions: works as said, glad I didnâ€™t go for cheaper options (not that itâ€™s too costly) just plug and play. Will update if it screws up,The hdmi cable is good to watch movie,sports and its gives better quality while connecting your laptop with TV and play ðŸŽ®.I loved it,Works as expected. Length of the cable is short and it was mentioned also satisfied my requirement. If you need more length better look other options.,All good,It's the best HDMI cable at this price range. No problems yet. Just go for it !!,I was expecting this to be delivered on time and it was delivered on time.Product is good as i have tried other cables and wires from Amazon basica brand.,Good one | Q14: https://m.media-amazon.com/images/I/41nPYaWA+ML._SY300_SX300_.jpg | R14: https://www.amazon.in/AmazonBasics-Flexible-HDMI-Cable-3-Foot/dp/B07KSMBL2H/ref=sr_1_14?qid=1672909124&s=electronics&sr=1-14
A15: =LEFT(B15,LEN(B15)-1) -> B085DTN6R | B15: B085DTN6R2 | C15: =CONCATENATE(Sheet2!B15,Sheet2!C15) -> PortronicsKonnect | D15: Computers&Accessories | E15: $350 | F15: $899 | G15: 0.61 | H15: 4.2 | I15: 2262 | J15: [20W PD FAST CHARGING]-Itâ€™s supports 20W PD quick charge protocol, charge up to 50% in around 30 minutes. It is ideal for charging your USB type c enabled devices at maximum speed|[USB-C to 8 Pin Cable]- Itâ€™s offer rapid charging and syncing between USB Type-C and 8 Pin enabled devices. Safe charging at up to 3A is ensured by high-standard components|[MORE DURABLE]- This cable is unique interms of design and multi-use and is positioned to provide the best comfort and performance while using|[FLEXIBLE CORD]- The Cable uses nylon Braided + Metal Housing material to make sure that the life of the cable is enhanced significantly. It is 4mm extra thick slim 1.2meter long|[UNIVERSAL COMPATIBILITY]-Charge for all Type C USB connectivity devices including MacBook 12 inch, Nexus 5x, Nexus 6p, OnePlus 2, pixel c, Lumia 950, Lumia 950 xl, Nokia n1, etc | K15: AGUAYQHARAKR2VZTRP276KAGETKQ,AFKTST2773VUOKUHE7FCR6QCAURQ,AEGLHOQOWUUUQEDV6EWXTSHIUE7A,AEHQYGI5L4FFALBMC5XMT5KXSZCA,AHJFXFGDAXEHIG2ZLUWVMZ3LWPBA,AEP4CW3UI7AJ7XM7PAAKVCB6U3ZA,AHIWCPCQ2Z4HWEM7V4HGTLVZQM6Q,AHT4JDEYWRIQGCA2WAQJ6E2POHCQ | L15: =CONCATENATE(Sheet4!B15,Sheet4!C15) -> PriyaMansi | M15: =COUNTA(Sheet4!B15:K15) -> 8 | N15: R1QETDIPRCX4S0,RARQYQ8POOFA9,R952F931MCOR5,R3LLDHV3WXED9C,R282YHZ5A4GMY4,R34W3B1C7RP98Q,R1467F9VL3DLSY,R3KLQRR1UM44JG | O15: Works,Nice Product,Fast Charging as original,Good for data transfer,Average. Cost effective,Good quality,Great Product,Nice | P15: Definitely isnâ€™t as good as the original cord but works. Fast charging and pretty sturdy,Worth it,So I had a faulty cable. I was lazy and have a lot of money so instead of calling Apple I bought this for like 300 bucks. Didnâ€™t expected much but for my surprise, this cable actually works and has fast charging. JUST GO FOR IT,Felt quite sturdy, the connectors look premium and were easy to insert. I used this cable to switch all my data from iphone 7 to an m30s. Cable worked like charm while using smart switch app, all my data including whatsapp data was transferred successfully. Satisfied with performance.,Just good,Quality is very goodWorking smoothly.. using same portronics pd charger,This is a real fast charging cable that is serving the purpose,Very good | Q15: https://m.media-amazon.com/images/I/31J6qGhAL9L._SX300_SY300_QL70_FMwebp_.jpg | R15: https://www.amazon.in/Portronics-Konnect-Delivery-Support-Braided/dp/B085DTN6R2/ref=sr_1_15?qid=1672909124&s=electronics&sr=1-15
A16: =LEFT(B16,LEN(B16)-1) -> B09KLVMZ3 | B16: B09KLVMZ3B | C16: =CONCATENATE(Sheet2!B16,Sheet2!C16) -> PortronicsKonnect | D16: Computers&Accessories | E16: $159 | F16: $399 | G16: 0.6 | H16: 4.1 | I16: 4768 | J16: [CHARGE & SYNC FUNCTION]- This cable comes with charging & Data sync function|[HIGH QUALITY MATERIAL]- TPE + Nylon Material to make sure that the life of the cable is enhanced significantly|[LONG CORD]- The Cable is extra thick 1.2 meter long, optimized for an easy use for your comfort at home or office|[MORE DURABLE]-This cable is unique interms of design and multi-use and is positioned to provide the best comfort and performance while using|[UNIVERSAL COMPATIBILITY]- Compatible with all devices like iPhone XS, X, XR, 8, 7, 6S, 6, 5S, iPad Pro, iPad mini and iPad Air | K16: AF2XXVO7JUBUVAOBTJ3MNH4DGUFQ,AH6VDJLLPBXKCWXMLBKMBCQ2ESGA,AE642RIGZIT2VPQJOLNUZ34QVWJQ,AFLHNKQH5UQZU3ATISKSMRE2KEDQ,AF2L4MCRCIDOOREQJN7QPQ4QBZCA,AGKLZ4SUHAU47KJXDVHBBEWJODUA,AHESCOYXLCXB56F4JO45X4CZQCYA,AGGHDE6KFZHEDUDJBD5R27AYMEWA | L16: =CONCATENATE(Sheet4!B16,Sheet4!C16) -> Deepaak Singhsiva k. | M16: =COUNTA(Sheet4!B16:K16) -> 8 | N16: R20XIOU25HEX80,R2X55FA2EEUEYM,R393Z224NBTDLN,R3Q4ZCHWSAQD5B,R1AE3A4NSVM9SC,R2U1YAAZE07I1V,R36NVL58WQ7D64,R1E7GPZ569TBIZ | O16: Great but,Worked well for 6 six months thatâ€™s it,Compatible with Apple iPad 2nd generation and charging very well.,CABLE,The product is good but the phone gets disconnected at multiple occasions.,Not a fast charging cable,Good item. Value,Amazing product and value for money | P16: Loosing charging cable of apple is costly affair. This wire was great purchase made to correct it,Worked well for six months thatâ€™s it, now itâ€™s stopped working, now planning to buy one more because the price has come down to 150,Very good product. Compatible with iPad 2nd generation and charging very well. Quality of the product is very good and also works fine. Totally worth for its price.,Product is super,I'm using from last 6 month. Till now it was good functioning. Now I noticed phone gets disconnected at multiple occasions. might be cable may be damaged.Overall worked well for 6 month.,Takes 5-6 hours to charge full.,Good item. Value,It is the best product I have used till now. | Q16: https://m.media-amazon.com/images/W/WEBP_402378-T2/images/I/41R08zLK69L._SX300_SY300_QL70_FMwebp_.jpg | R16: https://www.amazon.in/Portronics-Konnect-POR-1401-Charging-Function/dp/B09KLVMZ3B/ref=sr_1_16?qid=1672909124&s=electronics&sr=1-16
A17: =LEFT(B17,LEN(B17)-1) -> B083342NK | B17: B083342NKJ | C17: =CONCATENATE(Sheet2!B17,Sheet2!C17) -> MIBraided | D17: Computers&Accessories | E17: $349 | F17: $399 | G17: 0.13 | H17: 4.4 | I17: 18757 | J17: 1M Long Cable. Usb 2.0 (Type A)|Toughened Joints|Strong And Sturdy|Country Of Origin: China|6 Months Warranty | K17: AGSGSRTEZBQY64WO2HKQTV7TWFSA,AEYD5HVYAJ23CR6PTWOOIKUOIDHA,AFRMNW6TDHDZBP2UHF2K3MEAEYUA,AHICHCW6EC3BNV2IDAEAJPBG4HZQ,AGWFKE7RNP6EVC4JFLFSL76EEVVQ,AGEOQQHGNELZNEUKJAJUA7NTPBLA,AFS3QBSOMCE2FAZFUYZ3NBFQDLMQ,AGJYG6ZWCWD74WNE6Y37XZ2VUSMA | L17: =CONCATENATE(Sheet4!B17,Sheet4!C17) -> Birendra ku DashAditya Gupta | M17: =COUNTA(Sheet4!B17:K17) -> 8 | N17: R2JPQNKCOE10UK,RQI80JG2WZXNF,R2LYZ4CUWPMUJN,R1ZBD2ZB2ZYEWX,R2ITEDC9KOCY3N,R1115HIQP3BKKJ,R31OMS6DNMI7M,R2DCFXQMUNO93L | O17: Good product,using this product 8months It is done I have not faced any problem so far, its build quality best,I really liked this one.,Very strong and support fast charging ,,Nice cable,Best data cable charging fast,Good job,Good but need some improvement | P17: I like it ðŸ‘ðŸ‘,Best charging power . I used this cable on note 8 pro mi. Using 8month also fast working.,350 might be a little expensive but physically itâ€™s so good. Feels premium. But power limitation is there it is not suitable for fast charging.,,https://m.media-amazon.com/images/W/WEBP_402378-T1/images/I/61WnvIUaIwL._SY88.jpg,Best data cable charging fast,Very good quality and good durability,Overall good but need some improvement... | Q17: https://m.media-amazon.com/images/W/WEBP_402378-T1/images/I/31gaP7qpBNL._SX300_SY300_QL70_FMwebp_.jpg | R17: https://www.amazon.in/Mi-Braided-USB-Type-C-Cable/dp/B083342NKJ/ref=sr_1_17?qid=1672909124&s=electronics&sr=1-17
A18: =LEFT(B18,LEN(B18)-1) -> B0B6F7LX4 | B18: B0B6F7LX4C | C18: =CONCATENATE(Sheet2!B18,Sheet2!C18) -> MI80 | D18: Electronics | E18: $13,999 | F18: $24,999 | G18: 0.44 | H18: 4.2 | I18: 32840 | J18: Note : The brands, Mi and Xiaomi, are part of the same multinational conglomerate|Resolution : HD Ready (1366 x 768) Resolution | Refresh Rate : 60 Hertz | 178 Degree wide viewing angle|Connectivity: Dual Band Wi-Fi | 2 HDMI ports to connect latest gaming consoles, set top box, Blu-ray Players | 2 USB ports to connect hard drives and other USB devices | ALLM | ARC | Bluetooth 5.0 | Ethernet|Sound: 20 Watts Output | Dolby Audio, DTS Virtual: X, DTS-HD|Smart TV Features : Android TV 11 | PatchWall | IMDb Integration | Universal Search | 300+ Free Live Channels | Kids Mode with Parental lock | Smart Recommendations | Language Universe â€“ 15+ Languages | User Centre | Okay Google | Chromecast suporting Apps : Netflix, Prime Video, Disney+ Hotstar | 5000+ apps from Play Store |Quad core Cortex A35 | Chromecast built-in | Ok Google | Auto Low Latency Mode | 1GB RAM + 8GB Storage|Display: HD Ready | Vivid Picture Engine|Warranty Information: 1 year comprehensive warranty on product and 1 year additional on Panel provided by the brand from the date of purchase | K18: AHEVOQADJSSRX7DS325HSFLMP7VQ,AG7XYZRCSKX6G2OLO7DVZWIZ3PUQ,AE2THTCCQLBIUSWPF4CPXC6GGP7Q,AHUJZOV34DFEN55QQ5XOYKVKHV6Q,AELX4DI77ZHURZTDLYFU7XMP7R6Q,AE2ODWBBOBD2SITDDIEJ644OSRFQ,AFLW4WXYQ3G6HU5LBQORDDZO3FOQ,AGGRC2P6M43GDEWCAHGYAILCSKTQ | L18: =CONCATENATE(Sheet4!B18,Sheet4!C18) -> Manoj maddheshiyaManoj Kumar Sahoo | M18: =COUNTA(Sheet4!B18:K18) -> 8 | N18: R13UTIA6KOF6QV,R2UGDZSGFF01K7,RHHIZ45VYU5X6,R14N9HBE5EIUY0,R2WMW096T9Y0OU,R1SHIIE6M72825,R22P6BE9DBME4F,R2TEINENXTIHT2 | O18: It is the best tv if you are getting it in 10-12k,Good price but the OS lags,GARBAGE QUALITY,Good product.,Good quality,Great experience everything is fantastic ðŸ¤ ,Super picture quality and sound quality,Awesome | P18: Pros- xiomi 5a is best in budget-Nice picture quality-Very nice audio output- Full of featureCONS- sometimes tv lags-Sometimes stucksIn this prize range all tv having cons like this.::Overall nice tv,The product in this price range is good but as it is running in Android 12 it lags. I hope after few updates the lags problem will be resolved,Useless product and useless quality. Display issues within 7 months and service center is not upto the mark. Go for better brands where quality is assured. I would wish if there was option of negative stars.,Uses as connectes TV the picture is very good. I was hopping a best level of song. Globaly it is a good product.,https://m.media-amazon.com/images/I/61spXDbojZL._SY88.jpg,Greater then ever,Good quality,Good ðŸ‘ | Q18: https://m.media-amazon.com/images/I/51fmHk3km+L._SX300_SY300_.jpg | R18: https://www.amazon.in/MI-inches-Ready-Android-L32M7-5AIN/dp/B0B6F7LX4C/ref=sr_1_18?qid=1672909124&s=electronics&sr=1-18
A19: =LEFT(B19,LEN(B19)-1) -> B082LSVT4 | B19: B082LSVT4B | C19: =CONCATENATE(Sheet2!B19,Sheet2!C19) -> AmbraneUnbreakable | D19: Computers&Accessories | E19: $249 | F19: $399 | G19: 0.38 | H19: 4 | I19: 43994 | J19: Compatible with all Type C enabled devices, be it an android smartphone (Mi, Samsung, Oppo, Vivo, Realme, OnePlus, etc), tablet, laptop (Macbook, Chromebook, etc)|Unbreakable â€“ Made of special braided outer with rugged interior bindings, it is ultra-durable cable that wonâ€™t be affected by daily rough usage|Ideal Length â€“ It has ideal length of 1.5 meters which is neither too short like your typical 1meter cable or too long like a 2meters cable|Supports maximum 3A fast charging and 480 Mbps data transfer speed|6 months manufacturer warranty from the date of purchase | K19: AECPFYFQVRUWC3KGNLJIOREFP5LQ,AGYYVPDD7YG7FYNBXNGXZJT525AQ,AHONIZU3ICIEHQIGQ6R2VFRSBXOQ,AFPHD2CRPDZMWMBL7WXRSVYWS5JA,AEZ346GX3HJ4O4XNRPHCNHXQURMQ,AEPSWFPNECKO34PUC7I56ITGXR6Q,AHWVEHR5DYLVFTO2KF3IZATFQSWQ,AH4QT33M55677I7ISQOAKEQWACYQ | L19: =CONCATENATE(Sheet4!B19,Sheet4!C19) -> ArdKnNirbhay kumar | M19: =COUNTA(Sheet4!B19:K19) -> 8 | N19: RGIQEG07R9HS2,R1SMWZQ86XIN8U,R2J3Y1WL29GWDE,RYGGS0M09S3KY,R17KQRUTAN5DKS,R3AAQGS6HP2QUK,R1HDNOG6TO2CCA,R3PHKXYA5AFEOU | O19: A Good Braided Cable for Your Type C Device,Good quality product from ambrane,Super cable,As,Good quality,Good product,its good,Good quality for the price but one issue with my unit | P19: I ordered this cable to connect my phone to Android Auto of car. The cable is really strong and the connection ports are really well made. I already has a Micro USB cable from Ambrane and it's still in good shape. I connected my phone to the car using the cable and it got connected well and no issues. I also connected it to the charging port and yes it has Fast Charging support.,It quality is good at this price and the main thing is that i didn't ever thought that this cable will be so long it's good one and charging power is too good and also supports fast charging,Value for money, with extra lengthðŸ‘,Good, working fine,Product quality is good,Good,very good,Bought for my daughter's old phone.Brand new cable it was not charging, I already repacked and requested for replacement.I checked again, and there was some green colour paste/fungus inside the micro USB connector. I cleaned with an alcoholic and starts working again.Checked the ampere of charging speed got around 1400ma-1500ma - not bad, came with braided 1.5m long cable, pretty impressive for the price.Can't blame the manufacturer.But quality issues by the distributor, they might have stored in very humid place. | Q19: https://m.media-amazon.com/images/I/41d84o5-M-L._SY445_SX342_QL70_FMwebp_.jpg | R19: https://www.amazon.in/Ambrane-Unbreakable-Charging-Braided-Cable/dp/B082LSVT4B/ref=sr_1_19?qid=1672909124&s=electronics&sr=1-19
A20: =LEFT(B20,LEN(B20)-1) -> B08WRBG3X | B20: B08WRBG3XW | C20: =CONCATENATE(Sheet2!B20,Sheet2!C20) -> boAtType | D20: Computers&Accessories | E20: $199 | F20: $499 | G20: 0.6 | H20: 4.1 | I20: 13045 | J20: Type C A 325 Cable Is Designed With A Perfect 1.5 Meters In Length For Hassle Free Usage|It Dons Premium Braided Skin That Makes It Sturdy And Invincible Against External Damage With 10000+ Bends Lifespan The Cable Stays Stronger And Lasts Longer|Type C A 325 Offers Universal Compatibility With Smartphones, Tablets, Pc Peripherals, Bluetooth Speakers, Power Banks And All Other Devices With Type C Port|The Reversible Metallic Aluminium Tip Lets The User Connect Devices In A Carefree Manner|Its Flexible Design Offers The User A Tangle-Free Experience|2 years warranty from the date of purchase | K20: AFB5KJR4Q5FICAHBOPDPUTB3O7QQ,AHW3QBHDOUMXODZ4EAMHD5JMDIDQ,AGXRGH7DLS3RVFS5KWU4PGR3H3GQ,AFLIHOX2HH7S2OJAD63UAHKMY34Q,AEHBE4U3HD6G2TMSHKE7TNZYOWCA,AFHKIURZM4R62UEXTOCZLI2FPQ6A,AEW6K4E5A4RUWRFFUDINQE5WWBSQ,AG4LMDCRAAKD4U2FZ6B6N75KTHXA | L20: =CONCATENATE(Sheet4!B20,Sheet4!C20) -> Rohan NarkarJAGWINDER SINGH | M20: =COUNTA(Sheet4!B20:K20) -> 8 | N20: R2BP8Y5OJXKJLF,R218813TNRHNSY,R3VIKEVJ5DBF5G,R2PQNCTR8TQCT4,R3FI11UEJC9ZOJ,R3ULCCZZHBNLA4,RELIQ4H7CYX2Q,R3ALQNTJN4ER9N | O20: Good for charging and Data transfer,à¨®à¨œà¨¼à¨¬à©‚à¨¤,Good Quality but less Power Delivery,Fantastic!,Good,Not useful,Doesn't fit properly,Can't support Oppo mobile for fast charging | P20: Check for offera before buying,18w charging cable,,Awesome cable!Charging, data transfer and durability is simply awesome, and there is not a single disconnection issue, which I always faced in original mi cable from box. Bought 1 more time as last cable damaged when phone fell on usb cable port as my phone is heavy and I never faced any issues so i bought one more time and didn't went for replacement as its waste of time and energy, i also have boat earphones that is also awesome..ðŸ˜„,Good,Charging is very slow. Forget about fast charging. Not useful at all,Cable is not fit properly on my samsung galaxy m31 type C port. If little hit happens then cable is plug it out. Otherwise length and cable quality is very nice,Boat type C cable doesn't support fast charging on Oppo F15, earlier i was using Vooc cable, which worked excellent | Q20: https://m.media-amazon.com/images/W/WEBP_402378-T1/images/I/41xwPQLxTML._SX300_SY300_QL70_FMwebp_.jpg | R20: https://www.amazon.in/boAt-A325-Tangle-Free-Charging-Transmission/dp/B08WRBG3XW/ref=sr_1_20?qid=1672909124&s=electronics&sr=1-20
A21: =LEFT(B21,LEN(B21)-1) -> B08DPLCM6 | B21: B08DPLCM6T | C21: =CONCATENATE(Sheet2!B21,Sheet2!C21) -> LG80 | D21: Electronics | E21: $13,490 | F21: $21,990 | G21: 0.39 | H21: 4.3 | I21: 11976 | J21: Resolution: HD Ready (1366x768) | Refresh Rate: 50 hertz|Connectivity: 2 HDMI ports to connect set top box, Blu Ray players, gaming console | 1 USB ports to connect hard drives and other USB devices|Sound output: 10 Watts Output I 2 Speakers | DTS Virtual:X | Sound Type : Down Firing|Smart TV Features: Web OS Smart TV | Wi-Fi | Home Dashboard | Screen Mirroring | Mini TV Browser | Multi-Tasking | Office 365, Set WXHXD (with Stand ) mm - 739 x 472 x 168|Display: Active HDR | Display Type: Flat | BackLight Module: Slim LED|Warranty Information: 1 Year LG India Comprehensive Warranty and additional 1 year Warranty is applicable on panel/module from the date of purchase|Installation : For requesting installation/wall mounting/demo of this product once delivered, please directly call LG support (Please visit LG Website for Toll Free Numebrs) and provide product's model name as well as seller's details mentioned on the invoice | K21: AHBNKB74LGTYUOKPAJBSKNFV45CA,AFIECTV45ADX5YPTE2VU6ORRHTGQ,AFDUJI7KG7VMZF4JGJHV4DBCA4OA,AEUWKSX5ZL7DWOOYVDOWJKBHOVXA,AHEJW5MYVFOQBEXD6BIUBB3PJBPQ,AEM2Y22BKLFYL5BK7SC56Q75ODOQ,AHWDVB4OO4S3YS5RYQZIDBNV6BUQ,AFCEDQXVCB4LUUBWXRJS6KRU62FQ | L21: =CONCATENATE(Sheet4!B21,Sheet4!C21) -> NIRMAL.NManoj kumar | M21: =COUNTA(Sheet4!B21:K21) -> 8 | N21: R2PNR69G0BQG2F,R31A0WWDEYMKEW,R2C4XEWFLVU7JV,RYWES5AT5FQO6,R1PGWAY5TEWLT4,R32542OPR0QC4I,R2JDJEVZ2G7EEK,R36EHHPAQNSSOF | O21: Sound quality,Very nice,Value for money,Good,Good for its price.,Good item,Budget friendly,Good | P21: LG was always Good , correct delivery, good service but sound quality was poor. The speakers were fitted below the tv. No clear sound. That was the only problem.,Good videoGood vice,Picture quality is awesome.,Good at that price,Okay product, the OS has lags after about a year of use. This is the best you can get for the price tag it comes with.,I like it,Best one when it comes to bugdet, easy installation and handy features.,Good | Q21: https://m.media-amazon.com/images/W/WEBP_402378-T2/images/I/51v-2Nzr+ML._SY300_SX300_.jpg | R21: https://www.amazon.in/LG-inches-Ready-Smart-32LM563BPTC/dp/B08DPLCM6T/ref=sr_1_21?qid=1672909124&s=electronics&sr=1-21
A22: =LEFT(B22,LEN(B22)-1) -> B09C6HXFC | B22: B09C6HXFC1 | C22: =CONCATENATE(Sheet2!B22,Sheet2!C22) -> DuracellUSB | D22: Computers&Accessories | E22: $970 | F22: $1,799 | G22: 0.46 | H22: 4.5 | I22: 815 | J22: Supports Ios Devices With Max Output Up To 2.4A|Up To 10, 000+ Bend And 10, 000+ Plugging And Unplugging Test Ensure This Cable A Longer Lifespan|Ensure Fast And Stable Data Transmission Up To 480 Mbps|2 Years Warranty|Compatible Designed To Work Flawlessly With Mfi Or Apple Devices, Iphone, Imac, Ipad Etc|1.2M Tangle Free Durable Tough Braiding Sync & Charge Cable | K22: AFNYIBWKJLJQKY4BGK77ZOTVMORA,AFCTNNMP2LZLY5466YJ5AY3JE5ZA,AG3XBWOAL65DJSBHJ7LQ2K54HJKQ,AF2ZFMLJS4UBCGZO4FMJTEPP6MHA,AFBZMRHC4GXUU7KNAK4OBKORDF6Q,AHSIQL276K7X2UP72QOOOWNVRSXA,AF3D6X5NQWOBOEVVH2Y37N55AKZQ,AFWOTSQXCQJLZ653Y7ACEZADKGYQ | L22: =CONCATENATE(Sheet4!B22,Sheet4!C22) -> Prasannavijayaraghavan G.Preet Sikka | M22: =COUNTA(Sheet4!B22:K22) -> 8 | N22: R12D1BZF9MU8TN,R32MNCWO5LGFCG,RZU3UK8OZKD6X,R3BSTKR3JUW6GY,R1ARVYPXS4XPB7,R1V6GDYE2IBX8O,R28EG2PXZTJL90,R2SQNU7OIOOLHT | O22: Good cable for car,Good substitute for orginal,Better Value for money Product,Way better than the original,Absolutely amazing.,Namm hi kafi hai,Very good,As the names say Durable cell it a durable cable ;-) | P22: I trust this product! Works well with car play!,Very good quality and charging is fine. As good as original,Build quality is awesome, best lightening cable ever seen, better than a official lightening from ï£¿If ur looking for a cable close your eyes and go for it ðŸ”¥ or you can buy a (Amazon basics) one I was using that for past 3 years that a bit a cheaper side, I recommend both these cables had better build quality and value for money,Gr8 product overall,Just loved it, very good charging speed.,,Good quality,it well packed, all sealed coveredthe wire looks of a very good qualityrecommended!!!! | Q22: https://m.media-amazon.com/images/W/WEBP_402378-T1/images/I/41TZJiPRRwL._SX300_SY300_QL70_FMwebp_.jpg | R22: https://www.amazon.in/DURACELL-Lightning-Certified-braided-Devices/dp/B09C6HXFC1/ref=sr_1_22?qid=1672909124&s=electronics&sr=1-22
A23: =LEFT(B23,LEN(B23)-1) -> B085194JF | B23: B085194JFL | C23: =CONCATENATE(Sheet2!B23,Sheet2!C23) -> tizumHDMI | D23: Electronics | E23: $279 | F23: $499 | G23: 0.44 | H23: 3.7 | I23: 10962 | J23: Superior Stability: Built-in advanced Certified AG6200 IC chip converts HDMI digital signal to VGA analog signal. It is NOT a bi-directional converter and cannot transmit signals from VGA to HDMI.|Compact Design: Tizum HDMI to VGA adapter is compact & lightweight which makes it easy to carry, travel friendly and also saves space on your desk helping it keep clutter free.|High Definition Image Quality: The HDMI male to VGA female converter supports resolution up to 1920x1080 60Hz (1080p Full HD) including 720p, 1600x1200, 1280x1024 for high definition monitors & projectors.|Wide Compatibility: The adapter is compatible with Computer, PC, Desktop, Laptop, Notebook, Chromebook, PS3, Xbox, Set Top Box, TV & other devices with HDMI port. Note: Does not Support Audio.|Incredible Performance: It resists corrosion & abrasion; improves signal transmission; & protects HDMI port of your device to ensure a longer lifespan | K23: AEO5FHWNOSFBT554DKQAG4ICBGFQ,AGIQ5Y7Q4MKZ542KKVFZLAIZV6GQ,AFD53TWXXCPJAYQJ7REZPW34AKKQ,AHBMHE56M3IAD7Z4KXUKREAZX3WQ,AFR4YULNFZZC5DJOWH2KNFAOM6BQ,AEP5UMK4KDMGZGBHBLZDB2R37OMA,AHLKQWAPXICPCSCIPIF6C6FOENOQ,AHTBS46SCEBGWK4SUH3FOQEORR3Q | L23: =CONCATENATE(Sheet4!B23,Sheet4!C23) -> aditya d.Paranthaman | M23: =COUNTA(Sheet4!B23:K23) -> 8 | N23: R1GYK05NN6747O,R1J21BZ29NGQF9,R16JCHEILBYOMW,R2WVVS88M7SH18,R2MQ3VB8ZTUS48,RBJPTKHYQ7G7U,R37PKO5FUPJW35,R38R2YC2J2BMWR | O23: Good product ; Average Finishing,Save it purpose well without any issue. I am satisfied,No issues,NO NEED TO PUT AUX CABLE FOR CONNECTING AUDIO FROM SECONDARY MONITOR,Good product,Not so Bad,Good,Worked will for only 3-4 months. | P23: This connector has provided as a boon for my old Samsung LCD monitor and I am proactively using that monitor as the 2nd screen just if the finishing of the product can be improved then it would be a better purchase option.,Save it purpose well without any issue. I am satisfied,Working fine,GO FOR IT,Itâ€™s works properly good product but poor quality,I buy this product after so many reviews. this product is not so much clear. But it get the job done. you can buy to get display only. not so much clear. but still price is very good compare to other products.,Good,It worked really well for 3-4 months but now it started showing its "cheap chinese" side. Display keeps disconnecting randomly and will come back. It's a headache to read/work on external monitor now since it keeps disconnecting the external monitor and then reconnects it. | Q23: https://m.media-amazon.com/images/W/WEBP_402378-T1/images/I/31MIyzg8uzL._SX300_SY300_QL70_FMwebp_.jpg | R23: https://www.amazon.in/Adapter-Projector-Computer-Laptop-Projectors/dp/B085194JFL/ref=sr_1_23?qid=1672909124&s=electronics&sr=1-23
A24: =LEFT(B24,LEN(B24)-1) -> B09F6S8BT | B24: B09F6S8BT6 | C24: =CONCATENATE(Sheet2!B24,Sheet2!C24) -> Samsung80 | D24: Electronics | E24: $13,490 | F24: $22,900 | G24: 0.41 | H24: 4.3 | I24: 16299 | J24: Resolution: HD Ready (1366x768) | Refresh Rate: 60 hertz|Connectivity: 2 HDMI ports to connect set top box, Blu Ray players, gaming console | 1 USB ports to connect hard drives and other USB devices|Sound : 20 Watts Output | Dolby Digital Plus|Smart TV Features : Personal Computer | Screen Share | Music System | Content Guide | Connect Share Movie|Display : LED Panel | Mega Contrast | PurColor | HD Picture Quality | Slim & Stylish Design|Warranty Information: 1 year comprehensive warranty plus additional 1 years on panel by brand from date of invoice|Installation: TV Table stand is not included in the box with this model. customer may ask for Table Top Stand or Wall Mount which will be provided to the customer at the time of installation, please directly call Samsung support on [1800407267864 / 180057267864] and provide product's model name as well as seller's details mentioned on the invoice|Easy Returns: This product is eligible for replacement within 10 days of delivery in case of any product defects, damage or features not matching the description | K24: AHEVO4Q5NM4YXMG2HDDXC5XMBGRQ,AFZPH7ZAWX5VDY3HOBNYRDGIDBVA,AFURD6VVHRG4HZ36KXGXYUTVUDLA,AHJF5BZJNDLXJXSW74ZPLHGO7GUA,AFUS52CHEA75E2YGQ6SYGP3PKBGA,AGS3YC22FW2PCSH3I7ODDXETZ6BA,AGGI2H2AGOIX6IBDJRWULYUP5DPQ,AG4TU4LCQXF2XTLMMGMFTNWL3OOA | L24: =CONCATENATE(Sheet4!B24,Sheet4!C24) -> Rahman AliMARIYA DASS | M24: =COUNTA(Sheet4!B24:K24) -> 8 | N24: R1SN0D4DFBKAZI,R1SX5L77L2CD6V,R1NAZ6M4QBUJMK,R25I5FXOJA76KS,R32V7DQLDSKJ99,R8QWY8HXI120P,R2OZPGGMUCLSC1,R1G4SA1P865EIS | O24: Good,Sound is very low another brand comparing in better,Service provider not meet my home refuse, tv i am not using bad service,Good product,Ok super,Floor stand does not come with it ...,Good,A budget friendly TV with a clumsy UI and Remote | P24: Overall good.,TV picture ok smart betterSound very low another brand,Service provider refuse install my TV, bad service and samsung, I am calling 3 times service provider. Not meet my home address.why ? Bad bad,They product did not come with the support stand or wall hanging hook to install the Tv,Picture quality is very poor in cables,Floor stand does not come with it ... You have to buy it seperately. Request Amazon to cleary mention it in the add . You will have to pay seperate charges for the installation guy to buy the floor mount .,Good, | Q24: https://m.media-amazon.com/images/W/WEBP_402378-T1/images/I/51q3+E64azL._SX300_SY300_.jpg | R24: https://www.amazon.in/Samsung-Inches-Wondertainment-UA32T4340BKXXL-Glossy/dp/B09F6S8BT6/ref=sr_1_24?qid=1672909124&s=electronics&sr=1-24
A25: =LEFT(B25,LEN(B25)-1) -> B09NHVCHS | B25: B09NHVCHS9 | C25: =CONCATENATE(Sheet2!B25,Sheet2!C25) -> FlixMicro | D25: Computers&Accessories | E25: $59 | F25: $199 | G25: 0.7 | H25: 4 | I25: 9378 | J25: Micro usb cable is 1 meter in length, optimized for easy use for your comfort at home or office, helps you to overcome distance restrictions|Durable pvc outer exterior: Pvc cables are versatile, high in tensile strength, flexible, and good conductors|Charge & sync, this usb cable can charge and data sync simultaneously at 480mbps speed, compatible with all devices with a micro usb port. Core : Tinned copper|Micro usb charging cable for android phones and any other device with micro usb port|Contact us on 1800-102-2700 or write us on support@flixaccessories.com | K25: AHIKJUDTVJ4T6DV6IUGFYZ5LXMPA,AE55KTFVNXYFD5FPYWP2OUPEYNPQ,AEBWA5I4QFCA3P3OBEPMELBGN4GQ,AHMGAC6QM62UXNEOCZIHLHSXPP2Q,AFHROSCGIXUPV3FYQ7H5QOD46Q7Q,AEAMIR3CMSA32IDEINSJKHRNANTA,AF355FTXYAKFH5NYPRTE7SL3WO3Q,AG5DWPD54QGSLWJ6QUFERLPNAX4Q | L25: =CONCATENATE(Sheet4!B25,Sheet4!C25) -> $@|\|TO$|-|Sethu madhav | M25: =COUNTA(Sheet4!B25:K25) -> 8 | N25: R3F4T5TRYPTMIG,R3DQIEC603E7AY,R1O4Z15FD40PV5,RDVX50PD4CTFE,R3H6WKG0TA5CGU,R3Q3L1KP5QWPV3,RU0LU2PAIIME,R20FTANBPFA653 | O25: Worked on iPhone 7 and didnâ€™t work on XR,Good one,Dull Physical Looks,Just Buy it,Go for it,About the product,Get charging cable at the price,Working well. | P25: Worked on iPhone 7 and didnâ€™t work on iPhone XR,https://m.media-amazon.com/images/I/71qFFAlV9ZL._SY88.jpg,Look-wise, I didnâ€™t like it. Still, I use it for my work.,Product is quite good and is fast charging.Loved it.,I like it . Looks last long.,The sturdiness will depend on the manner of its use. But its speed of charging is great. Very good product for the average income group.,It's great for charging devices with various types of ports. But works best when charging one device at a time.,Good item. | Q25: https://m.media-amazon.com/images/I/31qGpf8uzuL._SY445_SX342_QL70_FMwebp_.jpg | R25: https://www.amazon.in/Flix-Micro-Cable-Smartphone-Black/dp/B09NHVCHS9/ref=sr_1_25?qid=1672909125&s=electronics&sr=1-25
A26: =LEFT(B26,LEN(B26)-1) -> B0B1YVCJ2 | B26: B0B1YVCJ2Y | C26: =CONCATENATE(Sheet2!B26,Sheet2!C26) -> Acer80 | D26: Electronics | E26: $11,499 | F26: $19,990 | G26: 0.42 | H26: 4.3 | I26: 4703 | J26: Resolution : HD Ready (1366x768) | Refresh Rate : 60 Hertz | 178 Degree wide viewing angle|Connectivity: Dual band Wifi | 2 way Bluetooth | HDMI ports 2.0 x 2 (HDMI 1 supports ARC) to connect personal computer, laptop, set top box, Blu-ray speakers or a gaming console | USB ports 2.0 x 2 to connect hard drives or other USB device|Sound: 24 Watts Output | High Fidelity Speakers with Dolby Audio | 5 Sound Modes - Movie, Music, Standard, News, Sports|Smart Tv Features: Google certified Android TV 11 | Google Assistant | Chromecast built-in | Voice controlled Smart Remote | Hotkeys for Quick Access - Netflix, Prime Video, YouTube, Disney+Hotstar | 5 Picture Mode | 1.5GB RAM | 8GB Storage | 64bit Quad Core Processor|Display : 16.7 Million Colours | Wide Colour Gamut | Intelligent Frame Stabilization Engine | HDR10+ | Super Brightness | Micro Dimming | Blue Light Reduction|Warranty Information: 1 year comprehensive warranty provided by the manufacturer from date of purchase|Installation: Installation/Wall mounting/demo will be arranged by AHS Team. For any other information, please contact Amazon customer support | Wall Mount is not included in the box and will be charged at the time of installation|Easy Returns: This product is eligible for replacement within 10 days of delivery in case of any product defects, damage or features not matching the description | K26: AFSMISGEYDYIP3Z42UTQU4AKOYZQ,AF5ILQY4KFDTO5XHHBJ42W5DXCZQ,AFBK3X6D3AHEHSYYXPL4L6JEMSLQ,AFNB6YVNGE6IT3AWQVSIG2TJ5L3Q,AGGKMIGXUM3JRNVY7HZ3JHPJ7WTQ,AFMECPERM2GI2XQJSBWEPZKODISQ,AETPKXNOTUEX5GH7WL7XQHDR5M7Q,AERFCJ6BOMVO5YW5XM5Z2ESOIK3A | L26: =CONCATENATE(Sheet4!B26,Sheet4!C26) -> AyushROHIT A. | M26: =COUNTA(Sheet4!B26:K26) -> 8 | N26: R1EBS3566VCSCG,R24MB66WRPSN2A,R25UU2M1B9BO5X,R1NXW7PGVND2LE,R3OSBPH7X9AQUK,R2I8RVEPDM0IMQ,R5RES2LABIW7Q,R3A3IRV8ZWP1U9 | O26: Wonderful TV and Awful installation service from amazon,Acer Television Review,It's a good product for that price.,Good for the price,Almost a complete package,Nice Product,Good product,Super designed | P26: About the TV - Wonderful---------------------------------------------------------------Probably the best TV in this price range (INR13000).Good - Google interface, loaded with features, lightweight, 55 watt power consumption, stable designAverage - Sound and Picture quality is quite good but if you compare it with premium brands then obviously not that good.Features- Most of the streaming apps available and compatible- You can connect with WiFi, LAN Cable, HDMI, Set top box, Laptop, USB, Gaming console, Old dish cable, and direct TV antenna as well- Built in chromecast to cast any compatible app directly from phone to TV over same WiFi networkWays to connect phone -1. Via cast feature on mobile apps - no password needed only need to be on the same WiFi network2. Via chromecast app - project only selected media (pics, videos) or entire phone screenWays to connect PC/Laptop -1. Windows cast option - project the entire laptop screen on TV using windows cast option ( need to be connected on same WiFi network2. Via HDMI cableAbout the Amazon installation service - Awful-------------------------------------------------------1. The technician brought a cheap hanging hook that had MRP INR116 on it and asked for INR499 for it without any receipt. He kept telling that it was not for sale and company had sent this specially. However, it clearly had MRP mentioned on it2. I went to market and bought a much better cabinet for just INR200 and for installation of that as well, technician was really adamant to drill the two required holes on top. He just drilled one on top and one on bottom and kept all the other spare screws ( which I had bought ) with him. After about half an hour of arguments, he finally drilled the other required holes. And for all this, he kept cussing me that I wasted his time. There was no assistance from the person who represented the service agency as well.This whole process took me two hours to complete that too with lots of arguments. This was the worst installation experience in my life so far.Bottomline - Please do not avail the 'so called free' installation service from Amazon. It is just a scam. Instead call the acer support. They will do the job much better.,After using it for 2 months, here are it's pros and cons:Pros :1. Great picture quality. It's awesome.2. Blacks are very good and is adjustable.3. Sound with 30db is very good4. Looks great with thin besel5. Remote comes with favorite OTT buttons.6. Content upscaling is very good.Cons:1. Remote could have been better. Can't use DTH remote to turn on both televisison and set top box.2. Remote operation is bit complex.3. Motion technology not great. There is a noticeable blur when watching moving ballson OTT, but it decreases when you switch to DTH.Overall, it's a nice buy at this price point. I think I am getting fairly better picture quality and sound. I am satisfied with the product.,Product has good picture quality. Good product at that price with 25w sound. Applications running smoothly. 3 months older & no issues yet. It's running smoothly.,You get decent features for the price you pay. Screen resolution might be. Set back as you may find pixalation. Overall it's good,I am amazed with the picture quality of this 720p (HD Ready) TV. It is truly an amazing panel. I found it suitable for a viewing distance of between 6 to 10 feet. Any nearer it may not look very crisp and any farther, it will feel like a very small size. The speakers are also very good for the price and can get very loud without any distortions. However, since the speaker is downward firing, the experience will vary based on whether the TV is wall mounted or kept on a stand.The remote is good, voice search works well for me. TV start up takes a long time in my opinion, but I have not compared it against any other 32 inch TV and hence do not know where it stands among peers.5 GHz Wifi works very well even across walls. Only negative aspect I faced is w.r.t the experience of using my bluetooth headphones/earphones. Firstly, the connection sometimes doesn't happen automatically after a restart - which means I have to remove and re-discover the device thru the menu which is not simple. Secondly, the signal itself seems to be very weak and even at a distance of 8 feet in front of the TV, the signal breaks even if you move your head by 2-3 inches.However, I am still super happy with this TV. I got it for 8k during the launch offer and it is totally worth it and is recommended from my side.,At this price range(â‚¹11499/-)it is good quality product on this market..acer only should work with Sound quality improvement otherwise all ok.Picture quality really impressive,wifi connectivity good,easy to install,boderless screen design is premium and also google voice support is good(sometimes lagging).No major issues found on this TV.Just go for it.,Vellu for money. Good product,Very nice productSave money | Q26: https://m.media-amazon.com/images/I/41gikeSuhAL._SY300_SX300_QL70_FMwebp_.jpg | R26: https://www.amazon.in/Acer-inches-Ready-Android-AR32AR2841HDFL/dp/B0B1YVCJ2Y/ref=sr_1_26?qid=1672909125&s=electronics&sr=1-26
... A41: =LEFT(B41,LEN(B41)-1) -> B09C6HWG1 | B41: B09C6HWG18 | C41: =CONCATENATE(Sheet2!B41,Sheet2!C41) -> DuracellType | D41: Computers&Accessories | E41: $970 | F41: $1,999 | G41: 0.51 | H41: 4.2 | I41: 462 | J41: Up To 10,000+ Bend And 10,000+ Plugging And Unplugging Test Ensure This Cable A Longer Lifespan|Ensure Fast And Stable Data Transmission Up To 5 Gbps|Compatible Designed To Work Flawlessly With All Usb-C Devices|2 Years Warranty|1.2M Tangle Free Durable Tough Braiding Sync & Charge Cable | K41: AHRUMHBZ7IAQPLH4W5Y3A6HLQFVA,AGSJW5TCLJEKW4HAJAA4XRRNDAWQ,AFPK3KEV3ZSEJ7K6U6C3LERQ2E7A,AE43YOKQNGCH4SSBHBYFXDSPX6YA,AF6UDET5A7UZVF6X6PLTCNPAG2JA,AG4NQECOQ6XL3YXY2ARSILF65W6Q,AGQKQGF2M565PCZ2RPUYM7HIWH3Q,AF5PAF6QWH67HHLGCH6LBYQJPPUQ | L41: =CONCATENATE(Sheet4!B41,Sheet4!C41) -> Koushal K JainMathew Jibin | M41: =COUNTA(Sheet4!B41:K41) -> 8 | N41: R32JZC43P990BL,R3H7SAJ305WZL4,R37X6NTSTYLVQA,R2D7LP2EBIX3W8,R3C7TL9CMBKBQK,R3UI3Z6GBVW39Z,R331DK9D3GC0XJ,R2G3RRE7N560V7 | O41: Product is as expected,Cable has problem with samsung galaxy s8 ultra tablet,Quality and service is good.,It's perfect, definitely what i needed,Worth buying this cable,Just awesome ðŸ‘Œ,fast charge, sturdy build quality, absolute value for money product, 2yrs warranty, just go for it,Good | P41: Same type is available in half prize other make on Amazon,Cable is good and well built. it supports all sort of charging protocols. But Samsung galaxy s8 ultra seems to have some issues. It falls back to slower charging after a second or two of ultra fast charging when plugged in. It works fine with other devices just fine.,Quality of yhe cable is good. My cable is not working after 8 months. Duracell team is very responsive. They replaced the item immediately. Service is good. But only one problem is thickness of the pin must be improved.,The product is upto my expectations, worth the price, braiding is really good, i may not have the need to buy another cable again,Worth buying this cable, very durable,Its very tough material and very much durable too.,Super fast charging...long lasting due to sturdiness & strong build quality...absolute value for money product...plus 2yrs warranty...Sometime bit difficult to fold the cable due to its sturdy build but its OK looking at its edge...just go for it....a real value for money.,Very sturdy but over priced | Q41: https://m.media-amazon.com/images/W/WEBP_402378-T1/images/I/41v5BQZzfAL._SX300_SY300_QL70_FMwebp_.jpg | R41: https://www.amazon.in/DURACELL-Type-C-braided-Charge-Cable/dp/B09C6HWG18/ref=sr_1_43?qid=1672909125&s=electronics&sr=1-43
A42: =LEFT(B42,LEN(B42)-1) -> B00NH11KI | B42: B00NH11KIK | C42: =CONCATENATE(Sheet2!B42,Sheet2!C42) -> AmazonBasicsUSB | D42: Computers&Accessories | E42: $209 | F42: $695 | G42: 0.7 | H42: 4.5 | I42: 1,07,687 | J42: One 6-foot-long (1.8 meters) high-speed multi-shielded USB 2.0 A-Male to B-Male cable|Connects mice, keyboards and speed-critical devices, such as external hard drives, printers and cameras to your computer|Constructed with corrosion-resistant, gold-plated connectors for optimal signal clarity and shielding to minimize interference|Full 2.0 USB capability/480 Mbps transfer speed|1 year limited warranty | K42: AEYHTCWWZYU3JQBU6SLNFFT3OMVQ,AENQPV63OVBZHJ7L7V37M2ADFY7Q,AH7J7BCTWAMK2REWT4AMA2V5DPUQ,AFZSC27UUKDN5VYQVMAPYZNQTULA,AHM56NVJXROPTI5WICZITI4YAZAA,AEWZZXQWEU2QSVBCT7AJQ3FXMZWA,AFBLTBDVC23HRPXW2OQ2JDV3BNNQ,AGCX23QVQFBCYCAUWQNM4YHMKMQA | L42: =CONCATENATE(Sheet4!B42,Sheet4!C42) -> ShivaUzef | M42: =COUNTA(Sheet4!B42:K42) -> 8 | N42: R2AE3BN2Y58N55,R6YVRITBSRECR,R232KD83Q3MVML,R23FRK2ABESQGU,R3NE24KAHO8M69,R2PZRPBF9ZAOMA,R1DC9VBYLSSEB,R2BBEAL7JZWXYR | O42: Functionality as described,Working,Great USB in budget,Good,Good,It just works,Works with my Casio ct-x700 well,Still working after 3 months | P42: Using it and satisfactory.,Working good also not so expensive,Using this for an audio transition from Yamaha mgxu20 sound mixer to the laptop for live purpose excellent quality.,Bought it before one and a half month.... Works well.. Satisfied...ðŸ™‚,Good quality, and cheap price,Great for the price works with my usb mic fantastically well. Just I find the usb b side is a bit loose when compared to my original OEM cables.. I have ordered several pairs but all are same. At least for my mic. But itâ€™s not too loose to be called unusable,Works with my Casio ct-x700 well, | Q42: https://m.media-amazon.com/images/I/4101vlzySzL._SY300_SX300_QL70_FMwebp_.jpg | R42: https://www.amazon.in/AmazonBasics-USB-2-0-Cable-Male/dp/B00NH11KIK/ref=sr_1_44?qid=1672909125&s=electronics&sr=1-44
A43: =LEFT(B43,LEN(B43)-1) -> B09JPC82Q | B43: B09JPC82QC | C43: =CONCATENATE(Sheet2!B43,Sheet2!C43) -> Mi108 | D43: Electronics | E43: $19,999 | F43: $34,999 | G43: 0.43 | H43: 4.3 | I43: 27151 | J43: Resolution : Full HD (1920x1080) | Refresh Rate : 60 Hertz | 178 Degree wide viewing angle|Connectivity: 3 HDMI ports to connect set top box, Blu-Ray players, gaming console | 3 USB ports to connect hard drives and other USB devices | 3.5mm to connect your headphones | S/PDIF port to connect Speakers|Sound: 20 Watts Powerful Stereo Speakers | DTS-HD|Smart TV Features : Android TV 9 | Chromecast built-in | PatchWall 4 with IMDb integration | 75+ Free Live Channels | Universal search | Language Universe (16+ Languages) | Miracast | Supported Apps: Prime Video | Netflix, Disney + Hotstar, YouTube, Apple TV, 5000+ apps from Play Store | Quad core processor | Built-in Wi-Fi | 1GB RAM + 8GB Storage|Display: LED Panel | Vivid Picture engine | Detailed Picture Controls | Ultra bright screen | Dynamic contrast | Dynamic backlight|Warranty Information: 1 year comprehensive warranty on product and 1 year additional on Panel provided by the brand from the date of purchase|Installation/Wall mounting/demo will be arranged by AHS Team or Xiaomi service partner. For more information, please call Mi support on Toll Free Number (Please visit brand website for toll free numebrs) | Wall Mount is not included in the box and will be charged extra at the time of installation | K43: AHB43CZ4RHLJ5S6CBOWX6MEI7J4Q,AHP24JLRZ2DTLBEX22A6DVUJDSBA,AGLKKKJCKHZ32S7MCK46JWDZ2A3A,AHXCZCBKCKFAOJJ2GOCQS3OKPQOQ,AHZ4UBDUCUMY6IGCR67LB4P5RBXA,AHCGV72I3RKXOSSUNK3SQOB677NA,AFTCOTLY72MCSV5WHMHSZ67ZZG6A,AEF55HUCR2L3DMBXVV4SGD55JKIQ | L43: =CONCATENATE(Sheet4!B43,Sheet4!C43) -> Sameer PatilTechnoLoon | M43: =COUNTA(Sheet4!B43:K43) -> 8 | N43: R1VOXBV87EI37W,R1BIBCTNJPJOX3,R2RRCA47QEK9C1,R2WHV3RU3J4985,R22K5MQ8Z8N6L2,R3TQACIQUXT2WO,R2YKPF09C6G76,R1E6GYG29CA7RM | O43: DETAILED REVIEW after 3 WEEKS of Usage !!!,Priceworthy.,It's a good product,Good,Vivid picture quality is stunning,SUPER DEAL,Value for money,Very nice | P43: NOTE:@ If you select brand-authorized TV installation, then DO NOT unbox the tv until MI representative arrives.This ensures, that if TV is damaged in transportation, then you will get replacement easily.@ If you didn't choose installation, then just SHOOT the video of unboxing by yourself, to avoid any hassle in case replacement is needed.@ Amazon Prime and Netflix are not inbuilt, but can be Side-loaded !!!@ To use your Set top box with android interface, you need to buy MI IR cable and set it up.* OR else directly connect the set up box via AV or HDMI port, to use it conventionally.@ Out of 8GB memory, you only get around 4.7GB free to use (check the image attached)There are Hundreds of review on this TV here as well as on youtube, but NONE explains the TV's potential completely and what its actual flaws are. Here's a quick Fact for the User's complaining about the LESS cost to benefits ratio, guys if you buy a Android TV box alone which has processing capacity similar to this tv, then it would alone cost you more than 5K rupees & here you get this TV with that android setup with various other feature under 15K. So just check once, what options you have before complaining.Eventually I bought this TV, since I was already using 4A 43 version for months and wanted smaller version for bedroom. Now after using this TV for over 3 weeks, I am stating my DETAILED user experience. Its a detailed & huge review, but do read it, if you want to invest this much amount.â—â— If you want to get quick overview of the device, then read below else scroll down for Detailed Review â—â—# Firstly its budget friendly & ONLY Smart TV under 15k in the current market.# Has Most number of Output port ( 1*AV, 3*HDMI, 2*USB ).# Has Android 8.1 out of the box along with inbuilt Bluetooth# Has Dual interface - MI Patchwall & Android TV ( I mostly prefer android TV interface )# Remote has Bluetooth & Voice Search with sleek profile.# Has better processor compared to predecessor along with 1GB RAM + 8GB storage ( 4.7GB actual )# Speaker Output is low.# Need IR cable for using set top box with android interface.# Amazon prime & Netflix is NOT preloaded, but can be side loaded.# Native Display is ONLY HD, though 1080p & even 4K videos from youtube works well (check images attached).# Can install & play tons of High quality games like RR3, etc (check images attached).# Finally smartphone mirroring works fine most of the time.FULL DETAILED REVIEW :---->BUILT QUALITY :------------------# Has combination of plastic and aluminium for the main body. Its not great, but above average.# Table top stands looks bit flimsy, but are workable.* The screws which are provided in the box, DOES NOT fits the tv perfectly, so I bought new from local store.# It has averagely slim profile, not the slimmest in the market.# Speaker Placement is inconvenient. Since they are placed at the bottom, so when you keep it on table top, the sound tends to dampen and bulge.# Has good ventilation for electronics and it hardly heats up.# Overall built quality is above average.DISPLAY QUALITY :---------------------# It has very Thin bezels, which looks great.# Video resolution is 1366x768p, but 1080p videos works fine on it.* 4K videos on youtube runs smoothly as well.# Viewing angle are good compared to price. ( Check the images attached )# Contrast is above average, Brightness is good and colours are quite vivid.# Display quality is also above average, not very great.REMOTE CONTROL :-----------------------# Its very sleek and compact.# Has only 7 buttons and is easy to operate.# Fortunately it has Volume buttons, which is handy. ( I have couple of android TV boxes without volume button on remote, so I know the pain of using mouse to adjust the volume :P )# Placement of Voice search button is improper. Its just below Power button, and I end up pressing power button a lot.# Finally its bluetooth, so no need to point it towards tv for operation.OTHER FEATURES :---------------------# It has Dual interface, i.e. Patchwall and android TV. Has tons of content.# Many games can be installed (till you have memory left), including multiplayer games.# Google voice search is very useful, if you don't want to use keyboard.# Processing speed is fast and I haven't detected any lags yet. ( Lags in streaming can be due to slow internet speed, not due to hardware )# Bluetooth and wifi connectivity works perfectly.CONS :------# Speaker output though rated 20W, is NOT upto the mark. My 16W JBL speakers has better and louder sound.# Placement of speaker is inconvenient, as in table top position, speakers face the table and sound dampens.# Internal Memory is very LESS.# NO Netflix and amazon prime pre loaded, though you can side load them.# Miracast not supported. Even normal smartphone mirroring lags sometimes.# Native resolution is just 720p HD, though the 1080p videos works on usb & 4K on youtube.# Screen is Slightly reflective, its similar to almost all the other LED tv's.# Mixed experiences of after sales service.CUSTOMER CARE :--------------------# Firstly the installation is a Joke. My installation was scheduled 16 days after my product Delivery and the fun part is, there's ONLY 10 days replacement window for this product :P# Company only takes replacement if the product is opened by their Representative, so there's NO point of return window time frame.# MI has mixed reviews for repairs and services. Though I have not encountered any problem with any MI tv yet, I have had issues with other mi products and service center near me is always very helpful.VERDICT :-----------Considering all the facts, if you are fine with above average Display quality, want a Smart tv and if you have tight budget, then this the TV you should certainly go for. Trust me, you won't get any better deal than this least for coming couple of months. If you have higher budget, then certainly explore brands like sony, samsung, etc.This is NOT a perfect smart TV, but for the given price and 2 Years of warranty, its NO brainer to choose this, its certainly worth the investment.,This television is definitely a perfect balance between price and performance especially during flash sale at an exceptional price of â‚¹12500.Performance â­â­â­â­â­-----------------------The processor in this Smart TV is powerful enough to play 4K 10bit HEVC videos right out of the box. VLC or MX player can be installed for enhanced media support.Picture Quality â­â­â­â­â­--------------------------Many people complain about the overbright screen. But it can be compensated by adjusting the display settings.These are my preferred settings.Backlight :1 to 20*********************During night even the lowest value of 1 is bright enough and can watch content without hurting eyes.During day time adjust it as per your requirement depending on your ambient lighting conditions. A maximum of 20 would be enough.Setting backlight to minimum improves black levels, reduces power consumption, increases LED life and reduces eye strain especially during night.Brightness :48*****************Brightness setting controls black level.Increasing brightness reduces black levels and hence reduces contrast.Brightness at 50, pictures looks washed out with poor blacks and color saturationAt 45 black looks deep but lots of details at dark areas are lost while watching movies.48 is an optimal setting to my eyes with good blacks and not so lack of details.Contrast : 40 to 45*********************Contrast setting controls white level.Contrast can be set anywhere between 40 and 45. Increasing contrast too much may cause highlight areas in a picture, like bright skies or shiny objects might look overexposed. As the screen itself is very bright, increasing contrast further makes whites look over bright. Also colors gets washed out while increasing contrast.Saturation: 45 to 50************************Color saturation can be set anywhere between 45 to 50. At 45 colors look more natural. At 50 colors looks a bit punchy. But still its a personal preference.At the above settings, the black levels and colors were pleasing while watching demo videos of OLED TVs on YouTube at 1080p . The following Youtube videos help you to check the black level quality of the TV.LG 4K OLED Beauty Of Black DemoLG OLED Eclipse 2 DemoLG HD Demo Art NouveauFull HD and 4K videos looks sharp in this TV. Downloaded a sample 4K HEVC video named 'Life Untouched' and also a 4K HEVC sample of the movie Elysium. Both of them played smoothly on the TV with very good details.Screen Quality â­â­â­â­--------------------------I think this is a VA panel , the quality of which sits right in between TN and IPS panels. The screen is glossy and hence reflective. This might be a problem if the TV is placed in a room with windows facing it.Like all other LCD panels, this also has also got uneven screen uniformity but that's only noticed in plain dark grey backgrounds. While watching movies or other content it's not at all a problem. Screen non uniformity is a common issue even with high end TVs of big brands like LG Samsung etc.Luckily there's no backlight bleeding in the unit I received.Viewing angles are average with some loss of contrast even at low angles but that's a common VA panel characteristic. IPS panels with good viewing angles can't be expected at this price point.All LCD panel technologies have their strengths and weaknesses. IPS panels have good viewing angles but has poor black levels. VA panels excels in black depth despite it's average viewing angles and this TV has got very impressive black levels.Sound Quality â­â­â­â­â­--------------------------Bass is a bit weak (I think bass is improved following some updates. So giving 5 stars from 4.) It's very loud even at low volume. Midrange and treble are very good. Even minute high pitched click and tick sounds in movies can be heard very clearly.Edit:In a previous review I have mentioned these EQ settings sounds good. But it isn't.100Hz : 7300Hz : 81000Hz : 43500 Hz : 610000 Hz : 5A high value of 8 for 300 Hz actually make the sound muddy and muffled.The following settings sounds much better and here's the reason.100 Hz : 8 - BassFrequency setting for deep bass male vocals and instruments like Kick Drum,Toms, Snare etc.300 Hz : 4 - Low MidrangeEnhances bass and depth of male vocals. Increasing 300Hz too much makes sounds muddy and muffled reducing clarity of high frequency sounds1000 Hz : 3 - MidrangeImparts a metallic tone. Increasing makes sound tinny and unpleasant.3500 Hz : 5 - Upper MidrangeVocals especially female sounds best at this frequency. A value of 5 enhances vocal quality. Increasing too much makes vocals harsh.10000 Hz : 7 -TrebleAdds crispiness and sparkle to vocals and instruments. Enhances tinkling sounds of metallic instruments.Human ear is sensitive to midrange and upper midrange frequencies Here it's 1000 and 3500 Hz. Setting these values too high can cause listening fatigue. Even increasing 300Hz is disturbing.Great sound performance especially bass is not even expected from a television in this budget. But considering its midrange frequency, clear treble and loudness, it deserves 4 stars.Remote Control â­â­â­â­-----------------------------Minimalism is great. But minimalism with less functionality is not so great. Addition ofMute,TV Settings and Video input selection buttons would 've made the remote more functional.App support â­â­â­â­â­(Update)-----------------------When the TV was released there was no support for Netflix and Amazon Prime. But now with Pie update it supports both Netflix and Amazon Prime. Now the TV deserves 5 stars for app support.Pros and Cons--------------------------- Pros:1. Powerful processor for 4K media playback.2. App installation via USB3. Built in Chromecast4. Bluetooth remote5. Voice CommandCons: (Update)Previously the main issues with the TV were the lack of Autoplay function and Standby option.But in the latest update both these issues are solved.Now when the TV is turned on it will automatically go to the previous Input sourceTo enable it, go to Settngs >Inputs > Enable 'Stay on the previous source' option.Screen off feature is also added in the new update. Long pressing Power button will show Screen Off option.The only disadvantage left on the TV was lack of Miracast. But on a latest update build PI.4316 miracast is included and now its perfect.To sum up:--------------------Overall considering the picture quality, powerful hardware and the price, the TV definitely deserve 5 stars devoid of it's average audio quality and the glossy screen because there are no other TVs in market with such features at this price point. Also Xiaomi now has got very strong service support across India.New brands like iFFalcon, Blaupunkt ,Thomson etc might provide better options at a competitive price. But when it comes to service centres, it's a dead end.I am very much satisfied with the purchase.,It's good product,Good,if you like a best tv on your budget I'll recommend you this stunning picture quality and DTS surround is osm but there was a few lagging problem and Miracast is not good ðŸ™,Build quality good.sound and bass excellent.,Product is very good. Sound quality is crisp. Worth buying. I brought it 2 years back. Still working fine,Good quality | Q43: https://m.media-amazon.com/images/I/41nsy8kxWUL._SY300_SX300_QL70_FMwebp_.jpg | R43: https://www.amazon.in/inches-Full-Android-L43M6-INC-Black/dp/B09JPC82QC/ref=sr_1_45?qid=1672909125&s=electronics&sr=1-45
A44: =LEFT(B44,LEN(B44)-1) -> B07JW1Y6X | B44: B07JW1Y6XV | C44: =CONCATENATE(Sheet2!B44,Sheet2!C44) -> WayonaNylon | D44: Computers&Accessories | E44: $399 | F44: $1,099 | G44: 0.64 | H44: 4.2 | I44: 24269 | J44: [High Compatibility] : iPhone X/XsMax/Xr ,iPhone 8/8 Plus,iPhone 7/7 Plus,iPhone 6s/6s Plus,iPhone 6/6 Plus,iPhone 5/5s/5c/se,iPad Pro,iPad Air 1/2,iPad mini 1/2/3,iPod nano7,iPod touch and more apple devices.|[Fast Charge&Data Sync ] : It can charge and sync simultaneously at a rapid speed, Compatible with any charging adaptor, multi-port charging station or power bank.|[Durability] : Durable nylon braided design with premium aluminum housing and toughened nylon fiber wound tightly around the cord lending it superior durability and adding a bit to its flexibility.|[High Security Level ] : It is designed to fully protect your device from damaging excessive current.Copper core thick+Multilayer shielding, Anti-interference, Protective circuit equipment. | K44: AG3D6O4STAQKAY2UVGEUV46KN35Q,AHMY5CWJMMK5BJRBBSNLYT3ONILA,AHCTC6ULH4XB6YHDY6PCH2R772LQ,AGYHHIERNXKA6P5T7CZLXKVPT7IQ,AG4OGOFWXJZTQ2HKYIOCOY3KXF2Q,AENGU523SXMOS7JPDTW52PNNVWGQ,AEQJHCVTNINBS4FKTBGQRQTGTE5Q,AFC3FFC5PKFF5PMA52S3VCHOZ5FQ | L44: =CONCATENATE(Sheet4!B44,Sheet4!C44) -> ManavAdarsh gupta | M44: =COUNTA(Sheet4!B44:K44) -> 8 | N44: R3HXWT0LRP0NMF,R2AJM3LFTLZHFO,R6AQJGUP6P86,R1KD19VHEDV0OR,R3C02RMYQMK6FC,R39GQRVBUZBWGY,R2K9EDOE15QIRJ,R3OI7YT648TL8I | O44: Satisfied,Charging is really fast,Value for money,Product review,Good quality,Good product,Good Product,As of now seems good | P44: Looks durable Charging is fine tooNo complains,Charging is really fast, good product.,Till now satisfied with the quality.,This is a good product . The charging speed is slower than the original iPhone cable,Good quality, would recommend,https://m.media-amazon.com/images/W/WEBP_402378-T1/images/I/81---F1ZgHL._SY88.jpg,Product had worked well till date and was having no issue.Cable is also sturdy enough...Have asked for replacement and company is doing the same...,Value for money | Q44: https://m.media-amazon.com/images/W/WEBP_402378-T1/images/I/41rB0DnVFmL._SX300_SY300_QL70_FMwebp_.jpg | R44: https://www.amazon.in/Wayona-Braided-WN3LB1-Syncing-Charging/dp/B07JW1Y6XV/ref=sr_1_46?qid=1672909125&s=electronics&sr=1-46
A45: =LEFT(B45,LEN(B45)-1) -> B07KRCW6L | B45: B07KRCW6LZ | C45: =CONCATENATE(Sheet2!B45,Sheet2!C45) -> TP-LinkNano | D45: Computers&Accessories | E45: $999 | F45: $1,599 | G45: 0.38 | H45: 4.3 | I45: 12093 | J45: High Speed WiFi â€”â€” Up to 600Mbps speeds with 200Mbps on 2.4GHz and 433 Mbps on 5GHz, upgrades your devices to higher AC WiFi speeds|Dual Band Wireless â€”â€” 2.4GHz and 5GHz band for flexible connectivity, upgrades your devices to work with the latest dual-band WiFi router for faster speed and extended range|Nano design â€”â€” Small, unobtrusive design allows you to plug it in and forget it is even there|Operating System â€”â€” Supports Windows 11/10/8.1/8/7/XP, Mac OS 10.15 and earlier|Advanced Security â€”â€” Supports 64/128-bit WEP, WPA/WPA2, and WPA-PSK/WPA2-PSK encryption standards|Worry-free customer support â€”â€” For other installation related query, compatibility issue or any other queries call on toll free no | K45: AEM356PVXFHAXWV56KDO75FS5WPA,AHVTFTBEBRRJCG72ZG7ABDNQSAOA,AHFTFGF2YB5ZEUB3NC3KOBGZBG5Q,AEI36WUCG27UYFAGDF7HX74VEGIA,AGW3NGXVSGUB34Q5V6ACANURQMGQ,AEIMBDWSM42YEDEE6476WUXFZJHQ,AHM5MCT3ZO5Q2MBYZUDB6UI5AXLA,AFTPXYKUNENYJVDOC55L2CJXPXFQ | L45: =CONCATENATE(Sheet4!B45,Sheet4!C45) -> Paul JoeSimon Rex P. J. | M45: =COUNTA(Sheet4!B45:K45) -> 8 | N45: RSNHWPVLK9SAQ,R2RKKAN3GRHI0G,R1FVWKC3ORTKKX,RTWMPZGIX9EDV,R3TRCC0769D12A,R2NJK9AW0NVU1C,R3M97OC4YJNBQT,R2IUPWWR3XMJ3D | O45: Dual Bandwidth,It's good,Simple and effective,Easy plug and play,Only 200mbps support,Great Device for Old Laptops,Good device but be careful for a defective one.,Excellent Speeds and Coverage! | P45: Easy to use,It's good and useful,Had been using this for quite sometime. Supports dual bands. Signal coverage is yet like others. Good use. Easy to install and use,Excellent product revived by old laptop.,,I got this product because for some reason my laptop's internal WiFi and Bluetooth stopped working. Now there are options to buy two separate devices but this solves my purpose and it doesn't sticks out as well.It's having Dual WiFi but I will suggest you to use on 5GHz as the 2.4GHz is a bit slow, slower then the regular 2.4GHz.,It's a good device, good strength, plug and play so no installation needed,BUT got a defective device first which malfunction immediately on plugging, Replaced it with a new one and it's been working well.,Using it for a couple of months now. This has proved to be the much helpful adapter I needed when I moved my PC from Wired to Wireless in a different room. Getting speeds of 148-149Mbps in my 150Mbps subscription speeds. | Q45: https://m.media-amazon.com/images/W/WEBP_402378-T2/images/I/31EHCPHbSlL._SX300_SY300_QL70_FMwebp_.jpg | R45: https://www.amazon.in/TP-Link-Archer-T2U-Nano-Wireless/dp/B07KRCW6LZ/ref=sr_1_47?qid=1672909125&s=electronics&sr=1-47
A46: =LEFT(B46,LEN(B46)-1) -> B09NJN8L2 | B46: B09NJN8L25 | C46: =CONCATENATE(Sheet2!B46,Sheet2!C46) -> FLiX(Beetel | D46: Computers&Accessories | E46: $59 | F46: $199 | G46: 0.7 | H46: 4 | I46: 9378 | J46: Micro USB charging cable for android phones and any other device with Micro USB Port|Charge & sync, this USB cable can charge and data sync simultaneously at 480Mbps speed, compatible with all devices with a Micro USB port. Core : Tinned Copper|Durable PVC Outer Exterior: PVC cables are versatile, high in tensile strength, flexible, and good conductors.|micro USB cable is 1 meter in length, optimized for easy use for your comfort at home or office, helps you to overcome distance restrictions. | K46: AHIKJUDTVJ4T6DV6IUGFYZ5LXMPA,AE55KTFVNXYFD5FPYWP2OUPEYNPQ,AEBWA5I4QFCA3P3OBEPMELBGN4GQ,AHMGAC6QM62UXNEOCZIHLHSXPP2Q,AFHROSCGIXUPV3FYQ7H5QOD46Q7Q,AEAMIR3CMSA32IDEINSJKHRNANTA,AF355FTXYAKFH5NYPRTE7SL3WO3Q,AG5DWPD54QGSLWJ6QUFERLPNAX4Q | L46: =CONCATENATE(Sheet4!B46,Sheet4!C46) -> $@|\|TO$|-|Sethu madhav | M46: =COUNTA(Sheet4!B46:K46) -> 8 | N46: R3F4T5TRYPTMIG,R3DQIEC603E7AY,R1O4Z15FD40PV5,RDVX50PD4CTFE,R3H6WKG0TA5CGU,R3Q3L1KP5QWPV3,RU0LU2PAIIME,R20FTANBPFA653 | O46: Worked on iPhone 7 and didnâ€™t work on XR,Good one,Dull Physical Looks,Just Buy it,Go for it,About the product,Get charging cable at the price,Working well. | P46: Worked on iPhone 7 and didnâ€™t work on iPhone XR,https://m.media-amazon.com/images/I/71qFFAlV9ZL._SY88.jpg,Look-wise, I didnâ€™t like it. Still, I use it for my work.,Product is quite good and is fast charging.Loved it.,I like it . Looks last long.,The sturdiness will depend on the manner of its use. But its speed of charging is great. Very good product for the average income group.,It's great for charging devices with various types of ports. But works best when charging one device at a time.,Good item. | Q46: https://m.media-amazon.com/images/I/31v7NnnAItL._SY445_SX342_QL70_FMwebp_.jpg | R46: https://www.amazon.in/FLiX-Charging-480Mbps-Devices-XCD-M11/dp/B09NJN8L25/ref=sr_1_48?qid=1672909125&s=electronics&sr=1-48
A47: =LEFT(B47,LEN(B47)-1) -> B07XJYYH7 | B47: B07XJYYH7L | C47: =CONCATENATE(Sheet2!B47,Sheet2!C47) -> WecoolNylon | D47: Computers&Accessories | E47: $333 | F47: $999 | G47: 0.67 | H47: 3.3 | I47: 9792 | J47: Special Features Of The Universal Cable: This Cable Is Touch And Sleek, Highly Durable, Premium Nylon Braided Cable, Has 1 Year Warranty.|Ultra Durable Usb Cable: This Universal Cable Is Made Of High-Quality Nylon Material And Makes It Resistant To Fraying And Wear-Related Damage, More Flexible And Durable|Fast Charging Cable: This Universal Cable Can Simultaneously Charge Android, Ios And Type C Devices. All Combined 3 In 1 Power Cord. All In One Charger|Usb Cable For Fast Charging: This Charging Cable Is Designed For Charging The Devices Quickly. The 3A Charger Is Universally Suitable For Charging All Smartphones|Country Of Origin: China|Multifunctional Usb Cable: Wecool 3 In 1 Charging Cable Is Tangle Free, Rugged, Quick Charging, Universally Compatible, Flexible And Of | K47: AE47XF2766XJOEOI42DVP2HMB4YQ,AH6JPV326WGUKC2J4EGVP3IN6ZLA,AF4X3QT4KW3DV2HUMQVSOJDISOOQ,AG46FAHE6KV3OQCLJYKRDZWNNYGQ,AFG6OH7UYU5ZITX4NE2KQR3DX5SA,AFCZMUBZNRVRW2EJJKK5PN2YQZVQ,AHDMHAUOY75NWLNOF3X4UPNKXFSQ,AHWCWBYXHX4QO7ZOFUYIUFTTAJIQ | L47: =CONCATENATE(Sheet4!B47,Sheet4!C47) -> Amazon CustomerDHONDU | M47: =COUNTA(Sheet4!B47:K47) -> 8 | N47: RWSHFGBE1WU3I,R1VBNTH3HSMVMB,RTATA9H2ELJ81,R1B0APD6HVOT8V,R99TNL1C7XQ5O,R37RT17N8YUWT4,R1WG1ARVL9YH61,R2UFM5PKO62Z5R | O47: Its slow in charging,Ok product,Looks good, but charges slow,very slow charing.,Poor quality, iPhone part will last for two months only, other two are ok,Charger,Product ok,Slow charging | P47: Charging power is very less. It takes hours to charge even a single phone.,Ok type product. Not very sturdy,Although it is written fast charging. However it charges quite slow compared to original chargers, even when one mobile is charged at one time.,When using a regular cable, it takes about 2 hrs for a full charge. When using this cable to the same socket and charger, it showing 10 hrs.,IPhone charger last for two months only,Charging not fast,Slow charging4500amh battery18 watt Charger4 khant full charge,Slow charging speed | Q47: https://m.media-amazon.com/images/W/WEBP_402378-T2/images/I/41CnR1WhD3L._SX300_SY300_QL70_FMwebp_.jpg | R47: https://www.amazon.in/WeCool-Braided-Multifunction-Charging-Android/dp/B07XJYYH7L/ref=sr_1_49?qid=1672909126&s=electronics&sr=1-49
A48: =LEFT(B48,LEN(B48)-1) -> B002PD61Y | B48: B002PD61Y4 | C48: =CONCATENATE(Sheet2!B48,Sheet2!C48) -> D-LinkDWA-131 | D48: Computers&Accessories | E48: $507 | F48: $1,208 | G48: 0.58 | H48: 4.1 | I48: 8131 | J48: Connects your computer to a high-speed wireless network|Supports WPA/WPA2 wireless encryption to help prevent outside intrusion and protect your personal information from being exposed.|3 Year Brand Warranty|2.4Ghz frequency band (300mbps)|2 fixed internal Wi-Fi antenna|N300 MIMO Wi-Fi USB Adapter|This is a plug and play device with generic configuration|Compatible with all CCTV DVRs | K48: AGA2PZGWMQIRA46VYOTICFE7KCBA,AHI2QJ4CLTCQWACDIC2LDFJPDAPA,AEXAFY7V2ZRZI2GD2J6KDOWBZUBQ,AHAEBXTXQDY355AGFMFX3Z2VAAUQ,AETRIARSUFSMNG5LFJZMW6CBJMMQ,AEHQQTEDMSXRGSBDDEIH3JF4AOMQ,AGMG74N6WQGI376W7GEJJ4XD3ARQ,AG7QMBEFFY2LJJKKEVWMJU2BMNRQ | L48: =CONCATENATE(Sheet4!B48,Sheet4!C48) -> nileshEAGLE | M48: =COUNTA(Sheet4!B48:K48) -> 8 | N48: R2EJIN3N3L3XKI,R2JMJ8QNG66LV4,R3B46JNPC2T4E7,R3HHJCTEJ7J9CS,R2LOAPI3SK4RCX,R1MLGZDQDKIVIF,R10KVN4LSVD459,R3BO9D050WHWVX | O48: good tool to use for,Brand is always good,Overall good and a better experience,It is useful to me.,Works well with cpplus dvr,Good,Its not plug an play u need to install the driver and will support till 2.4 Ghz not above that,Surveillance Camera In My House | P48: good quality tool from d linkWiFi signal is good,Nice product,Overall good and a better experience,It funcions properly and useful to me.,I you want to buy it for CP Plus Orange DVR, it works.,Nice,Its not plug an play u need to install the driver and will support till 2.4 Ghz not above that. Im using in Jio wifi so its not supporting 5G connectivity as its 3.0,The first reason I bought this item was to have a surveillance camera in my house. To view it on my mobile Used,etc.... | Q48: https://m.media-amazon.com/images/I/31+NwZ8gb1L._SX300_SY300_.jpg | R48: https://www.amazon.in/D-Link-DWA-131-Wireless-Adapter-Black/dp/B002PD61Y4/ref=sr_1_50?qid=1672909126&s=electronics&sr=1-50
A49: =LEFT(B49,LEN(B49)-1) -> B014I8SSD | B49: B014I8SSD0 | C49: =CONCATENATE(Sheet2!B49,Sheet2!C49) -> AmazonBasics | D49: Electronics | E49: $309 | F49: $475 | G49: 0.35 | H49: 4.4 | I49: 4,26,973 | J49: Please select appropriate display resolution & refresh rate for proper display output. HDMI A Male to A Male Cable: Supports Ethernet, 3D, 4K video and Audio Return Channel (ARC)|Connects Blu-ray players, Fire TV, Apple TV, PS4, PS3, XBox one, Xbox 360, computers and other HDMI-enabled devices to TVs, displays, A/V receivers and more|Cable allows you to share an Internet connection among multiple devices without the need for a separate Ethernet cable|Meets HDMI 2.0 standards (4K Video at 60 Hz, 2160p, 48 bit/px color depth) that supports bandwidth up to 18Gbps and backwards compatible with earlier versions|Cable Length: 6 feet (1.8 meters); 1 year limited warranty | K49: AEYJ5I6JZZPOJB6MGWRQOHRQLPSQ,AFY5TVFOMVHGBPBTIJODYDQRZM5Q,AE3O6366WGEQAANKJ76QETTUQQTQ,AEQIJCPWSBCDKUO5VROXXHWX3PPA,AGVIAQK2HQ47P7UVXHW2NBAEU7YQ,AE3D5CJ2GDUP5SQ3AAYMVAGDTX7A,AH77IQRYD54XCRMCO7XEAIAYCLPA,AEA2HQHMFG3ZGJFOLLJQ65WKIZUQ | L49: =CONCATENATE(Sheet4!B49,Sheet4!C49) -> Rishav GossainShashank Mallamraju | M49: =COUNTA(Sheet4!B49:K49) -> 8 | N49: R1FKOKZ3HHKJBZ,R2WNMZI1EXTA0H,RCA1M3W4RIXUR,R3BKCLL6D7ZLIX,REVSR0ILY3547,R15W5KMQB95IV5,R10PB68FRUHT5V,R3TLCE9JSBU3UP | O49: It's quite good and value for money,Works well,Hdmi cable,Value for money,All good,Gets the job done,Delivery was good,This one was my need to purchase | P49: I am using it for 14 days now. The experience is pretty good as of now. Picture quality is also not bad. Don't expect something out of the world at this price point. But you can go for it if you have a tight budget.,Initial impressions: works as said, glad I didnâ€™t go for cheaper options (not that itâ€™s too costly) just plug and play. Will update if it screws up,The hdmi cable is good to watch movie,sports and its gives better quality while connecting your laptop with TV and play ðŸŽ®.I loved it,Works as expected. Length of the cable is short and it was mentioned also satisfied my requirement. If you need more length better look other options.,All good,It's the best HDMI cable at this price range. No problems yet. Just go for it !!,I was expecting this to be delivered on time and it was delivered on time.Product is good as i have tried other cables and wires from Amazon basica brand.,Good one | Q49: https://m.media-amazon.com/images/I/41bCxnHksnL._SY300_SX300_QL70_FMwebp_.jpg | R49: https://www.amazon.in/AmazonBasics-High-Speed-HDMI-Cable-Feet/dp/B014I8SSD0/ref=sr_1_51?qid=1672909126&s=electronics&sr=1-51
A50: =LEFT(B50,LEN(B50)-1) -> B09L8DSSF | B50: B09L8DSSFH | C50: =CONCATENATE(Sheet2!B50,Sheet2!C50) -> 7SEVENÂ®Compatible | D50: Electronics | E50: $399 | F50: $999 | G50: 0.6 | H50: 3.6 | I50: 493 | J50: 1. 7SEVEN Compatible remote suitable for all Original samasung TV / Monitor remote and have speciality with Hotkeys feature. It comes with NETFLIX, prime Video and ZEE5(www) Hotkeys. Incase ZEE5 app not available in your samsung smart tv then it will open default www(web broswer).|2. Equipped with various buttons and controls, this remote lets you adjust settings of your LED OLED QLED Curved & Plasma TV easily with the comfort of your sofa or bed.|3. This Remote does not have Bluetooth feature. No voice functions. This is a remote control to control TV mode & it does not control or support the set-top box mode.|4. No pairing required after load new AA Alkaline batteries, Samsung Remote suitable for smart tv's and monitor|5. This is a 7SEVEN compatible Product & Not Original Samsung Remote. | K50: AH5G2FWQ6AJBXK2IDCA22BNQTT2A,AEEV73PQDYYMSQSW46LQMZ526YVQ,AHWB25RGISH5XJ2YQCR4J6FDBPOQ,AE2PYPC3OF2HEF4NCE63FBFFFOMQ,AHYUM6XUA4K6V4QEAPT5MLQQIDPA,AG6U2ZW7UGA562DK4W6NVANEMKDA,AFALQ6JKOEKVRVI3BZ2G5PJ63HQQ,AGAXJLX3K3I7WQKQA4Q4NT2IJ2WQ | L50: =CONCATENATE(Sheet4!B50,Sheet4!C50) -> MONTYQais Makani | M50: =COUNTA(Sheet4!B50:K50) -> 8 | N50: RVEWH0LAEO3NH,R3E42NTD6HXN1Q,R3IC0VLPIDBPTY,R1F0O9EAQGRSQS,R2B02VD2RPE2SE,RO2E58ZA8YH7E,R10AUMHF2MJRRU,R1BBQYI4QO69ID | O50: Overall Good,Works well. Will comment on durability after using it for a few months.,Nice product,Channel button doesn't work,Compatible with every smart tv,functionality at a budget,Number keys not working,It's good to go ahead with this, for Samsung 6 series | P50: Overall replacement of original samsung remote.its compatible easily with my samsung uhd tv.but there is no voice command in the remote.,Works well. Will comment on durability after using it for a few months.,It uses two AA battery.Seems durable.,Product quality of good. But the channel button doesn't work. I did return and replaced the same product, but it's th same result, channel button doesn't work,Good to go with this rather than purchasing a original one from samsung,we have an expensive samsung TV.TV is great but original remote started draining battery and we had to put in new battery every 5 days which was not ideal.replacing with original remote is a costly affair ( 4k ?)this is a good cheap replacement- has all the functionalities except voice (which we rarely use),Everything works fine except number keys which is very important to change channels , what a waste of money had to buy another remote,Like the design | Q50: https://m.media-amazon.com/images/W/WEBP_402378-T1/images/I/21rBnbHkW9L._SX300_SY300_QL70_FMwebp_.jpg | R50: https://www.amazon.in/7SEVENTM-Compatible-Replacement-Original-BN59-01259E/dp/B09L8DSSFH/ref=sr_1_52?qid=1672909126&s=electronics&sr=1-52
A51: =LEFT(B51,LEN(B51)-1) -> B07232M87 | B51: B07232M876 | C51: =CONCATENATE(Sheet2!B51,Sheet2!C51) -> AmazonbasicsMicro | D51: Computers&Accessories | E51: $199 | F51: $395 | G51: 0.5 | H51: 4.2 | I51: 92595 | J51: Cable Length: 6 Feet (1. 82 Meters)|Gold-Plated Connectors Resist Corrosion For Signal Purity|Smaller Connector Designed To Fit Smaller Spaces|1 Year Limited Warranty|Supports Up To 480 Mbps Data Transmission Speed|Micro Usb Charging Cable For Android Phones|Ideal For Charging Android Phones And Tablets Or Connecting Pc Peripherals Such As Hard Drives, Printers, And More | K51: AF7IXQKBUL6NEIQG4R53LMJJUGXQ,AFODI4XXHXHBFFUHK7N5LVKWEXTQ,AGNONTMQDE5KLLDEEB57Z3C5WAEA,AFW6NV5N3FUXV3CNUACPSYC5AB3Q,AEW6KBDGJEWIOQKAW3FP74GMV6TA,AEGT7WPGXXMSH5J3LZLL6CPJ7QMQ,AEKCUG7WMX6KMP6VFBWI3ICW5CBQ,AF2544C4RGIBQX7Y4JMKMSMXMRRQ | L51: =CONCATENATE(Sheet4!B51,Sheet4!C51) -> Neeraj VishwakarmaSiddharth | M51: =COUNTA(Sheet4!B51:K51) -> 8 | N51: R22EUJ1B1AM0OU,R2K89RVGN8N9MO,R177X9L6ND6OA7,R2YU5RDRT44DE6,R1K5FLRLAUZLKF,R1HAZS2PLM3RRQ,R3EX1BCG3VPANF,R1C72DNWTJGUI2 | O51: Using it with my QC 3 Charger .So far- So good.A Quality cable with a sturdy construction & troublefree performance.,Awesome product go for buy it ðŸ‘,Execellent,Sturdy micro USB cable for Old phones,Super,Product description says 3 feet it's hardly a foot length wire.,Good,Excellent quality cable | P51: ABOUT AMAZONBASICS:xxxxxxxxxxxxxxxxxxxxxxxxxxxxxxAmazon Basics was launched in 2009 & is Amazonâ€™s own inhouse brand for fast moving small electronic consumer goods.Here amazon uses its massive collection of sales data to launch products that are in huge demand & already exist in the market- but at lower prices. Simply put up a similar replica for something successful but at much affordable prices.If something isnâ€™t an immediate hit, Amazon pulls it and moves on.Amazon otherwise is like an online marketplace where it provides a portal for various sellers to sell their product BUT with amazonbasics - Amazon is selling its own product at its own marketplace .Here it derives the benefit of eliminating any intermediate distributors or retailers & hence amazonbasics branded products are available for a lower price attracting bulk customers online.As an additional benefit, Amazonbasics products are delivered free to prime members & are covered under amazon warranty for all and hence any claim or replacement procedures are highly streamlined & immediately taken care of.ABOUT OUR PRODUCT ( REQUIREMENT vs ACTUAL):xxxxxxxxxxxxxxxxxxxxxxxxxxxxxxxxxxxxxxxxxxxxxxxxxxxxxxI recently purchased a new Qualcomm 3 Qbix car charger & was looking for a cable with USB A to Micro B connector. I listed my priorities under various heads to come up with a conclusion and let us compare the actual product based upon my initial requirements:1.) DATA EXCHANGE:*****************************Since it was to be primarily used for fast mobile devices charging in car, Data exchange capability was not much of my concern. Preference though would surely have been a USB 3 but it didnâ€™t bother me if I could only get a USB 2.0 too.ACTUAL PRODUCT: I did try to copy a movie file just for the sake of testing data exchange and I found it to be pretty well. I did not capture any speed data but then we all know speed of data transfer also varies with the type of data being transferred. The more variety of data being transferred simultaneously the lower will be the speed.2.) LENGTH OF THE CABLE :**************************************Again since I could not afford to have a lengthy loop of cable bunched around my gear knob, I preferred to keep it short & simple hence my only lookout was upto around a meter or below.ACTUAL PRODUCT: The cable came nicely packed in a paper packet and was precisely 0.9 meters or approximately 3 feet long. The length was sufficient for me to plug-in any of the mobile devices to my car charger at the drivers or the side passengerâ€™s seat.3.) TANGLE FREE/ FLEXIBILITY/ STRENGTH STANDARDS:**************************************************************************I am not particularly a fan of those stubborn braided wires which are so hard that they retain the shape in which they are bent. I wanted something that was thick yet flexible enough to acquire a circular shape when bunched.ACTUAL PRODUCT: The cable received looked exactly as shown over the site with good flexibility , reasonable thickness & a sturdy intermediate cable. The whole construction of the cable due itâ€™s cable size & flexibility is almost tangle-free.The associated cable was not exactly thick but canâ€™t be termed as thin or delicate too. Itâ€™s not the thickest Iâ€™ve seen but then thickest doesnâ€™t always means most durable. Given my application itâ€™s more than just suitable.The overall built & quality of the cable & insulation looks promising enough to last few years. Even if used for other than car charging it looks durable enough to last long.I had further shortlisted mansaa & an amkette cable for the same purpose but they were too long for my requirement.4.) COMPACT MOULDED CONNECTORS:*********************************************************Had an inclination towards moulded connectors to avoid any issues where the connectors break open exposing the terminal PCBs.ACTUAL PRODUCT : There are no complaints regarding the connectors of the actual cable. The connectors are perfectly moulded without any joints or risks of splitting open. The connector casings are further quite compact at terminals to fit in comfortably at scarce spaces.The connector ports are sturdy enough both at USB A & micro B ports. The micro B port pins lock securely onto the charging mobile devices which is quite good.No signs of loose construction.Being Gold-plated is more of a misleading & fancy term(in this case) as most of the metal ports designed today already have a corrosion resistance & nobody is going to use them in saline sea water anyways.5.) AVAILABILITY OF TIES/VELCRO STRAPS :***********************************************************As per my intended use in a car where compactness was of paramount importance, I expected an included cable tie or a Velcro strap would be a nice add-on to properly adjust & arrange the cable as per requirement.ACTUAL PRODUCT: This I miss the most in the provided actual cable, there is no provision of an included strap or cable tie through which I could adjust my required cable length easily.6.) DECENT CURRENT HANDLING CAPABILITY:******************************************************************On the newest QC 3.0 certified chargers the current transmission can go up to 3.4 amps in certain cases hence the cable needed to have a decent current handling ability.ACTUAL PRODUCT : The actual cable has a nameplate rating of handling up to 2.1 amps against demands at new QC 3.0 chargers that could go up to 3.4 amps. Here, let me clear out that the latest QC chargers vary voltage to current ratios to achieve desired fast charging & thus it is not like a continuous flow of 3.4 amps is there, it keeps on reducing hence cable ratings designed for a continuous current handling of anything above 2.0 amps would sufficiently work with QC 3.0 chargers.Have tried it safely multiple times charging my Samsung S7 from 10 % without the cable getting hot.7.) WARRANTY:************************Comes with a 1 year warranty as expected. Not the best in the industry but reasonable.OTHER OBSERVATIONS:*************************************Apart from the above listed features, the other details of the actual product received worth mentioning are:8.) The cable is manufactured in China & imported by amazon warehouse dealers under the brand name & philosophy of amazonbasics.9.) The cable has a manufacturing date of Oct 2017 & it was imported to India in Dec 2017.10.) The cable has a MRP tag of 495 bucks however I purchased it online for 269 bucks.being a prime member shipping was free.11.) A customer care toll free number & email is also printed over the label for registration of any consumer grievances.FINAL VERDICT:xxxxxxxxxxxxxxxxxxIt has been few days since I have received & been using this product. So far everything from construction to performance seems to be convincing enough to recommend it and for a price of around 260 I suppose, its worth it.Will surely update if any malfunction is observed.,Worth for buy!,The quality that amazon basics at times give at cheap prices is beyond imagination. simply superb, goverment shouldnt hinder amazon products , amazon products rather gives competition to local qualityless products which consumers are forced to buy beacause they have no quality competition. Make in india is good, but if the make in india products are simple cheap copies of branded products without any investment in R and D, without R and D make in india would never be successfull and ousting companies like amazon will only lead to loss for consumers , govt should infact encourage such competition.,Amazon basics provides one of the best cables available for charging your phone or connecting devices.As an past customer of many cables from Amazon this cable doesn't also disappoint,Supports fast charging for all my Samsung phones.I use Samsung a9pro 2016, Samsung s8plus 2017, which this cable is compatible with .Very sturdy, thick and very long. 6 ftVery affordable pricing. Thanks AmazonI also use a USB c cable for my Samsung s20fe.,Super,Product charging is ok.. however it's mere 1 foot in length.. the vendor could have mentioned correct product description.. there is no need to mislead.. too early to say performance as I have received it today.,Good,I have bought many cheap chinese micro usb cable in Rs 50 and Rs 100 of ubon and of many other chinese local companies,and none of them worked properly.Finall i decided to go for this.And it is charging as well transferring data, without any issue and i am very happy with my purchaseMy advice : Dont buy, cheap chinese local cables of.You will have to throw them in dustbean after some time.Better buy this one. | Q51: https://m.media-amazon.com/images/W/WEBP_402378-T1/images/I/31nrDWDT8+L._SX300_SY300_.jpg | R51: https://www.amazon.in/AmazonBasics-Micro-Charging-Android-Phones/dp/B07232M876/ref=sr_1_53?qid=1672909126&s=electronics&sr=1-53
A52: =LEFT(B52,LEN(B52)-1) -> B07P681N6 | B52: B07P681N66 | C52: =CONCATENATE(Sheet2!B52,Sheet2!C52) -> TP-LinkAC600 | D52: Computers&Accessories | E52: $1,199 | F52: $2,199 | G52: 0.45 | H52: 4.4 | I52: 24780 | J52: High-Speed Wi-Fi â€”â€” 256QAM support increases the 2.4 GHz data rate from 150 Mbps to 200 Mbps, 200 Mbps on the 2.4 GHz band and 433 Mbps on the 5 GHz band, ensure you fully enjoy fast AC Wi-Fi.|Dual Band Wireless â€”â€” 2.4 GHz and 5 GHz band provide flexible connectivity, giving your devices access to the latest dual-band Wi-Fi router for faster speed and extended range|High-Gain Antenna â€”â€” A 5dBi high-gain antenna greatly enhances the reception and transmission signal strength of the USB adapter|Supports the Latest Operating Systems â€”â€” Fully compatible with Windows 11/10/8.1/8/7/XP, Mac OS 10.15 and earlier|In an unlikely case of product quality related issue, we may ask you to reach out to brandâ€™s customer service support and seek resolution. We will require brand proof of issue to process replacement request. | K52: AHDFR3PDKEBV72HXRL3RJJLS3YYA,AHYUZ2BLKNN6UJLFYWCXCEFZTOVQ,AHBST4ZJ5665DV2TCR4W4J2OI3DA,AGHPOFCHZ73Q2Q2IFTCJLUSEL2NQ,AHOMYGLSLJLCOT7Z24PZSVJY3LJQ,AESJE2EZD7S7WOYBN7RE7ZF3J2MA,AF23GXF525XSMXPJBEHP4SPKOZNQ,AFX5NHAAOUKKENAT6GWNKY3X5YTQ | L52: =CONCATENATE(Sheet4!B52,Sheet4!C52) -> AnonymousSugam Agrawal | M52: =COUNTA(Sheet4!B52:K52) -> 8 | N52: R2GUL8IL005EGF,R3NZCVYJBN0CPD,RHUJOS46Q51UG,R1ZW4PQHUECROJ,R7F86XL2S6MY,R1JRRVOFWQAC4C,R2WZHK2E301YV,R10J01VHCKFB42 | O52: Works flawlessly on Ubuntu 22.04 (if installed correctly),Best for kali. Do not read another review.,Nice product,From 0 to 70 â€¦,Good External Wifi Signal Provider,Superb,Awesome and easy to use,Good product | P52: I am using this on an old Mac Mini, since the Broadcom proprietary drivers aren't available and the replacement B43 drivers don't allow for sufficient download speeds, at least in my experience. I got this device up and running with Ubuntu 22.04 with Linux 5.15.0-56-generic.Google search for "morrownr/8821au-20210708" and use the driver on Github. I'm using the product "TP-Link AC600" btw. If you are using the other variant sold on Amazon, use lsusb and find out which network interface you are going to have to install drivers for. GIYF.I will admit, this is probably going to be hard for someone who is not generally comfortable with a shell, bash for example. But even though I had never used dkms or iw before, the Github repo along with the build tools available in the jammy repo made it easy enough to get the device working (read the GitHub Readme).To be sure I first got the drivers working in a local Ubuntu VM using Guest Additions to connect to the USB device directly from the guest OS, which also worked.Ultimately, I installed the OS on the host and setup the drivers using USB tethering. I then got the same download speed using this device I was previously getting on my other network interfaces on Windows and Mac, but now on Ubuntu.The device itself is a bit sensitive to the antenna direction when it comes to the impact on download speed. Have been using for about a month now without complaints.,Do not go for reviews that say that it do not support kali. Me and some of my friends all are using it for Wi-Fi hacking and it works really well, it also supports monitor mode. If you are having issues in connecting it to your Kali machine then just go through the web surf a bit and you will find relevant articles on how to connect this TP link adapter to your kali machine. There is also a driver of realtek which you might need to install to make it work in your kali machine.I have given it 4 stars just because the performance if not good as the Alpha adapters which is reasonable for this range of price but in this range and for as a beginner it is the best adapter you can buy.,Nice product. Working fine. My PC is now 5G Price is too high so giving 4 star,Got the Wi-Fi in one of the rooms from 0 to 70%. Has been working well since a month now. Good alternative to a repeater if only a single device needs to access the Wi-Fi from a corner.,The product is very nice and have good Wifi signal. Using this for over a month now, no complain. But when it for the first time, you need to install the driver on your desktop/laptop from the TP link website to make it operational, which is not very well explained in the manual.,This product is very good,I have buy this product because my laptop donâ€™t support wifi 5ghz band, in 2.5 ghz I receive 30-40Mbps speed only but my broadband plan is 150Mbps.1. Easy to use plug and play windows 102. Good signal i am using another room from router no signal drop , I receive full signal.3. Little bit expensive but go with this because of good signal.4. I receive 170Mbps + download and 110Mbps upload speed on 5ghz and my broadband plan is 150Mbps.I highly recommend this product.,i purchase this product for company use and this is a very good product. | Q52: https://m.media-amazon.com/images/I/216Q4FqmZVL._SX300_SY300_QL70_FMwebp_.jpg | R52: https://www.amazon.in/TP-Link-Wireless-Adapter-Archer-T2U/dp/B07P681N66/ref=sr_1_54?qid=1672909126&s=electronics&sr=1-54
A53: =LEFT(B53,LEN(B53)-1) -> B0711PVX6 | B53: B0711PVX6Z | C53: =CONCATENATE(Sheet2!B53,Sheet2!C53) -> AmazonBasicsMicro | D53: Computers&Accessories | E53: $179 | F53: $500 | G53: 0.64 | H53: 4.2 | I53: 92595 | J53: Micro usb charging cable for android phones|Supports up to 480 mbps data transmission speed|Ideal for charging android phones and tablets or connecting pc peripherals such as hard drives, printers, and more|Gold-plated connectors resist corrosion for signal purity|Smaller connector designed to fit smaller spaces|Compact connector head works with nearly all cases|Improved charging capability up to 2100 ma | K53: AF7IXQKBUL6NEIQG4R53LMJJUGXQ,AFODI4XXHXHBFFUHK7N5LVKWEXTQ,AGNONTMQDE5KLLDEEB57Z3C5WAEA,AFW6NV5N3FUXV3CNUACPSYC5AB3Q,AEW6KBDGJEWIOQKAW3FP74GMV6TA,AEGT7WPGXXMSH5J3LZLL6CPJ7QMQ,AEKCUG7WMX6KMP6VFBWI3ICW5CBQ,AF2544C4RGIBQX7Y4JMKMSMXMRRQ | L53: =CONCATENATE(Sheet4!B53,Sheet4!C53) -> Neeraj VishwakarmaSiddharth | M53: =COUNTA(Sheet4!B53:K53) -> 8 | N53: R22EUJ1B1AM0OU,R2K89RVGN8N9MO,R177X9L6ND6OA7,R2YU5RDRT44DE6,R1K5FLRLAUZLKF,R1HAZS2PLM3RRQ,R3EX1BCG3VPANF,R1C72DNWTJGUI2 | O53: Using it with my QC 3 Charger .So far- So good.A Quality cable with a sturdy construction & troublefree performance.,Awesome product go for buy it ðŸ‘,Execellent,Sturdy micro USB cable for Old phones,Super,Product description says 3 feet it's hardly a foot length wire.,Good,Excellent quality cable | P53: ABOUT AMAZONBASICS:xxxxxxxxxxxxxxxxxxxxxxxxxxxxxxAmazon Basics was launched in 2009 & is Amazonâ€™s own inhouse brand for fast moving small electronic consumer goods.Here amazon uses its massive collection of sales data to launch products that are in huge demand & already exist in the market- but at lower prices. Simply put up a similar replica for something successful but at much affordable prices.If something isnâ€™t an immediate hit, Amazon pulls it and moves on.Amazon otherwise is like an online marketplace where it provides a portal for various sellers to sell their product BUT with amazonbasics - Amazon is selling its own product at its own marketplace .Here it derives the benefit of eliminating any intermediate distributors or retailers & hence amazonbasics branded products are available for a lower price attracting bulk customers online.As an additional benefit, Amazonbasics products are delivered free to prime members & are covered under amazon warranty for all and hence any claim or replacement procedures are highly streamlined & immediately taken care of.ABOUT OUR PRODUCT ( REQUIREMENT vs ACTUAL):xxxxxxxxxxxxxxxxxxxxxxxxxxxxxxxxxxxxxxxxxxxxxxxxxxxxxxI recently purchased a new Qualcomm 3 Qbix car charger & was looking for a cable with USB A to Micro B connector. I listed my priorities under various heads to come up with a conclusion and let us compare the actual product based upon my initial requirements:1.) DATA EXCHANGE:*****************************Since it was to be primarily used for fast mobile devices charging in car, Data exchange capability was not much of my concern. Preference though would surely have been a USB 3 but it didnâ€™t bother me if I could only get a USB 2.0 too.ACTUAL PRODUCT: I did try to copy a movie file just for the sake of testing data exchange and I found it to be pretty well. I did not capture any speed data but then we all know speed of data transfer also varies with the type of data being transferred. The more variety of data being transferred simultaneously the lower will be the speed.2.) LENGTH OF THE CABLE :**************************************Again since I could not afford to have a lengthy loop of cable bunched around my gear knob, I preferred to keep it short & simple hence my only lookout was upto around a meter or below.ACTUAL PRODUCT: The cable came nicely packed in a paper packet and was precisely 0.9 meters or approximately 3 feet long. The length was sufficient for me to plug-in any of the mobile devices to my car charger at the drivers or the side passengerâ€™s seat.3.) TANGLE FREE/ FLEXIBILITY/ STRENGTH STANDARDS:**************************************************************************I am not particularly a fan of those stubborn braided wires which are so hard that they retain the shape in which they are bent. I wanted something that was thick yet flexible enough to acquire a circular shape when bunched.ACTUAL PRODUCT: The cable received looked exactly as shown over the site with good flexibility , reasonable thickness & a sturdy intermediate cable. The whole construction of the cable due itâ€™s cable size & flexibility is almost tangle-free.The associated cable was not exactly thick but canâ€™t be termed as thin or delicate too. Itâ€™s not the thickest Iâ€™ve seen but then thickest doesnâ€™t always means most durable. Given my application itâ€™s more than just suitable.The overall built & quality of the cable & insulation looks promising enough to last few years. Even if used for other than car charging it looks durable enough to last long.I had further shortlisted mansaa & an amkette cable for the same purpose but they were too long for my requirement.4.) COMPACT MOULDED CONNECTORS:*********************************************************Had an inclination towards moulded connectors to avoid any issues where the connectors break open exposing the terminal PCBs.ACTUAL PRODUCT : There are no complaints regarding the connectors of the actual cable. The connectors are perfectly moulded without any joints or risks of splitting open. The connector casings are further quite compact at terminals to fit in comfortably at scarce spaces.The connector ports are sturdy enough both at USB A & micro B ports. The micro B port pins lock securely onto the charging mobile devices which is quite good.No signs of loose construction.Being Gold-plated is more of a misleading & fancy term(in this case) as most of the metal ports designed today already have a corrosion resistance & nobody is going to use them in saline sea water anyways.5.) AVAILABILITY OF TIES/VELCRO STRAPS :***********************************************************As per my intended use in a car where compactness was of paramount importance, I expected an included cable tie or a Velcro strap would be a nice add-on to properly adjust & arrange the cable as per requirement.ACTUAL PRODUCT: This I miss the most in the provided actual cable, there is no provision of an included strap or cable tie through which I could adjust my required cable length easily.6.) DECENT CURRENT HANDLING CAPABILITY:******************************************************************On the newest QC 3.0 certified chargers the current transmission can go up to 3.4 amps in certain cases hence the cable needed to have a decent current handling ability.ACTUAL PRODUCT : The actual cable has a nameplate rating of handling up to 2.1 amps against demands at new QC 3.0 chargers that could go up to 3.4 amps. Here, let me clear out that the latest QC chargers vary voltage to current ratios to achieve desired fast charging & thus it is not like a continuous flow of 3.4 amps is there, it keeps on reducing hence cable ratings designed for a continuous current handling of anything above 2.0 amps would sufficiently work with QC 3.0 chargers.Have tried it safely multiple times charging my Samsung S7 from 10 % without the cable getting hot.7.) WARRANTY:************************Comes with a 1 year warranty as expected. Not the best in the industry but reasonable.OTHER OBSERVATIONS:*************************************Apart from the above listed features, the other details of the actual product received worth mentioning are:8.) The cable is manufactured in China & imported by amazon warehouse dealers under the brand name & philosophy of amazonbasics.9.) The cable has a manufacturing date of Oct 2017 & it was imported to India in Dec 2017.10.) The cable has a MRP tag of 495 bucks however I purchased it online for 269 bucks.being a prime member shipping was free.11.) A customer care toll free number & email is also printed over the label for registration of any consumer grievances.FINAL VERDICT:xxxxxxxxxxxxxxxxxxIt has been few days since I have received & been using this product. So far everything from construction to performance seems to be convincing enough to recommend it and for a price of around 260 I suppose, its worth it.Will surely update if any malfunction is observed.,Worth for buy!,The quality that amazon basics at times give at cheap prices is beyond imagination. simply superb, goverment shouldnt hinder amazon products , amazon products rather gives competition to local qualityless products which consumers are forced to buy beacause they have no quality competition. Make in india is good, but if the make in india products are simple cheap copies of branded products without any investment in R and D, without R and D make in india would never be successfull and ousting companies like amazon will only lead to loss for consumers , govt should infact encourage such competition.,Amazon basics provides one of the best cables available for charging your phone or connecting devices.As an past customer of many cables from Amazon this cable doesn't also disappoint,Supports fast charging for all my Samsung phones.I use Samsung a9pro 2016, Samsung s8plus 2017, which this cable is compatible with .Very sturdy, thick and very long. 6 ftVery affordable pricing. Thanks AmazonI also use a USB c cable for my Samsung s20fe.,Super,Product charging is ok.. however it's mere 1 foot in length.. the vendor could have mentioned correct product description.. there is no need to mislead.. too early to say performance as I have received it today.,Good,I have bought many cheap chinese micro usb cable in Rs 50 and Rs 100 of ubon and of many other chinese local companies,and none of them worked properly.Finall i decided to go for this.And it is charging as well transferring data, without any issue and i am very happy with my purchaseMy advice : Dont buy, cheap chinese local cables of.You will have to throw them in dustbean after some time.Better buy this one. | Q53: https://m.media-amazon.com/images/W/WEBP_402378-T1/images/I/31iESA2h2gL._SY300_SX300_QL70_FMwebp_.jpg | R53: https://www.amazon.in/AmazonBasics-Micro-Charging-Android-Phones/dp/B0711PVX6Z/ref=sr_1_55?qid=1672909126&s=electronics&sr=1-55
A54: =LEFT(B54,LEN(B54)-1) -> B082T6V3D | B54: B082T6V3DT | C54: =CONCATENATE(Sheet2!B54,Sheet2!C54) -> AmazonBasicsNew | D54: Computers&Accessories | E54: $799 | F54: $2,100 | G54: 0.62 | H54: 4.3 | I54: 8188 | J54: Added Protection: An additional layer of protection has been added to the Lightning and USB ends to improve durability and reduce fraying; | K54: AFWJSD4AVIM6DC3YA63G2QPENQSQ,AGKSW3FNH3REYN3OKPKJN4KWXLMQ,AEI7HJU4RFV6NR5WSRDQV5ZSRYSA,AGFN3SLEECW6DYL2CVGLIHJCVVHA,AGY7ZX7WDDSGAZJBPPS3MCIL7U7A,AEX422U2J6S45PAKDJIFJB7WNVLQ,AEHU6ETDR7HVQOGLKITDETHZEO7A,AE7VL5JTR7ZZ67UPBM6KP2NYEOYQ | L54: =CONCATENATE(Sheet4!B54,Sheet4!C54) -> Arun vermaArv | M54: =COUNTA(Sheet4!B54:K54) -> 8 | N54: R1Q0PEVL6X8WZJ,RW0MMI9AUXK5J,R2F3ACPBFRCFSK,R2SB3XYC8XHNUQ,R5L8G10EKZ9ZR,R3W2X53D3BLIBR,R29J3JSPZYQYCM,R35I0ZZH2J58P7 | O54: Good product but costly,Itâ€™s really long n sturdy no homo ðŸ”¥,Takes longer to charge than the regular cable,Quality is really good,iPhone X pink charging cable long one â˜ï¸,A good purchase,It charges fine for me,Absolutely fantastic USBðŸ‘ðŸ‘ðŸ‘ | P54: It cost should be under Rs. 500,Buy it,Color is as per the photo but takes longer to charge. Also doesnâ€™t charge on all sockets.Seems to work better when plugged in directly in the laptop.,Length of the cable is long so that you can happily use it for long distance as week and quality is really good,1 meter pInk charging wire for iPhone X long and strong one for use..,I have been using this lighting cable for almost a month now and the cable turned out exactly as it was shown. I took the rose gold one that matches my phoneâ€™s color. Although the metal ends of the cable was rose gold, but the whole cable was pink, which I didnâ€™t like. I went for the 2m long cable so that i can use it conveniently even if it is charging. Though itâ€™s kinda bulky, yet serves itâ€™s purpose. Charging speed is fast and efficient just like the original cable had. Also quite durable and sturdy. My Appleâ€™s original lighting cable had some problem while charging so I purchased this one after watching many YouTube videos and reviews. It was indeed a good purchase.,Itâ€™s long and good,Itâ€™s a superb product in terms of sturdiness, looks, and charging speed. | Q54: https://m.media-amazon.com/images/I/31kw1RgU5yL._SX300_SY300_QL70_FMwebp_.jpg | R54: https://www.amazon.in/AmazonBasics-Nylon-Braided-Lightning-Cable/dp/B082T6V3DT/ref=sr_1_57?qid=1672909126&s=electronics&sr=1-57
A55: =LEFT(B55,LEN(B55)-1) -> B07MKFNHK | B55: B07MKFNHKG | C55: =CONCATENATE(Sheet2!B55,Sheet2!C55) -> VW80 | D55: Electronics | E55: $6,999 | F55: $12,999 | G55: 0.46 | H55: 4.2 | I55: 4003 | J55: Resolution: HD Ready (1366x768) | Refresh Rate: 60 hertz | Viewing Angle: 178 degrees|Connectivity: 2 HDMI ports to connect set top box, Blu Ray players, gaming console | 2 USB ports to connect hard drives and other USB devices|Sound : 20 Watts output | Powerful Stereo Output | Power Audio, Music Equalizer|Display: A+ Grade Panel | IPE Technology | True Colour | Cinema Zoom | Slim Bezel | Cinema Mode|Warranty Information: 1 year warranty provided by Visio World from date of purchase|Installation: For requesting installation/wall mounting/demo of this product once delivered, please directly call Visio World support on (Please visit brand website for toll free numbers) and provide product's model name as well as seller's details mentioned on the invoice|Easy returns: This product is eligible for replacement/refund within 10 days of delivery in case of any product defects, damage or features not matching the description provided | K55: AFIU4APGHOFMXEOVMSQMYKMZ46QQ,AEOFYPCJJQYCKISUR6EC66IZH23Q,AFZSMXS2MILXOSTT2ZEJDE3W7TLQ,AFREYXJZFUSZT7YHDJ4JOF67O6VQ,AGMQDZGGSEBXX4KBJOBAGIFI36OA,AHJ7INNUX3KZSEZRJKFMRJAX7TZA,AGYTCTSUZJJZTK2XVADTQI5MYUFQ,AFZHLQMILG47ZESR5TLNB5QK66HQ | L55: =CONCATENATE(Sheet4!B55,Sheet4!C55) -> Amazon CustomerYousuf | M55: =COUNTA(Sheet4!B55:K55) -> 8 | N55: RFZ1X95QMXWFZ,R1P8SL54VCWSMQ,RSWY4LT0L7TCL,R2GEJ1MJF28QVM,R2K5NT5XE6LM6T,R26BYG85S4SSVY,R3HB3IY6922TUM,R3A3CEQUX9QMFE | O55: Firestick plugging in issue, otherwise a good deal,Cheap & Best Product,Low budget led tv,Nice tv,Very. Good,Why is the installation guy asking for installation charge?,Good Budget Tv,Good TV but after using it for 9 days, has found a flaw | P55: I got this for 6k. At this price point, I believe the TV provides decent quality. You shouldn't expect amazing quality anyway from a 1366x768 screen resolution. The audio is also okay. Beyond 50 the audio starts cracking.From a viewing distance of 6-8ft the quality looks good.PLEASE NOTE: you will STRUGGLE quite a bit to directly add a firestick to the HDMI port. They have given some other ports right next to the HDMI ports because of which the firestick doesn't have proper space to fit properly unless you really shove it in there. My suggestion is to get an HDMI extender for it.Overall, I'd say, for a small room, it's a 7/10.,Value for money, Satisfied with the product till now,This Led tv low budget Good ðŸ‘ Performance but picture & audio not good,https://m.media-amazon.com/images/I/61QvXYP2McL._SY88.jpg,Good,Tv is great but the installation guy asked me for 400â‚¹ paid installation... Misleading information but again for this price it's good tv. Don't pay installation guy you can do it yourself,,I will give it 4 stars out of 5. I bought this 32 inch VW at 6150 after discounts. Picture quality and sound quality is good.I added firestick to it and it voila became smart tv. The connections to attach these usbs are at the bottom part of the tv which is slightly different from other tvs.So far, working as it should.Revising this after 9 days, the tv is not responding to switch off button. This is happening more when i watch the tv for a few hours and then when i switch off the tv with the firestick remote, the yellow colour indicator down below does not turn red, instead it remains yellow. As far as screen is concerned, the tv's screen changes to black whitish, seems to me that the tv goes into hibernation or sleep mode. This is a fault of the tv as a normal tv should swith off completely and the indicator should turn red. i have called technician tomorrow and if he checks and if he agrees, then i should get a replacement as i got still 2 days time to replace it.Just a helping note for people buying this tv: if you are going to connect firestick to it, as it asks for the brand name of the tv, you can select VU and it will perfectly work on your firestick. Thanks and enjoy! | Q55: https://m.media-amazon.com/images/I/418GxB04szL._SY300_SX300_QL70_FMwebp_.jpg | R55: https://www.amazon.in/Visio-World-inches-VW32A-Ready/dp/B07MKFNHKG/ref=sr_1_58?qid=1672909126&s=electronics&sr=1-58
A56: =LEFT(B56,LEN(B56)-1) -> B0BFWGBX6 | B56: B0BFWGBX61 | C56: =CONCATENATE(Sheet2!B56,Sheet2!C56) -> AmbraneUnbreakable | D56: Computers&Accessories | E56: $199 | F56: $349 | G56: 0.43 | H56: 4.1 | I56: 314 | J56: Compatible with all Type C enabled devices, be it an android smartphone (Mi, Samsung, Oppo, Vivo, Realme, OnePlus, etc), tablet, laptop (Macbook, Chromebook, etc)|Supports Quick Charging (2.0/3.0)|Unbreakable â€“ Made of special braided outer with rugged interior bindings, it is ultra-durable cable that wonâ€™t be affected by daily rough usage|Ideal Length â€“ It has ideal length of 1.5 meters which is neither too short like your typical 1meter cable or too long like a 2meters cable | K56: AF36YUJUEUU3SA42PFAULM2F5RYA,AESE26BMILSD6E4AVO3YM76G4UPA,AFFB6IUQ46CEIYZ2U7OAYVKAL5RQ,AGHGLXUVEHN4NFA3CCYIUFWBIC4A,AELBYFRFAGLMXQQJKVDUWO7QX2VQ,AHF4A3ZGP7G6JLXAAJ77O2QDJSEQ,AEGZCGGDNS4ZRNPG3CDULRVB5Z5A,AE4YGDAAZX7ZDDGP4BTONW72CMIA | L56: =CONCATENATE(Sheet4!B56,Sheet4!C56) -> Vipan AgnihotriHitender singh | M56: =COUNTA(Sheet4!B56:K56) -> 8 | N56: RQAF3Q7KCEGHP,R3CBLDFSRTKKYA,R3PZ3ENFIS7IJG,R2ACW4FTIVQJ77,R3K8YFINS1P9XN,R16G76XSWF9WTZ,R3O8ZTH4RRO02J,RXCDPPX5ZV2WX | O56: Good product,Strong and powerful,Useful product.,Very nice ðŸ‘Œ ðŸ‘ product,Good ðŸ‘ðŸ»,Good,USB,Strong buid , study design , charging speed â˜¹ï¸ | P56: quality is ok ok only,Well go for it good cable,Useful product in this price.,Very nice,Good,Charging speed supports up to 25V,Product quantity is excellent but very slow charging,Cable is absolutely good looking , strong , durable. But not support fast charging as I expected , I checked speed with stopwatch , I am using Realme phone , with my original realme 20w charger and original cable the time takes to charge 68% to 69% is 34 sec. But with this ambrane cable it takes 1 min 32 sec to charge from 69% to 70%.Little disappointed with charging Speed , overall product is goodHope this review help you guys ! | Q56: https://m.media-amazon.com/images/W/WEBP_402378-T2/images/I/41rbKciLrcL._SX300_SY300_QL70_FMwebp_.jpg | R56: https://www.amazon.in/Ambrane-Unbreakable-Charging-RCT15-Supports/dp/B0BFWGBX61/ref=sr_1_59?qid=1672909126&s=electronics&sr=1-59
A57: =LEFT(B57,LEN(B57)-1) -> B01N90RZ4 | B57: B01N90RZ4M | C57: =CONCATENATE(Sheet2!B57,Sheet2!C57) -> TataSky | D57: Electronics | E57: $230 | F57: $499 | G57: 0.54 | H57: 3.7 | I57: 2960 | J57: Universal remote control|Ensures long lastinga and consistent performance|Sturdy built | K57: AEOM4KLP4SKKVSOCAMP7ORLGPGUA,AE4VKQV43AJEZDWE4WVJWFDY6RVA,AGAUULKME2K6WYOHPLL5XT5XLQGA,AFP5TMKVX6PTNYNMLHFCVDXCTN4A,AGNYTWD4ORSSUWNGICU3TRNRMRIA,AGQCT5HPQJXUN2FVZNCBSEQIYDPQ,AHWMHRT7TOMXLYI3XYM4K4OY3NEQ,AEXIFRBO4546MRMJHYKE2AH26VCQ | L57: =CONCATENATE(Sheet4!B57,Sheet4!C57) -> Jacob.Dinesh Ahuja | M57: =COUNTA(Sheet4!B57:K57) -> 8 | N57: RJ19CW7WCSFUI,R3W3PK017U6SIG,RJB32KHP5D5O3,R3POHJCTG2XX71,R1EKLLUH4KRRS9,R2S00YTPGW362,R24N5IPVE7LGCM,R2ZOR8P02Z5J8F | O57: The button contacts are not very good.,Okay for temporary use,Seller: Smart Place Store; Remote Not original,It's below average,Ok,Tata sky remote,Tatasky remote.,Working one, but parts are flimsy. | P57: The button contacts are not very good.,Doesn't look as standard and durable as original product,Purchased from Seller: Smart Place Store;Remote works but low build quality. Not original.,Material is very average,Works as described,Not meet expectations,but O K.,It's a good product.,Parts are likely to break even in case of small fall. | Q57: https://m.media-amazon.com/images/I/315GdnF+LcL._SY300_SX300_.jpg | R57: https://www.amazon.in/TATASKY-Universal-Remote/dp/B01N90RZ4M/ref=sr_1_60?qid=1672909126&s=electronics&sr=1-60
A58: =LEFT(B58,LEN(B58)-1) -> B0088TKTY | B58: B0088TKTY2 | C58: =CONCATENATE(Sheet2!B58,Sheet2!C58) -> TP-LINKWiFi | D58: Computers&Accessories | E58: $649 | F58: $1,399 | G58: 0.54 | H58: 4.2 | I58: 1,79,691 | J58: 300 Mbps Wi-Fi â€”â€” 300Mbps wireless speed ideal for smooth HD video, voice streaming and online gaming|Design â€”â€” Mini-sized design for convenient portability with a reliable high performance|SoftAP Mode â€”â€” Turn a wired internet connection to a PC or Laptop into a Wi-Fi hotspot|Â·Â WPS â€”â€”Â Easily setup a secure wireless connection with one-touch WPS button|Compatibility â€”â€” Supports Windows 11/10/8.1/8/7/XP,Â Mac OS 10.15 and earlier, Linux|Interface â€”â€” USB 2.0|In an unlikely case of product quality related issue, we may ask you to reach out to brandâ€™s customer service support and seek resolution. We will require brand proof of issue to process replacement request. | K58: AGV3IEFANZCKECFGUM42MRH5FNOA,AEBO7NWCNXKT4AESAN443HQH35FQ,AE7GD3VRRYQEAHDR7FXJIR23INYA,AHPAW24BI5X2GCX5M2LHI72VSJJQ,AE2VXY4CFO36MDSIMPG43XHNF4GA,AHHQEKUNVETALN7DTRHUQ2WAWEKQ,AFMIFTNTUD5PIHGONWOTRMMZ5EBA,AHOJBIZVVIIFJKRREY4B6ESVA4KA | L58: =CONCATENATE(Sheet4!B58,Sheet4!C58) -> Azhar JuManAnirudh Sood | M58: =COUNTA(Sheet4!B58:K58) -> 8 | N58: R1LW6NWSVTVZ2H,R3VR5WFKUS15C5,R2F6GC79OYWUKQ,R3QZ19MECGWG9A,R2MPU42MYK7GPO,R33DVXFB4VYPZZ,R1SQ7OGFR4JRUR,R1S5F9QI0M1VBZ | O58: Works on linux for me. Get the model with antenna.,Does what it say but other brands available at lesser price,Easy Handle,Great product,Perfect working,Speed is perfect,Great Design, Build, Connectivity Range, Packaging and other features but no linux support since v2,Very good | P58: I use this to connect an old PC to internet. I tried lubuntu 20 and ubuntu 22, it worked out of the box in both, didn't have to do any setup. There's an extender cable so you can place this in a comfortable place. Get the model with antenna because otherwise you'll have range problems if you're not directly in line of sight from your wifi router.,The wifi dongle is a simple plug & play device, will start catching available networks right after you plug it into your USB port, no additional installations/ softwares requires. Signal strength is good.... just wonder what would be different in other adapters of lesser known brands which are available at a much more competitive pricing, hence a star less.,Pros:*Easy to use & Portable*Can be connected to Mobile Hotspot and used in PC( Budget Friendly)*Less installation process*No heating issues & Good Coverage*Best alternative for USB Tethering (phone's battery may get damaged for long term run with Tethering)Cons:*Internet connection speed varies at times, also depends on your modem or cellular connection*Issues occur while installing via CD, which is available along with the product( Installation driver can be downloaded from TP-Link site)*Needed to reconnect the adapter every time system is turned ON*Will not work if your software has some issues, so encountered any just update your system(worked for me)*Support Center is worse, calls are unattended most of the times or just visit nearby storeConclusion:Brought this @499/-Ideal for users who don't need very high speed internet usage,a good alternative for USB Tethering and are on Budge(1080p Youtube videos can be easily played with this without any interruptions),wifi connectivity is a great good result for me. however, some jitter problems did exist.,This is perfect device to connect wifi. Go for it.,This wifi adopter is good working,(Pictures attached)Size/Design: â˜… â˜… â˜… â˜… â˜…Build Quality: â˜… â˜… â˜… â˜… â˜…Packaging: â˜… â˜… â˜… â˜… â˜…Software: â˜… â˜… â˜… â˜…Speed: â˜… â˜… â˜… â˜… â˜…Connectivity: â˜… â˜… â˜… â˜… â˜…Experience: â˜… â˜… â˜… â˜… â˜…Warranty: â˜… â˜… â˜… â˜… â˜…Size and Design:The best part about this is that it is very compact in size and very sober and elegant in design. This is a big plus as it is easy plug in and use, add to it the good sober design.Build Quality:The build quality is undoubtedly superb. Just no qualms about that, at all. When held, it doesnt give off that cheap and flimsy product-like feeling. It is good sturdy with its build quality.Packaging:This part is also a big plus as the item was well cushioned and packaged with all the necessary items that ensured that no damage could have been caused to the product during transportation. This ensures that I as a customer have received something not damaged internally already.Software:This is actually good but not great part with the product.The good part is that a CD has been provided with it along with a manual.The not great part is that NO LINUX SUPPORT has been given from Version 2 onwards. This is bad, really.Speed:It easily supports net speeds upto 300 Mbps. Practically speaking, I have tested it at my home and it easily supports net speed of over 100-150 Mbps without a sigh.On testing I found that it did connect to 5GHz network, without any issue.Connectivity:Please mark its not feet its metres. Multiply metres x 3 to get the distance in feet.It easily connects to my laptop or phone from 7 metres across one room. So thats 21 feet. I mean even our old bluetooth used to connect to about 15 ft.So 20-25 feet is not at all an issue with this. This is the big plus I found with the product.Experience:From this point of view, so far except the linux non-compatibility issue, I found no other flaws with this product.So overall its a great product.Warranty:Its 3 years so I am assured that atleast for 3 years I am tension-free and not just 1 year, contrary to most electronic items today that only provide 1 year warranty with their items.,Best adapter I have bought ever. Works nicely seemless connectivity | Q58: https://m.media-amazon.com/images/I/41jxZkzNcnL._SX300_SY300_QL70_FMwebp_.jpg | R58: https://www.amazon.in/TP-Link-TL-WN823N-300Mbps-Wireless-N-Adapter/dp/B0088TKTY2/ref=sr_1_61?qid=1672909126&s=electronics&sr=1-61
A59: =LEFT(B59,LEN(B59)-1) -> B09Q5SWVB | B59: B09Q5SWVBJ | C59: =CONCATENATE(Sheet2!B59,Sheet2!C59) -> OnePlus80 | D59: Electronics | E59: $15,999 | F59: $21,999 | G59: 0.27 | H59: 4.2 | I59: 34899 | J59: Resolution : HD Ready (1366x768) | Refresh Rate : 60 Hertz|Connectivity: 2 HDMI ports to connect set top box, Blu Ray players, gaming console | 2 USB ports to connect hard drives and other USB devices | Dual-band Wi-Fi|Sound : 20 Watts Output | Dolby Audio | Dolby Atmos Decoding|Smart TV features: Latest Android TV 11, OnePlus Connect Ecosystem, Google Assistant, Chromecast, Miracast, DLNA, Auto Low Latency Mode | Supported Apps : Netflix, Youtube, Prime Video, Hotstar, SonyLiv, Hungama, JioCinema, Zee5, Eros Now, Oxygen Play|Display : Bezel-less Design | LED Panel | Anti-Aliasing | Gamma Engine | Decoding of HDR10+, HDR10, HLG|Warranty Information: 1 year comprehensive warranty and additional 1 year on panel provided by the manufacturer from date of purchase|Installation/Wall mounting/demo will be arranged by Amazon Home Services. For any other information, please contact Amazon customer support | Wall Mount is not included in the box and will be charged extra at the time of installation | K59: AFUT7ANZTZYGLXU65EQ2D5OP6UMA,AGT7YYJVUC6ZHRKQHVUQZMDNLXEA,AE7OMK3IQJR2U2JZE2HQ4BKSPA6A,AGCRCU432TIF4J2EL7GBEWOIULGQ,AERQBL3BISJQVHO3RLOOA4HKZX5A,AHIWNZ2HBQAHVE4OWODM6WH4PMOQ,AH2347WTE3DZ3TIZUB5LCLZPAYEQ,AHIH3QL5XONYJWEXF7VKLFHZBDJA | L59: =CONCATENATE(Sheet4!B59,Sheet4!C59) -> ATHARVA BONDRESujitkumar Thorat | M59: =COUNTA(Sheet4!B59:K59) -> 8 | N59: R3COVVOP2R7Z28,R2T6WHEO2ONNDD,RUFFV2QR43OCM,R2LK4WPIHJ7WDA,R6IPR9FHZ5BOT,R3DU4LFGTAIEMN,RVHHM5FW31JN1,R1QA870NJWIODF | O59: Worthy and most affordable - Great TV,Good product,It's really worth the money but,Better product in this budget,Product review,nice tv,Best product,Budget friendly TV | P59: This OnePlus TV is great if you want a affordable and middle range features TV. I got it in the offer and it was totally worth it.Pros:-1. Sound is awesome - 100% satisfied with the quality of sound. Dolby Audio 20W speakers are really great for sure affordable TV.2. Size and slim - It is slim and looks stylish. Very light weight and handy to install.3. Easy to install and mount to wall.4. Tye software installation and set up is very easy and anyone can do it at home.5. It gets integrated with mobile apps, remote, WiFi networks very quickly and easily.6. The overall sign up process and app installations are quick and automatic.7. It supports all the smart features like Netflix, Prime and YouTube. It is easily installable and sign-in to start using quickly.8. It is also easy to scan the Setup box channels and start viewing them.Cons:-1. Picture quality is 776p. It's average and not very clear. But it is worth the price range. I'll not complaint as the cost of TV is very affordable and this quality is justified.2. Bluetooth and WiFi connection can disconnect sometimes and cause some issues. I encountered this disconnect issue and had to reset complete device and do the complete sign up again.Rest all is very good and loved this product. I feel it was worth ordering. If you are looking something is medium range and only need it for your old parents and don't have extensive smart use then 100% go for this.If you want to use a lot of smart features and OTT platforms and watch movies, and sports then go for better version with full HD and 4K quality. This TV will not give good experience for sports due to less picture quality but it's very good for daily family shows and TV channels.One last thing I want to express and I'm ver disappointed about is this.I got my order delivered on Friday and I scheduled my installation for Saturday. But nobody turned up that day and I had to reschedule it for Tuesday morning, and even today nobody turned up. I got a call from Amazon to reschedule it for Tuesday evening and still, nobody turned up.This is very very bad and irresponsible service by OnePlus and Amazon. I'm very disappointed with the service and highly criticize this behavior. A company should always take care of its customer satisfaction and you have failed in doing this.What do you guys expect us to do? Wait for 5 to 6 days to get my TV installed even when it's been delivered and wait for you guys to come after so many days. Even when I'm having my smart TV delivered to my home, I have to wait and not enjoy it because you guys have not done your job properly.At least keep some decency and respect the customers who are paying a big amount and ordering a big item from your company. You should take care that the money I spent has been worth it and not facing any issues. Highly disappointed with this behavior and service.,Good product,Connectivity is faster,But performance is little bit slower,,The biggest problem I face is it don't have a aux cable so I'm not able to connect my sound bar......the HDMI port is useless it won't work .so,i connect it via bluetooth but the problem is that it won't connect automatically, everytime I on the tv i need to connect it manually it's a basic feature which is not provided in this tv then another drawback is that it was fast at the beginning now it's been 4 months and it's super laggy .....even after the update its just the same.....yeaa but in this price range the picture quality is outstanding......that's all,Good quality in picture and volume is little bit low other than that product is nice. Budget friendly, I'm happy with this .,After a few days, the TV will perform slowly and the remote is very very sentence,thank you amazon and oneplus,1. Sound is good2. Easy installation3. very Slim and less weight4. Voice recognition is good,LikeBudget-friendlyDislikeWiFi connectivity range is poor.Many times gets disconnected.Color depth not that good. | Q59: https://m.media-amazon.com/images/I/512YHGuR4RL._SX300_SY300_QL70_FMwebp_.jpg | R59: https://www.amazon.in/OnePlus-inches-Ready-Smart-Android/dp/B09Q5SWVBJ/ref=sr_1_63?qid=1672909126&s=electronics&sr=1-63
A60: =LEFT(B60,LEN(B60)-1) -> B0B4DT8MK | B60: B0B4DT8MKT | C60: =CONCATENATE(Sheet2!B60,Sheet2!C60) -> WecoolUnbreakable | D60: Computers&Accessories | E60: $348 | F60: $1,499 | G60: 0.77 | H60: 4.2 | I60: 656 | J60: Fast Charging Cable that can be used to charge your smartphone or Tablet or Earbuds or speakers etc...|3 in 1 Fast charging Cable is the best solution for your Travel needs. Just carry a single charging cable that can charge all your electronic Gadgets|The Multi purpose charging cable has 3 charging ports that includes type c cable fast charging 3.0 and Micro usb and charging pin compatible for iphone|The Charging Cable has 12 months of Brand Warranty. Register in the brand website with in 10 days of purchase to avail the warranty. Wecool dot com|Convenient Length cable. The Car charging cable has 1.25 Meters length that is very convenient to use while you travel | K60: AGH3POHLPXABF3I4ASSGTRXAUPPA,AEHVZHMJQYG456XUPYSWK7PWAJAA,AFBPPGDHU5S2IR5WEPYWGR4ABK4Q,AGEYWCB2JWQR7C3RF2SEK26PTK2A,AGWXGUALH6VESAYTZGWBZBUDTWFA,AHCG74BCEDINDMRYYF2QPYY3OHJQ,AHHGEASO3BOC2ET23MDU64DKQ5OQ,AF7TKY6E2EO7NSSPHFYFGE4FJDOA | L60: =CONCATENATE(Sheet4!B60,Sheet4!C60) -> nisarPralipta Kumar Sahoo | M60: =COUNTA(Sheet4!B60:K60) -> 8 | N60: R25WW5K08CGVXV,R1229K72SC8VW6,R3G7X6LSJFGFXP,R19IPICAE9A24Q,R1J0JL7TOG1YNE,R37NLAA34276Y9,R13G1K0IPVB3EA,R188FGJWORTDSC | O60: Nice,Awesome,Quick not chargerðŸ¤,Expensive at this price,Multiple mobile canâ€™t be charged at a time,THIS IS FAST CHARGING ON BOTH MY SAMSUNG PHONES AND IPHONE TOO. Go for it !!,Excellent quality!,CHARGING CABLE | P60: Good,Got a nice product,Quick not chargerðŸ¤,Cable is very good and looks durable but the pins quality are not good, infact iPhone pin keep coming out even with small movement, You can drive and charge simultaneously. Type C is good and the other pin is very hard to insert but workable.,This not a fast charger and canâ€™t be used for data transfer. Multiple mobile canâ€™t be charged at a time,This works as expected. It is working for both my Samsung phones and the lightning cable also works perfectly..,I loved this product for my car. It's long and quite valuable for charging three mobiles together in one go.,GOOD PRODUCT. | Q60: https://m.media-amazon.com/images/W/WEBP_402378-T2/images/I/313uqx3djjL._SX300_SY300_QL70_FMwebp_.jpg | R60: https://www.amazon.in/WeCool-Unbreakable-Charging-Purpose-iPhone/dp/B0B4DT8MKT/ref=sr_1_64?qid=1672909126&s=electronics&sr=1-64
A61: =LEFT(B61,LEN(B61)-1) -> B08CDKQ8T | B61: B08CDKQ8T6 | C61: =CONCATENATE(Sheet2!B61,Sheet2!C61) -> PortronicsKonnect | D61: Computers&Accessories | E61: $154 | F61: $349 | G61: 0.56 | H61: 4.3 | I61: 7064 | J61: MORE DURABLE- Konnect L Micro cable is unique in terms of design and multi-use and is positioned to provide the best comfort and performance while using|HIGH QUALITY MATERIAL- TPE + Nylon material to make sure that the life of the cable is enhanced significantly|COMPATIBILITY- Compatible with most Android smartphones, windows phone, tablets, PC peripherals and other micro USB compatible devices|CHARGE and SYNC FUNCTION- It comes with Fast Charging and quick Sync Function|LONG CORD- The Cable is extra thick 1.2 meter long, optimized for an easy use for your comfort at home or office | K61: AFDCSF36NJYXASQOJCQWFQTN7SDQ,AGHRDOQP7F74DK6KEXSY2NLLKZVQ,AF7HUEJWED3ZUCLTT2MNQDL5BQOA,AH62QNZEYJYC6LNXAJ4BXL6JZZEQ,AFMQH2YLIY5ST5VNIUADLQYIUNAA,AF5TLUDL3JKYZS74QEAMDMPXC3ZQ,AF57UETI4YHWNPSAOF2OVMNVV2JQ,AHNI4LKKPLQLDFCWJZ24SX4BGT7Q | L61: =CONCATENATE(Sheet4!B61,Sheet4!C61) -> Arun S.Jeevan Prasad | M61: =COUNTA(Sheet4!B61:K61) -> 8 | N61: R2ACU430AWSQ15,RZFPMZJQG4VEF,R2P7VTDLLMDOA3,R1B9M17A3N27E2,R4LNZP9RCX3H3,R3TL5BYHCMQSB3,R1B2BRD05LJZX4,R2WQKUAV6WUQ06 | O61: It's working,It's gud ðŸ˜³,Cable quality is good.,Durable and Works Well,Good data cable same as shown in pic,Portronics knonnect L 1.2 mtr Micro USB cable,Ok,Great quality | P61: Working fine,very good this data cable,Performance of this product is good enough.,Have been using it since quite a well. It is doing an excellent job. You can also avail the warranty by just messaging the serial number on whatsapp. Super happy with the overall performance.,Good data cable same as shown in pic. I brought this for my Nikon d5600 photos transfer to system.,Superb product...ðŸ‘ŒðŸ‘ŒðŸ‘Œ,Better,Seems to fast charge at 2A , not tried anything higher, but its a very sturdy cable should last for a long time | Q61: https://m.media-amazon.com/images/W/WEBP_402378-T1/images/I/31pQZsxPR4L._SX300_SY300_QL70_FMwebp_.jpg | R61: https://www.amazon.in/Portronics-Konnect-POR-1079-Charging-Micro/dp/B08CDKQ8T6/ref=sr_1_65?qid=1672909126&s=electronics&sr=1-65
A62: =LEFT(B62,LEN(B62)-1) -> B07B275VN | B62: B07B275VN9 | C62: =CONCATENATE(Sheet2!B62,Sheet2!C62) -> AirtelDigitalTV | D62: Electronics | E62: $179 | F62: $799 | G62: 0.78 | H62: 3.7 | I62: 2201 | J62: This is Generic Airtel Tv Remote|Universal configuration with any TV|Shining black colour with LED indicator | K62: AED54H4JXQGZT6GANH6PJN4SNU7Q,AF652OHBGHAEER2HLOH45T6E65CQ,AFJLA3VGFKFSX3VC6UC4ZAYVR4DQ,AFGQN6RWDATMEVHEO5POPH6VYFRQ,AENYOOBQJZGYT4GNQRR3YEKI7KAQ,AHKZN2KHHR7CQWCGJDX26C5TBHXQ,AHMJ5EEDULQII3FGSNR7PSHQABVA,AEA4764BEJKLL5UEYQ75K6TRRD3A | L62: =CONCATENATE(Sheet4!B62,Sheet4!C62) -> PeriyasamyMadhusudhanan | M62: =COUNTA(Sheet4!B62:K62) -> 8 | N62: R3MXMT6V18JJ1P,R1BQE9L2M5L12J,R369X3BEG4QPC4,R1ZBU0U8R5KBQD,R1A0NYJ6MOX3U3,R3RYEYCYNV47BZ,R28TZ1RZWX14PP,RNGN2ZRL685Z5 | O62: Simple and good,Satisfied!,Good one,Light weight, good working,ok,Poor quality! Stopped working after a month!,Not able to connect,Works well with Airtel DTH | P62: Nice,Works very well with Airtel DTH. The pairing is as same as every Airtel DTH remote. All the buttons works properly.,Nice,Good substitute for original. Nice product,ok,Poor quality! Stopped working in a month,This remote will work only for the new TV and not able to connect even follow all the procedure mentioned on guide.,You need to sync with original tv remote to make volume, power, mute and av buttons work. You can Google the same its very easy. | Q62: https://m.media-amazon.com/images/W/WEBP_402378-T2/images/I/41v00lhhdbL._SX300_SY300_QL70_FMwebp_.jpg | R62: https://www.amazon.in/Airtel-Digital-Remote-Compatible-Recording/dp/B07B275VN9/ref=sr_1_66_mod_primary_new?qid=1672909126&s=electronics&sbo=RZvfv%2F%2FHxDF%2BO5021pAnSA%3D%3D&sr=1-66
A63: =LEFT(B63,LEN(B63)-1) -> B0B15CPR3 | B63: B0B15CPR37 | C63: =CONCATENATE(Sheet2!B63,Sheet2!C63) -> Samsung108 | D63: Electronics | E63: $32,990 | F63: $47,900 | G63: 0.31 | H63: 4.3 | I63: 7109 | J63: Resolution : Crystal 4K Ultra HD (3840 x 2160) | Refresh Rate : 50 Hertz|Connectivity: 3 HDMI ports to connect set top box, Blu-ray speakers or a gaming console | 1 USB ports to connect hard drives or other USB devices|Display: Ultra HD (4k) LED Panel | One Billion Colors | New Bezel-less Design | Supports HDR 10+ | PurColor | Mega Contarst | UHD Dimming | Auto Game Mode|Sound: 20 Watts Output | Powerful Speakers with Dolby Digital Plus | Q Symphony|Smart TV Features : Prime Video, Hotstar, Netflix, Zee5 and more | Voice Assistant - Bixby & Alexa | Tap View | PC Mode | Universal Guide | Web Browser | Screen Mirroring|Warranty Information: 1 year comprehensive warranty plus additional 1 years on panel by brand from date of invoice|Installation: For requesting installation/wall mounting/demo of this product once delivered, please directly call Samsung support on (Visit Brand website for tollfree numbers) and provide product's model name as well as seller's details mentioned on the invoice|Easy Returns: This product is eligible for replacement within 10 days of delivery in case of any product defects, damage or features not matching the description | K63: AHDIDVECFGA6OQRNUBPUO6366UGQ,AFSII6HTAHTHGXERUNDOISNWZUNQ,AF64ON4HPPVD43H6PK3CHPTTYSSQ,AELNBR4H6235Y7NVYNCGNABDIDFQ,AF35OXRSRJ335IGMNW5FYCJDLHOA,AE3CFONNMANNC5QPYIAXV67EUYUQ,AHCWRQHRUAVMTMUH5NYNB3P4NWEA,AGKZVBLHK472MSGAAUABFRZL7SYQ | L63: =CONCATENATE(Sheet4!B63,Sheet4!C63) -> BinuSabjan | M63: =COUNTA(Sheet4!B63:K63) -> 8 | N63: R3RUBB6REUGTT,R281851EB9L5G6,R4ATJJVUY9JO6,R18455FQDOCS3H,RLZ80A5MC1F5G,R2DYRNTDPPD8A5,R3IFT4P8VHQGL3,R1DSJOGV3DFZK2 | O63: Best(Branded) Budget TV,A high-quality 4k Smart TV from Samsung,Received Defective,Got Replacement,Nice product but,Tv is good,Best budget tv,Value for money. Samsung is always good,Value for money product | P63: Before finalizing the AUE60 55", I visited Croma and Vijay Sales to check for the same TV or similar models for their features and picture quality. I was told AUE60 & AUE70(the models listed here as Crystal 4K and 4K Pro) are E-commerce exclusive models, not available offline. I was shown AU7700 which has the same processor, panel and features, but was listed at 65K for the 55" version. I liked the picture quality, and decided I'll get the AUE60 since it shares so much with AU7700, and save ~20k.Why I went for AUE60 vs. AUE70 - I knew I wouldn't be needing a voice assistant, and wanted to save 3k. I knew even if I wanted a voice assistant, I could plug in Fire TV/Mi TV box and get those features later on. Delivery was pretty hassle free, the delivery executive unloaded the TV in the room I asked for, and opened the box to inspect the TV for any physical damages. Samsung technicians came in a few hours later, installed and gave a demo.Sound:Per other reviews - sound from speakers is apparently bad, but in my case, I found it satisfactory. I have it wall mounted in a 10X12ft room, and the TV's speakers sound better compared to Bose Soundlink Speakers that I connected it to via Bluetooth.Picture:The Panel's great, but nothing worth raving about. Gray uniformity isn't great(i.e. gray tones won't be perfectly uniform across the whole panel, there'll be darker zones towards the edges/corners based on backlight placement). Blacks aren't perfectly black - and they're brighter than you'd expect from a VA panel, but this isn't noticeable at all when the room is lit. No backlight bleed. Colors are as good as I'd like them to be, and the panel does get noticeably bright for my taste, even when brightness is turned down to 40%. 720p content is watchable from >8ft, 1080p is good(I'd say better than I expected), and 4K is well, 4K.Connectivity:I have a 35 Mb/s broadband connection and all content streams in 4K when available, without stutters. The TV has Bluetooth 5.0, and works with TWS and Neckband earphones fine(I use Oppo Enco W51 and Boat Rockerz 330) - there's no noticeable latency, and volume can be controlled through the remote itself.Apps & Features:Has all the standard slew of streaming apps I needed - Netflix, Hotstar, Prime, Apple TV+ & YouTube. All of them stream 4k content, except for Hotstar - which only streamed 4K a few times. 1080p is still very watchable, and not really a deal breaker. No Dolby Vision support - which I made my peace with considering the fact that 99% of budget TVs in the market can't produce the contrast you'd expect out of DV content anyways, so why care. You get HDR, and HDR content is definitely better looking than non-HDR ones in terms of colors and vibrancy. I planned to use the TV without cable, but the TV does come with some channels like Republic TV, Bloomberg, 9XM, etc., these stream in 1080p, so a great bonus to have.Remote:Very basic RF remote, unlike Bluetooth ones on most new TVs. The remote's looks pretty sleek and stylish, but that's about it. Biggest gripe - typing to search for things within apps is a pain in the behind, you'll need to use the D-pad to navigate on an on-screen keyboard. You can control the TV using Samsung's SmartThings App, but guess what - you can't even use your phone's keyboard to type in when controlling through the app - this is something that can be added through an update, but it's not there yet.Attached pictures are all of 4K content. Resolution might get scaled down after I submit the review, but you can still get an idea of the TV's design/looks, Panel colors and contrast, etc.I'd say I'm really happy - and given the chance, wouldn't change my decision. It's a Samsung TV, so end of the day, if it produces a decent picture, and lasts a couple of years more than I expect, I can overlook all other cons. I'd highly recommend the TV if you have the same expectations from your next TV.,,Placed order on 18th Dec'22 received Defective product, updated to Amazon service they replaced with new product today(27/12/22).will post long term review.Pros: Picture Quality, Design (thin n Bezel less)Cons: Sound (bit okay),upsacling of SD channelsOver all Satisfied.,Have been using it since month now.-Picture quality is amazing. 4.5/5-As always installation service from Samsung was seemless. 5/5-smart features are good this model don't have voice recognition. I don't require it so its fine. 4/5-Audio quality is not good. It's clear but loudness is not sufficient if installing in big hall. It also lacks base.Purchase a sound bar separately if buying this model.,But the picture quality is ok-ok.,Best tv product in given price range,Value for money. Samsung is always good,Value for money product | Q63: https://m.media-amazon.com/images/I/41Tz1YnJkoL._SY300_SX300_QL70_FMwebp_.jpg | R63: https://www.amazon.in/Samsung-inches-Crystal-Ultra-UA43AUE65AKXXL/dp/B0B15CPR37/ref=sr_1_67?qid=1672909126&s=electronics&sr=1-67
A64: =LEFT(B64,LEN(B64)-1) -> B0994GFWB | B64: B0994GFWBH | C64: =CONCATENATE(Sheet2!B64,Sheet2!C64) -> Lapster1.5 | D64: Computers&Accessories | E64: $139 | F64: $999 | G64: 0.86 | H64: 4 | I64: 1313 | J64: Plug & Play|Stable & Reliable Connectivity.|Special grip treads designed on wire ends for easy plugging and unplugging; plug-and-play.|Connector : USB 2.0 Type A Male to Type A Male|High quality USB 2.0 high speed cable. Usually used for some external drive enclosures or cameras.|Compatibility with USB 1.0,1.1 , Supporting data transfer rate at up to 480Mbps|High quality thin USB type A adapter M/M is designed for Data Transfer and fast Charging, ideal for hard drive enclosure, printer, modem, scanner, camera etc. Interference Free | K64: AF42EMTPEJAL4LNEPPX77TN77UHA,AHBMZRY43T2GTYDVNFMUVASIBTPA,AECCRE6ZTCPFGPVWDNY3IYYHCMOQ,AHOURK4XKLPPC4VHEDJ25NP64NPQ,AFC5K7RQQYKFB5PV47KAX2CHVIIQ,AHEVOBT5PFXMIS5A7GAXRG52XARQ,AHNOMOD65QU6QKFP3AMH5QPGQO6A,AGN2VH6RTYG5CM3YVH34VGYJFO4A | L64: =CONCATENATE(Sheet4!B64,Sheet4!C64) -> pruthvi natrajPhani | M64: =COUNTA(Sheet4!B64:K64) -> 8 | N64: RZJR37WFGXR9B,R39X6O18GM16TM,R18ZQ09EKVWZ9R,R3NHUC9S00KIR8,R30ZSNYE78E0O2,R2LVRBREQ4EFDM,R1UJ8BCYXWICT8,R34RH86MGL4HFB | O64: A well-priced product.,Lenthy cord.,Product is working as expected.,Lengthy cable, works for car dashcam,Product is okay but they give 50rs for giving 5 stars.,Misleading length (1.2m), rest fine,Good Product,Good | P64: i am writing this review after 2 months, the first cable had a cut and had to be replaced, the second cable is working fine, no issues, using it to charge me PS3 controller, works fine, at a good price, planning to pick up another one as a spare.,Product OK.,I bought this cable to charge my 10w Bluetooth speaker and its working as expected.,It's lengthy and usable for car dashcam.Quality is average and micro type B end does sit very tight.Otherwise, it's all good.But keep checking price of amazon basics cable of this type , price drops many times. That's better quality.,This is one of the good product in this price range. Quality is okay,Using it for my laptop cooling pad. Overall build looks sturdy, but longevity cannot confirm. Also, YOU CANNOT CONNECT 2 PCs USING A MALE TO MALE USB. THAT IS NOT HOW IT WORKS. Stop writing negative reviews after using this cable for something that it was NOT intended for.Can confirm that it is ~1.2m as most other products and not 1.5m as the seller claims both in title and on stickers on the product.No review mentions this. But I needed a 1.5m length for perfect use. So disappointed as I have to rotate the cooling pad and use it (cable falls short by around 15cm).,It works well. The cable is soft and flexible. In all probability, it will last long also.,But pover quality | Q64: https://m.media-amazon.com/images/I/310WOJIrwjL._SX300_SY300_QL70_FMwebp_.jpg | R64: https://www.amazon.in/Lapster-Type-Cable-computer-laptop/dp/B0994GFWBH/ref=sr_1_68?qid=1672909126&s=electronics&sr=1-68
A65: =LEFT(B65,LEN(B65)-1) -> B01GGKZ0V | B65: B01GGKZ0V6 | C65: =CONCATENATE(Sheet2!B65,Sheet2!C65) -> AmazonBasicsUSB | D65: Computers&Accessories | E65: $329 | F65: $845 | G65: 0.61 | H65: 4.2 | I65: 29746 | J65: Connect Usb Type-C Enabled Devices (Macbook, Chromebook Pixel, Galaxy Note 7 Etc.) With Standard Usb Type-C 2.0 Enabled Devices And Accessories (Smartphones, Car/Wall Charger, Multi-Port Adapters Etc.)|1 Year Limited Warranty|Up To 480 Mbps Data Transfer Speed; Power Output Up To 5V, 3 Amp|Certified By Usb-If To Be Compliant With Usb 2.0|Type-C Port Is Half The Width And One-Third The Height Of A Standard Usb-A Connector (Slightly Larger Compared To Lightning Or Micro-Usb Ports)|Ideal For Charging And Powering Usb Type-C Enabled Devices, As Well As Syncing Data, Photos And Music|Reversible Design - Easily Insert The Connector Into Any Type-C Enabled Device (Does Not Matter Which Side Is Up) | K65: AEITVIFC7WZAEQDIVWPB4KUGKLRQ,AHQVFZCGAMMHEBBOY4SXBSRF3ZDQ,AECB6RAIS3NCSRCNMUWNZAQARNMA,AE43KS43Y6L62UBGG6K64AD5OISA,AGCBWB4YSTCDFAERTYIJ52KVW6EQ,AGPWASWUND4PQYWAP6ICZEPQCWZA,AFHT4L657CBTBKZ2UZEYQBAROXNA,AFQEZSS2I5IGAKZY3Y3CGDZLCJIA | L65: =CONCATENATE(Sheet4!B65,Sheet4!C65) -> harpreetY Kiran Korneli Reddy | M65: =COUNTA(Sheet4!B65:K65) -> 8 | N65: R37S13YALMRPGK,R2OU2YTGFEMJHE,R25SDG11W8EAU9,R2W38EQOY97N87,R2U8MOGE4JDKBF,R2CN3CX7SGEWDK,RX74XLMFH35PD,R1B861YJE8YL2B | O65: Its ok product not too good not bad,Cheap and best,Performance,Works well,Not working with Fast Charger,This Type-C cable is awesomeðŸ˜.,Does not support display,Good | P65: Not too good not too bad,If you have the trust of Amazon basics then go for it. I am writing this review after using it for 18 months. Still as sturdy and durable as the new one.,Nil,Used it for a fortnight till now in my car for mobile charging. Works well.,Not working with Fast Charger , if you are planning to use with normal charger , its pretty good . Product quality too its GOOD.,I'm using this cable since 1 years and currently this cable is running perfectly without any problems.If you want to buy best type-c cable then without thinking buy it.,Does not support display only work to connect network and charging,Good and useful | Q65: https://m.media-amazon.com/images/W/WEBP_402378-T2/images/I/414y0iu5NUL._SX300_SY300_QL70_FMwebp_.jpg | R65: https://www.amazon.in/AmazonBasics-USB-Type-C-2-0-Cable/dp/B01GGKZ0V6/ref=sr_1_69?qid=1672909126&s=electronics&sr=1-69
A66: =LEFT(B66,LEN(B66)-1) -> B09F9YQQ7 | B66: B09F9YQQ7B | C66: =CONCATENATE(Sheet2!B66,Sheet2!C66) -> Redmi80 | D66: Electronics | E66: $13,999 | F66: $24,999 | G66: 0.44 | H66: 4.2 | I66: 45238 | J66: Resolution: HD Ready (1366 x 768) | Refresh Rate: 60 hertz | 178 Degree wide viewing angle|Connectivity: 2 HDMI ports to connect set top box, Blu-Ray players, gaming console | 2 USB ports to connect hard drives and other USB devices | 3.5mm to connect your headphones | Bluetooth 5.0 to connect Bluetooth speakers, earphones and TWS earphones|Sound: 20 Watts Powerful Stereo Speakers | Dolby Audio | DTS Virtual: X and DTS-HD | Dolby Atmos pass through ARC port|Smart TV Features : Android TV 11 | Chromecast built-in | PatchWall 4 with IMDb integration | Kids Mode with Parental Lock | 75+ Free Live Channels | Universal search | Language Universe (16+ Languages) | India's Top 10 | Miracast | Supported Apps: Prime Video | Netflix | Disney + Hotstar | YouTube | Apple TV | 5000+ apps from Play Store | Auto Low Latency Mode | Quad core processor | Dual band Wi-Fi | 1GB RAM + 8GB Storage|Display: A+ Grade LED panel | Vivid Picture Engine | Detailed Picture Controls | Ultra bright screen | Dynamic contrast | Dynamic backlight|Warranty Information: 1 year comprehensive warranty on product and 1 year additional on Panel provided by the brand from the date of purchase|Easy Returns: This product is eligible for replacement within 10 days of delivery in case of any product defects, damage or features not matching the description provided|Video capture format :avi, mp4,Included components :1 led tv, 2 table stand base, 1 user manual, 1 remote control, 4 screws,resolution :720p | K66: AG6WSLLXZY52HSQUY5PRCXTCYQYQ,AHGJ2DNFP3OJWO73XW2R7TDXI7WA,AGIC6PASSVB4T3KTZHK6ADD23GCA,AH4TEK5IQCC2BSF2KSQNKQEXAPLA,AFJIYRZTBOJBOWYQ5RNA36DBBXOA,AGCRWRS4RJYVGVKINV3VAR4CGDWA,AEGPWBXEAWPF6XRT7EZJOYJQA6DQ,AF5BU6DZ446HN4DTCO7W7AWXBJBA | L66: =CONCATENATE(Sheet4!B66,Sheet4!C66) -> prateeqSuraj Chand | M66: =COUNTA(Sheet4!B66:K66) -> 8 | N66: R3CR9H6ABJ4Q4O,R2S5VBYYN51ELA,R1U0718A15KBBU,R9YRKNJ667H1E,RAWMG4UI4CZD3,R877Y6K5MW32G,RC458V57ETXDN,R2VOHT3T6361C5 | O66: Worth the price,Mi Smart Tv 32" :- 7/10 average.,Worth using since 1.5 years,expect more from mi,Worth for money.,Good product,Itâ€™s good,Go for it without thinking twice. | P66: Worth the price. I use the local cable providers set up. With my previous tv (Samsung) I was not facing this problem. The only problem I am facing is each time I turn off the tv from the mains, I have to go to the settings and turn the settings on to tv speaker settings despite no other speaker or WiFi or blue tooth or cell phone being in the proximity. As a result I have stopped turning the tv off from the mains. I just use remote control to put it on stand by. BUT THIS IS A PROBLEM IN THE LONG RUN,,Display is very good. Sound is average iam using soundbar so no issues for me. Don't know how long it will last due to my previous mi 55 4 pro panel gone in 2.5 years. Bought this tv with 2 year warranty on panel.,improve the software response and improve the picture quality. worth for money for this budget (4K).,I have used 2-4 days. Picture quality looks good and impressive. Go for it..Hope long-term quality is also good.,This tv is very good but in this one thing bad is tha this tv some time get stop while playing only YouTube video but otherwise it's a good product,Itâ€™s good and value for money,Amazing pic and sound quality. 4K quality at this price. It's really good . | Q66: https://m.media-amazon.com/images/W/WEBP_402378-T2/images/I/41611VFTGwL._SY300_SX300_QL70_FMwebp_.jpg | R66: https://www.amazon.in/Redmi-inches-Ready-L32M6-RA-Android/dp/B09F9YQQ7B/ref=sr_1_72?qid=1672909126&s=electronics&sr=1-72
A67: =LEFT(B67,LEN(B67)-1) -> B014I8SX4 | B67: B014I8SX4Y | C67: =CONCATENATE(Sheet2!B67,Sheet2!C67) -> AmazonBasics | D67: Electronics | E67: $309 | F67: $1,400 | G67: 0.78 | H67: 4.4 | I67: 4,26,973 | J67: HDMI A Male to A Male Cable: Supports Ethernet, 3D, 4K video and Audio Return Channel (ARC)|Connects Blu-ray players, Fire TV, Apple TV, PS4, PS3, XBox one, Xbox 360, computers and other HDMI-enabled devices to TVs, displays, A/V receivers and more|Cable allows you to share an Internet connection among multiple devices without the need for a separate Ethernet cable|Meets HDMI 2.0 standards (4K Video at 60 Hz, 2160p, 48 bit/px color depth) that supports bandwidth up to 18Gbps and backwards compatible with earlier versions|Note: Supports Max resolution of 4K@60Hz, for display issues downgrade resolution & gradually increase resolution for compatibility/display issues.|Cable Length: 6 feet (1.8 meters) - 2 units; 1 year limited warranty | K67: AEYJ5I6JZZPOJB6MGWRQOHRQLPSQ,AFY5TVFOMVHGBPBTIJODYDQRZM5Q,AE3O6366WGEQAANKJ76QETTUQQTQ,AEQIJCPWSBCDKUO5VROXXHWX3PPA,AGVIAQK2HQ47P7UVXHW2NBAEU7YQ,AE3D5CJ2GDUP5SQ3AAYMVAGDTX7A,AH77IQRYD54XCRMCO7XEAIAYCLPA,AEA2HQHMFG3ZGJFOLLJQ65WKIZUQ | L67: =CONCATENATE(Sheet4!B67,Sheet4!C67) -> Rishav GossainShashank Mallamraju | M67: =COUNTA(Sheet4!B67:K67) -> 8 | N67: R1FKOKZ3HHKJBZ,R2WNMZI1EXTA0H,RCA1M3W4RIXUR,R3BKCLL6D7ZLIX,REVSR0ILY3547,R15W5KMQB95IV5,R10PB68FRUHT5V,R3TLCE9JSBU3UP | O67: It's quite good and value for money,Works well,Hdmi cable,Value for money,All good,Gets the job done,Delivery was good,This one was my need to purchase | P67: I am using it for 14 days now. The experience is pretty good as of now. Picture quality is also not bad. Don't expect something out of the world at this price point. But you can go for it if you have a tight budget.,Initial impressions: works as said, glad I didnâ€™t go for cheaper options (not that itâ€™s too costly) just plug and play. Will update if it screws up,The hdmi cable is good to watch movie,sports and its gives better quality while connecting your laptop with TV and play ðŸŽ®.I loved it,Works as expected. Length of the cable is short and it was mentioned also satisfied my requirement. If you need more length better look other options.,All good,It's the best HDMI cable at this price range. No problems yet. Just go for it !!,I was expecting this to be delivered on time and it was delivered on time.Product is good as i have tried other cables and wires from Amazon basica brand.,Good one | Q67: https://m.media-amazon.com/images/I/41eJqkFjCRL._SY300_SX300_QL70_FMwebp_.jpg | R67: https://www.amazon.in/AmazonBasics-High-Speed-Cable-2-Pack-Black/dp/B014I8SX4Y/ref=sr_1_73?qid=1672909128&s=electronics&sr=1-73
A68: =LEFT(B68,LEN(B68)-1) -> B09Q8HMKZ | B68: B09Q8HMKZX | C68: =CONCATENATE(Sheet2!B68,Sheet2!C68) -> PortronicsKonnect | D68: Computers&Accessories | E68: $263 | F68: $699 | G68: 0.62 | H68: 4.1 | I68: 450 | J68: [1.2 M LONG DURABLE CABLE] : The Konnect L is about 1.2 M long and this feature allows for maximum convenience of the user. Not only is the cable length ample it also is durably built which ensures that no matter how roughly its handled no harm is done to it!|[20 W PD QUICK CHARGE FOR 8 PIN USB] : The Konnect L cable for 8 pin USB is an efficient cable for Apple smartphones charging and is as powerful as its Apple counterparts. You can plug in your smartphone for lightning speed charging!|[TPE & NYLON BRAIDED CORD] : The cable has been designed for optimal results and keeping this in mind it has been built with TPE and has further been nylon braided to ensure longevity and safe upkeep.|[TANGLE RESISTANT] : Isnâ€™t it frustrating when we are in a hurry to charge our devices, and while pulling out the charger find it all entangled up? This is why we came up with this feature that will not only make charging hassle free but also ensure the cableâ€™s longevity.|[FAST DATA SYNC] : Sync data from two devices with accuracy and ultra speed. The cable allows zero glitches and ensures distortion free exchange of data. You can use the cable to transfer large amounts of data continuously from one device to another! | K68: AF6SKHWKK53BMAI6UVJA5FJMLK3A,AHIWSTMUSIYZAZQAMOLMPJHR7NMA,AHYDC5KBSNP2LD5ZV5SXO3CQSCDQ,AGACLGW4IBQOHLA6UJBIUNGVBRMQ,AGFX4BFHOC6FXDFPD2O24RCD32NQ,AGMXX5UGO3VXFAN2HOVYOWQYTRYA,AGNGZAPY5HMB7OOQAXQ3MH5OLVSA,AHR4VQLVSWORK3A35U3QA6IOEEBA | L68: =CONCATENATE(Sheet4!B68,Sheet4!C68) -> Thenmozhimanish | M68: =COUNTA(Sheet4!B68:K68) -> 8 | N68: R1LG3XV2XYCQQB,RPVNHPEU1HG9F,R1MD4LW015PP00,R5RCZRA2XSJVU,R1TPVT7TXNNW2,R1GYI0Y69RU13,R3S5U7BJ1KTKAU,R3F02OAHFU646V | O68: Iphone User,Overall good,Perfect price, perfect fit,Good,Worth,Perfect replacement for Apple cable,At this price it's a steal.,Good cable with decent price | P68: Good braided cable. Long length. Quick charge. I m using XR. This cable value for money. But chager apple OEM. Portronics type c to lighting cable worth.,Itâ€™s easy to carry and the build quality is quite ok charging speed to almost equal to original oneGiving this review after 1 month usage,Great fit connector, l shaped connectors are convenient and better than some higher priced products.,good,Best product at this price range go for itðŸ”¥ðŸ”¥ðŸ”¥ and the software shows product will be genuine ðŸ”¥ most recommended braided cable for ï£¿ products,Wish apple made this product as it is easier to hold the phone while charging,Superb quality and supports good charging speeds. Type c to lightning 20w at this price (250Rs) is a steal deal. Nobody is giving this quality at this price,Good cable available at a decent price of Rs. 312.ProsGood design.L shaped connectors will help keeping phone and power bank together in bag or pocket without causing and damage to the charging pins.Does fast charging and compatible with all fast charging power adapters. | Q68: https://m.media-amazon.com/images/I/41x3iKbD-+L._SX342_SY445_.jpg | R68: https://www.amazon.in/Portronics-Konnect-Charge-Charging-Resistant/dp/B09Q8HMKZX/ref=sr_1_74?qid=1672909128&s=electronics&sr=1-74
A69: =LEFT(B69,LEN(B69)-1) -> B0B9XN9S3 | B69: B0B9XN9S3W | C69: =CONCATENATE(Sheet2!B69,Sheet2!C69) -> Acer80 | D69: Electronics | E69: $7,999 | F69: $14,990 | G69: 0.47 | H69: 4.3 | I69: 457 | J69: Resolution: HD Ready (1366 x 768) | Refresh Rate: 60Hz | 178 Degree wide viewing angle|Connectivity: 2 HDMI Ports to connect set top box, Blu Ray players, gaming console | 2 USB Ports to connect hard drives and other USB devices | 1 VGA Slot to connect your Laptop/PC | 1 Headphone Jack | 2 AV Input Slot | 1 RF Slot|Sound: 20 Watts Output|Display: High Definition | Dynamic Contast | Intelligent Signal Calibration | 16.7 Million Colours | Digital Noise Reduction|Warranty Information: 1 year comprehensive warranty provided by the manufacturer from date of purchase|Installation: Installation/Wall mounting/demo will be arranged by AHS Team. For any other information, please contact Amazon customer support|Easy Returns: This product is eligible for replacement within 10 days of delivery in case of any product defects, damage or features not matching the description | K69: AFXQSBDW6232K22UMJWF5PMYX5RQ,AG4IENR3HNMEINBTJS3PET6VQY3Q,AEYIYXI67FZ3H57OBTA2BGZBGTHQ,AFUSP4NL7DIIS7CADTLDHGFLNOMQ,AEJG6XAZFMVQ7NRKCXG3ZCC3DIVA,AFIS3N547NISE4TGX3YU6F4X2AGQ,AGIJM2HE6GKI3I75OJ7PODHPP67Q,AGNXWXFWLOYZAYJ5PRIM2NB57E4A | L69: =CONCATENATE(Sheet4!B69,Sheet4!C69) -> ARUN KUMAR A VAnkesh kumar pandit | M69: =COUNTA(Sheet4!B69:K69) -> 9 | N69: R3FTW5HNPCX66C,RM7IFDV9KNC2O,RK9JKA9U9LZ49,R15UN38LGPS71W,RCBVF30PUU6UT,R1I75CYBWWYB2G,R2Z5R4CWX4B3KB,RX4O8WQ6VY2AS | O69: Value for Money,Good product,Great excellent picture quality,value for money,Worth for the money,Good,100% Value for money,Value for money | P69: Regarding rate I liked very much and reasonable. Regarding the product Acer Company is manufacturing Computer Monitor and are best in quality. So that, I prefer this company in buying TV,Its been 1 and half month using this product and have no complaint regarding the product some of its plus points are.1. Picture quality is good with clear sound quality2. We can easily connect any pan drive or otg to this Tv and access your content in tv.And Points in which it need improvement:1. Its does not support some audio format that.2. If we connect smartphone through OTG to TV it doesn't support the same3. Also we always have to use TV remote to start the TV. It doesn't start automatically when we on the swith, we have to press power button on remote each time to start this TV.Overall a very good product.,Picture quality is very good ðŸ˜Š,Bought this TV on amazon sale, value for money at this price, the picture and sound quality was okay, not that bad. If you want to buy a 32'' TV at an affordable price then go for this one.,Nice,Good,I purchased this tv two days before and now it's running. I observed the followings towards my experience.1. 100% value for money2. Good design and finish3. Great picture clarity. I am using Jio Fiber + Netflix4. Sound Also clear and smooth but little Bit improvement needed.5. Package packed well as advertised. Remote + Batteries + AV wire + warranty Card + Manual.6. Promptly Delivered. 0 damage.7. Refresh Rate is 60hzOverall Recommended.,Picture quality is good.sound also good.value for money. One can purchase at low price. | Q69: https://m.media-amazon.com/images/I/51FicDnawaL._SY300_SX300_QL70_FMwebp_.jpg | R69: https://www.amazon.in/Acer-inches-Ready-AR32NSV53HD-Black/dp/B0B9XN9S3W/ref=sr_1_75?qid=1672909128&s=electronics&sr=1-75
A70: =LEFT(B70,LEN(B70)-1) -> B07966M8X | B70: B07966M8XH | C70: =CONCATENATE(Sheet2!B70,Sheet2!C70) -> Model-P46 | D70: Electronics | E70: $1,599 | F70: $2,999 | G70: 0.47 | H70: 4.2 | I70: 2727 | J70: Full motion cantilever mount|Fits 32inch-55inch flat panel display|Vesa compliance 100x100 to 400x400mm | K70: AGZU6C2XL3X2B4NEWLQJDSJ75QGA,AHY62YAUHMMGFKSBGCECVGKXY2UQ,AEMGDIDXCHHDMTAJHRNXBUWISFQQ,AHQNYNRXESALGWMUFS6ITFGOVGMQ,AH7GOHZT6M5G6ELWPDTVZVKRZ7ZA,AEHIRIOGHJKVTFYHFZVQ322CMZMA,AFUU5Q42TD7WLXRGKOBMRGUZWRFQ,AFUV6WMMWSY6UM3P6ATQ6SME3H7A | L70: =CONCATENATE(Sheet4!B70,Sheet4!C70) -> Prashant PradhanRaghavendra Shetty | M70: =COUNTA(Sheet4!B70:K70) -> 8 | N70: R9GNL4OF49DH6,R2I0MJPJI6FOIE,R732VQVZLKUGL,R3L55JQKYQUMNC,R2MN9LXLLTNJ58,RY71WCYL05RXL,RPFUVX3Z31TRO,RO7LRFL67Z505 | O70: A nice & sturdy product.,Assembly,nyc hairdryee,Good,Fits perfectly!!,Not suitable for 50inch and above ðŸ˜Ÿ,Worth buying,Worth | P70: Its a good product. Used for 42 inch TV, had to get it installed by a TV mechanic.,Gud for 40inch above tv,best,Awesome,Nice and sturdy!!The quality of the product is outstanding.,The Stand is not suitable for 50inch and above.,Arrived in good condition. Quality of mount is excellent, heavy and sturdy. It has paper manual, with clear steps and tools required for installation. Installation was easy and quick. Happy with this purchase.,55inch to can handle this | Q70: https://m.media-amazon.com/images/I/41+mgWz7knL._SX300_SY300_.jpg | R70: https://www.amazon.in/Model-P4-Swivel-32-55-inch-Motion-Cantilever/dp/B07966M8XH/ref=sr_1_76?qid=1672909128&s=electronics&sr=1-76
A71: =LEFT(B71,LEN(B71)-1) -> B01GGKYKQ | B71: B01GGKYKQM | C71: =CONCATENATE(Sheet2!B71,Sheet2!C71) -> AmazonBasics | D71: Computers&Accessories | E71: $219 | F71: $700 | G71: 0.69 | H71: 4.3 | I71: 20053 | J71: Connect USB Type-C enabled devices (MacBook, Chromebook Pixel, Galaxy Note 7, etc.) with standard USB Type-A enabled devices (laptops, hard drives, power banks, wall/car chargers, etc.)|Ideal for charging and powering USB Type-C enabled devices, as well as syncing data, photos and music|Reversible design - easily insert the Type-C connector into any Type-C enabled device (does not matter which side is up)|Type-C port is half the width and one-third the height of a standard USB-A connector (slightly larger compared to Lightning or Micro-USB ports)|Up to 480 Mbps data transfer speed; power output up to 5V, 3 Amp|Certified by USB-IF to be compliant with USB 2.0 Standard | K71: AHVZCQP5SYIVGZJK4LRP55ZXWETA,AF6YDBL3KYIK3LBKKDIHUMOLKN4Q,AHKL2U5BIK4ZODWORRJ5RWNLL2TQ,AFKZHMXRXMRTVZLMHATTD53AVKRA,AGFTWXF3QWIHMPN7SMTSHB6HNJ7Q,AE4G376L73UNPWICYOSYO2KNXYJA,AHGFA5MNVOFDMIL3322YZ6IOA5VA,AGUR3CFYVZUMDJQIESKOIQOGV7AA | L71: =CONCATENATE(Sheet4!B71,Sheet4!C71) -> HremantAnjaneyulu | M71: =COUNTA(Sheet4!B71:K71) -> 8 | N71: R1BC08IFG4REKS,R1FJKIHIO54SOW,R3JR48W2CI480,R3JH7SHSXDT1GT,R35QWAY83WL8H6,R25N2U90N2A5AS,R19AK3DT3JOE82,R210WJI15JCSRE | O71: You can trust on this one,The best usb cable,Wel build just like original .,Nice!!,Working perfectly,Basic,Good,No issues | P71: Previously bought amazon basic USB type A cable and i didn't last long, but this USB C product seems manufactured with high quality materials. Supports fast chagrining, data supply etc. just go for it,Exllent,Very satisfied with this purchase, just like orginal quality . Will buy again in future .,My sister is using this cable to charge her phone and the cable is durable and good enough for my sister's phone. Love it!!,I bought it to use Android Auto on Tata Altroz car by connecting to my one plus nord 2T mobile.I have been using this for more than a week now. It's working perfectly..I am happy with the product so far.,Basic,Great product money worth,No issues | Q71: https://m.media-amazon.com/images/W/WEBP_402378-T1/images/I/31-BRsjrvDL._SY300_SX300_QL70_FMwebp_.jpg | R71: https://www.amazon.in/AmazonBasics-Type-C-USB-Male-Cable/dp/B01GGKYKQM/ref=sr_1_77?qid=1672909128&s=electronics&sr=1-77
A72: =LEFT(B72,LEN(B72)-1) -> B0B86CDHL | B72: B0B86CDHL1 | C72: =CONCATENATE(Sheet2!B72,Sheet2!C72) -> oraimo65W | D72: Computers&Accessories | E72: $349 | F72: $899 | G72: 0.61 | H72: 4.5 | I72: 149 | J72: ðŸ¥‡ã€Kindly NOTE before you purchaseã€‘:This is a USB-C to USB-C cable, which means it has the same USB C or Type C plug on both sides, please keep a note that this cable is not a USB-C to USB-A cable. Besides, you may need a USB C wall charger to charge your device. This product DO NOT support video output and monitor connection.|ðŸ¥‡ã€65W High Speed Chargingã€‘: Build-in updated smart chip, which makes this USB-C to USB-C PD cable strong enough to support max 3.25A current 65W power through, as well as support fast charging for more Type-C devices. You need a USB C wall charger for your device to charge and we would like you to recommend to use the original wall charger.|ðŸ¥‡ã€Compatible Devicesã€‘:This USB C to USB C cable compatible with Samsung S20, S21 Ultra, A71, laptop Macbook, Samsung S21 S22 S20 FE 2022 A71, A51, A33, M51, M31, M31s, M33, M53, Macbook Air, Macbook Pro, Macbook Air M1|ðŸ¥‡ã€Military grade materialã€‘:Strong military fiber, the most flexible, powerful and durable material, makes tensile force increased by 200%. Special Strain Relief design, can bear 10000+ bending test. Premium Aluminum housing makes the cable more durable|ðŸ¥‡Warranty: Oraimo offer 365days warranty .Oraimo develops cool and creative smart accessory for young people around the world, enableing them to explore more excitement. | K72: AEOIHOJD3O5MYSVWZOBDUJGYWZGQ,AF6LAYTAGSTBKL2QUF3WFB6OMCPQ,AHKXH7KSF7CPJCJMHB6B35VPTETA,AFELQLNWTS4QJNCCA4ZDTWHVORJQ,AGGE54AKRMX2XMQWQQTSUOPL7CHA,AG7ZAJNX4XZ5LTA4NLWBHTCX2V5A,AGYSVNZMQT5LOVKHSCYDE7OAPKVA,AHAI6EM7F7W3GV3SUIDSKWTBJOSA | L72: =CONCATENATE(Sheet4!B72,Sheet4!C72) -> Ravi ShankarPrakash Luhariya | M72: =COUNTA(Sheet4!B72:K72) -> 8 | N72: RDFETF8YFDP96,R3604ERFM30Q4D,R1CB3GDRVBHAIG,R29H4558OA57RW,R2C4V03DG7EDWE,R20CNK6VJGER17,RXZLH38FGBU9K,R3E6TE6HH92GC3 | O72: It worked well for some days later it is not working , I want it to replace.,Extremely fine,Superb product,This is very decent, quality is super good!,Good,Awesome Product Quantity & Value For Money,Go for it..,Be(a)st in the market. | P72: It worked well for some days later it is not working , I want it to replace.,Nice,Superb product with white lights at both ends when charging. colour and quality feels very premium..,https://m.media-amazon.com/images/I/81u-AB650VL._SY88.jpg,Good,Good Build Quality. Nice Product & Highly Recommended.,Good quality and looks beautiful... I will surely recommend,( After using it for 3 weeks). I use Samsung M51, few months back my USB Cable was torn, so I wasn't able to fast charge. It took a decade to charge from 20-90%. Samsung original cable was too pricey and too flimsy, so I was searching for something durable. While browsing through the product page I was skeptical to place an order, as the company claimed too many features in such a low price. Keeping the negative thoughts aside I ordered it anyhow. The product was delivered well in advance, which made me happy.I unboxed and plugged in the cable, to my surprise the cable delivered everything that the company claimed. The ends have aluminum casing which makes it durable and away from regular wear and tear, it has LED indicator on both ends which turns on when the charger is plugged to the phone. Also, the box that it comes with has a secret code that you need to scratch to reveal which helps to check its authenticity.It easily fast charges my phone in an hour. Overall, I'm very happy with the product.I highly recommend this cable to anyone who needs a fast charging Type C to C cable.Will update this review if any change is observed. | Q72: https://m.media-amazon.com/images/I/41gztmbiIgL._SX300_SY300_QL70_FMwebp_.jpg | R72: https://www.amazon.in/oraimo-Charging-Syncing-Indicator-Compatible/dp/B0B86CDHL1/ref=sr_1_79?qid=1672909128&s=electronics&sr=1-79
